Workbook
Name В11: Накладная!$A$12
Name В22: Накладная!$A$62
Name Значение: #REF!
Name Значение: #REF!
Name Значение: #REF!
Name Обвязочныйбрус: #REF!
Name Обвязочныйбрус: #REF!
Name Обвязочныйбрус: #REF!

Sheet Прайс
A1: Наименование работы | B1: Ед.измер. | C1: Характеристика | D1: Себ-ть,руб. | E1: Розница,руб
A2: Фундаменты
A3: Ленточный фундамет
A4: Выемка грунта вручную | B4: м3 | D4: 1000 | E4: 1200
A5: Выемка грунта механизировано | B5: м/ч | C5: мин 4 часа | D5: 1250 | E5: 1500
A6: Кирпич красный м 200 | B6: шт | D6: 30 | E6: 36
A7: Кирпич красный м 150 | B7: шт | D7: 20 | E7: 24
A8: Кирпич белый | B8: шт | D8: 16 | E8: 19.2
A9: Пленка (150 мк) | B9: м2 | D9: 15 | E9: 18
A10: Песок | B10: м3 | C10: 1,67т | D10: 667 | E10: 800.4
A11: Щебень(гранит 20 на 40) | B11: м3 | C11: 1,35т | D11: 1553 | E11: 1863.6
A12: Щебень (известняк 20 на 40) | B12: м3 | C12: 1,3т | D12: 476 | E12: 571.2
A13: Бетон | B13: м3 | C13: м 200 | D13: 3500 | E13: 4200
A14: Арматура( 8) | B14: п.м | D14: 15 | E14: 18
A15: Арматура( 10) | B15: п.м | D15: 19 | E15: 22.8
A16: Арматура (12) | B16: п.м. | D16: 25 | E16: 30
A17: Арматура пластик( 6) | B17: п.м. | D17: 10 | E17: 12
A18: Арматура пластик(8) | B18: п.м | D18: 15 | E18: 18
A19: Арматура пластик(10) | B19: п.м | D19: 22 | E19: 26.4
A20: Арматура пластик(12) | B20: п.м | D20: 30 | E20: 36
A21: Вязальная пров-ка | B21: кг | C21: min 3 кг | D21: 90 | E21: 108
A22: Опалубка | B22: м3 | C22: доски 2 сорт | D22: 4000 | E22: 4800
A23: Опалубка 1250Х2500х12 | B23: 1 шт | C23: OSB (3.125) | D23: 700 | E23: 840
A24: Аренда мотобура(для свай) | B24: сутки | D24: 5000 | E24: 6000
A25: Аренда буромашины(для свай) | B25: час | C25: min 4 час | D25: 1600 | E25: 1920
A26: Блочный фундамент | E26: 0
A27: Блок | B27: шт | D27: 41 | E27: 60
A28: Смесь М 150 | B28: меш | C28: 25 кг | D28: 90 | E28: 108
A29: Рубероид | B29: шт | C29: 1000 Х15000 | D29: 350 | E29: 420
A30: Свайно-винтовой | F30: Цена работы
A31: Керамзитобетонный блок | D31: 41
A32: Свая 2000 | B32: шт | C32: 1,5 меш.смеси | D32: 1400 | E32: 1680 | F32: 800
A33: Свая 2500 | B33: шт | C33: 2 меш смеси | D33: 1500 | E33: 1800 | F33: 800
A34: Свая 3000 | B34: шт | C34: 2,5 меш.смеси | D34: 1700 | E34: 2040 | F34: 1000
A35: Увеличение длины сваи | B35: 1 м.п. | D35: 250 | E35: 300 | F35: 100
A36: Укосины по сваям с грунтом | B36: 1 м.п. | D36: 250 | E36: 300 | F36: 150
A37: Обвязка швеллером 16 с грунтом | B37: 1 м.п. | D37: 600 | E37: 720 | F37: 300
A38: Пиломатериал( 6 м)
A39: 200Х200 | B39: шт | C39: 6500 | D39: =C39*0.2*0.2*6 -> 1560 | E39: =D39*1.2 -> 1872
A40: 150Х200 | B40: шт | C40: 6500 | D40: =C40*0.2*0.15*6 -> 1170 | E40: =D40*1.2 -> 1404
A41: 100Х200 | B41: шт | C41: 6500 | D41: =C41*0.2*0.1*6 -> 780 | E41: =D41*1.2 -> 936
A42: 50Х200 | B42: шт | C42: 6500 | D42: =C42*0.2*0.05*6 -> 390 | E42: =D42*1.2 -> 468
A43: 150Х150 | B43: шт | C43: 6500 | D43: =C43*0.15*0.15*6 -> 877.5 | E43: =D43*1.2 -> 1053
A44: 100Х150 | B44: шт | C44: 6500 | D44: =C44*0.1*0.15*6 -> 585 | E44: =D44*1.2 -> 702
A45: 50Х150 | B45: шт | C45: 6500 | D45: =C45*0.05*0.15*6 -> 292.5 | E45: =D45*1.2 -> 351
A46: 25Х150 | B46: шт | C46: 6500 | D46: =C46*0.025*0.15*6 -> 146.25 | E46: =D46*1.2 -> 175.5
A47: 100Х100 | B47: шт | C47: 6500 | D47: =C47*0.1*0.1*6 -> 390 | E47: =D47*1.2 -> 468
A48: 50Х100 | B48: шт | C48: 6500 | D48: =C48*0.05*0.1*6 -> 195 | E48: =D48*1.2 -> 234
A49: 25Х100 | B49: шт | C49: 6500 | D49: =C49*0.025*0.1*6 -> 97.5 | E49: =D49*1.2 -> 117 | G49: м2 | H49: =D49/0.6 -> 162.5
A50: 50Х50 | B50: шт | C50: 6500 | D50: =C50*0.05*0.05*6 -> 97.5 | E50: =D50*1.2 -> 117
A51: 25Х50 | B51: шт | C51: 6500 | D51: =C51*0.025*0.05*6 -> 48.75 | E51: =D51*1.2 -> 58.5
A52: 40Х50 | B52: шт | C52: 6500 | D52: =C52*0.04*0.05*6 -> 78 | E52: =D52*1.2 -> 93.6
A53: Сухой пиломатериал | C53: 11000
A54: Сухой строганый пиломатериал( 6 м)
A55: Брус 50Х50Х3 | B55: шт | D55: 120 | E55: 144
A56: Брус 50Х40Х3 | B56: шт | D56: 100 | E56: 120
A57: Брус 80Х80Х3 | B57: шт | D57: 900 | E57: 1080
A58: Брус 100Х100Х3 | B58: шт | D58: 1200 | E58: 1440
A59: Рейка 20Х40Х3 | B59: шт | D59: 100 | E59: 120
A60: Доска колиброваная17Х90Х3 | B60: шт | D60: 160 | E60: 192
A61: Доска колиброваная17Х140Х6 | B61: шт | D61: 230 | E61: 276
A63: Доска колиброваная45Х190Х6 | B63: шт | D63: 780 | E63: 936
A64: Доска колиброваная50Х200Х6 | B64: шт | D64: 1200 | E64: 1440
A65: Отделочные материалы
A66: OSB 1250х2500Х9 | B66: м2 | C66: 500 | D66: =C66/3.125 -> 160 | E66: 600
A67: OSB 1250х2500Х12 | B67: м2 | C67: 700 | D67: =C67/3.125 -> 224 | E67: 840
A68: OSB 1250х2500Х18 | B68: м2 | C68: 1050 | D68: =C68/3.125 -> 336 | E68: 1260
A69: OSB 1250х2500Х22 | B69: м2 | C69: 1280 | D69: =C69/3.125 -> 409.6 | E69: 1536
A70: ГСП 3000Х1250Х8 | B70: м2 | C70: 399 | D70: =C70/3.75 -> 106.4 | E70: 478.8
A71: ГСП 2500Х1250Х10 | B71: м2 | C71: 415 | D71: =C71/3.125 -> 132.8 | E71: 498
A72: ГСП 2500Х1250Х12 | B72: м2 | C72: 481 | D72: =C72/3.125 -> 153.92 | E72: 577.2
A73: ЦСП 2700Х1250Х8 | B73: м2 | C73: 620 | D73: =C73/3.375 -> 183.7037 | E73: 744
A74: ЦСП 2700Х1250Х10 | B74: м2 | C74: 747 | D74: =C74/3.375 -> 221.33333 | E74: 896.4
A75: ЦСП 2700Х1250Х12 | B75: м2 | C75: 850 | D75: =C75/3.375 -> 251.85185 | E75: 1020
A76: ЦСП 2700Х1250Х16 | B76: м2 | C76: 1010 | D76: =C76/3.375 -> 299.25926 | E76: 1212
A77: ЦСП 2700Х1250Х20 | B77: м2 | C77: 1220 | D77: =C77/3.375 -> 361.48148 | E77: 1464
A78: ЦСП 2700Х1250Х24 | B78: м2 | C78: 1410 | D78: =C78/3.375 -> 417.77778 | E78: 1692
A79: Фанера 1525Х1525Х10 | B79: м2 | C79: 600 | D79: =C79/2.32 -> 258.62069
A80: Фанера 1525Х1525Х10 | B80: м2 | C80: 435 | D80: =C80/2.32 -> 187.5 | E80: 522
A81: ДВП 2745Х1220 Х3,2 | B81: м2 | C81: 169 | D81: =C81/3.3 -> 51.212121 | E81: 202.8
A82: ГКЛ 2500Х1200Х9,5 | B82: м2 | C82: 215 | D82: =C82/3 -> 71.666667 | E82: 258
A83: ГВЛ 2500Х1200Х10 | B83: м2 | C83: 300 | D83: =C83/3 -> 100 | E83: 360
A84: Вагонка В | B84: м2 | D84: 200 | E84: 240
A85: Вагонка АВ | B85: м2 | D85: 220 | E85: 264
A86: Вагонка С | B86: м2 | D86: 130 | E86: 156
A87: Рау-хаус 135Х16 В | B87: м2 | D87: 230 | E87: 300
A88: Финский профиль 135Х16 В | B88: м2 | D88: 250 | E88: 330
A89: Рау-хаус 135Х16 С | B89: м2 | D89: 205 | E89: 246
A90: Блок-хаус 135Х27 | B90: м2 | D90: 380 | E90: 456
A91: Блок-хаус 135Х36 | B91: м2 | D91: 450 | E91: 540
A92: Блок-хаус 185Х35 | B92: м2 | D92: 500 | E92: 600
A93: Блок-хаус 185Х45 | B93: м2 | D93: 580 | E93: 696
A94: Вагонка липа В | B94: м2 | D94: 500 | E94: 600
A95: Вагонка липа С | B95: м2 | D95: 380 | E95: 456
A96: Вагонка осина В | B96: м2 | D96: 360 | E96: 432
A97: Доска колиброваная 35Х140Х6 | B97: шт | C97: Для лестницы | D97: 430 | E97: 516
A98: Шпунтованная доска, 27 мм | B98: м2 | C98: 27 ммХ135 | D98: 380 | E98: 456
A99: Шпунтованная доска, 36 мм | B99: м2 | C99: 36 ммХ135 | D99: 445 | E99: 534
A100: Фасады
A101: Сайдинг панель/ под ключ | B101: м2 | C101: белый | D101: 214 / 265 | E101: 300/371 | G101: 265
...

Sheet Просчет
A1: Сумма договора | B1: 0 | D1: Номер договора | E1: №
A4: Наименование | B4: Кол-во | C4: Ед. изм. | D4: Цена единицы | E4: Итого: | F4: сто-ть мат-ла | G4: Общий вес, кг | H4: Примечание
A5: Фундамент
A6: Блоки | C6: шт | G6: =F6*B6 -> 0
A7: Свая 2000 | C7: шт | G7: =F7*B7 -> 0
A8: Свая 2500 | C8: шт | G8: =F8*B8 -> 0
A9: Свайный фундамент (забивные сваи) | C9: шт | G9: =F9*B9 -> 0
A10: Смесь М150 | B10: =ROUNDUP(B6/8+B7*1.2+B8*1.5+B9*1.7,0) -> 0 | C10: шт | F10: 0 | G10: =F10*B10 -> 0
A11: Рубероид | B11: 1 | C11: шт | F11: 438 | G11: =B11*F11 -> 438
A12: Антисептик 3TREE BIO 10кг | B12: 2 | C12: шт | F12: 460 | G12: =B12*F12 -> 920
A13: Глухарь 8*100 | B13: =ROUNDUP(B7*2+B8*2+B9*2,0) -> 0 | C13: шт | F13: 0 | G13: =F13*B13 -> 0 | H13: глухарь+шайба для крепления в сваях
A14: Шайба М8 ув | B14: =ROUNDUP(B7*2+B8*2+B9*2,0) -> 0 | C14: шт | F14: 0 | G14: =F14*B14 -> 0
A15: Шпилька 10*1000 | C15: шт | F15: 0 | G15: =F15*B15 -> 0 | H15: Шпилька+гайка+шайба = анкерные болты= для крепления в буронабивных фундаментах
A16: Шайба М6 ув | B16: =B15*4*2 -> 0 | C16: шт | F16: 0 | G16: =F16*B16 -> 0
A17: Гайка М10 | B17: =B15*2*4 -> 0 | C17: шт | F17: 0 | G17: =F17*B17 -> 0
A18: Цанга | B18: =B17 -> 0 | C18: шт
A19: Буронабивной фундамент | C19: шт | G19: =F19*B19 -> 0
A20: Буронабивной фундамент с монолитной плитой | C20: шт | G20: =F20*B20 -> 0
A21: Ж/б лента | C21: шт | G21: =F21*B21 -> 0
A22: Фундаментная плита | C22: шт | G22: =F22*B22 -> 0
A23: Сетка от грызунов 1*10м | C23: шт | F23: 219 | G23: =F23*B23 -> 0
A24: Цоколь
A25: HAUBERK ТЕХНОНИКОЛЬ Терракотовый кирпич | C25: м2 | G25: =F25*B25 -> 0
A26: Пенополистерол 1180х580х50мм | B26: =(B25*0.05)/0.036 -> 0 | C26: шт | G26: =F26*B26 -> 0
A27: ЦСП 10 | B27: =B25/3.375 -> 0 | C27: шт | G27: =F27*B27 -> 0
A28: Профиль 20*40 | B28: =B25/0.4*2 -> 0 | C28: пог. М | G28: =F28*B28 -> 0 | H28: если винтовые сваи
A29: 40*50*3 | B29: =B25/0.4*2/3 -> 0 | C29: шт | G29: =F29*B29 -> 0 | H29: если забивные сваи
A30: Отливы 10 (на фундамент, цвет - вишня) | B30: =B25/0.4/1.9 -> 0 | C30: шт | G30: =F30*B30 -> 0
A31: Брус для обвязки
A32: 50*100*6 обвязка | C32: шт | E32: =0.05*0.1*6*B32 -> 0 | F32: 11500 | G32: =F32*E32 -> 0
A33: 50*150*6 обвязка | C33: шт | E33: =0.05*0.15*6*B33 -> 0 | F33: 11500 | G33: =F33*E33 -> 0
A34: 50*200*6 обвязка | C34: шт | E34: =0.05*0.2*6*B34 -> 0 | F34: 11500 | G34: =F34*E34 -> 0
A35: 100*100*6 обвязка | C35: шт | E35: =0.1*0.1*6*B35 -> 0 | F35: 11500 | G35: =F35*E35 -> 0
A36: 100*150*6 обвязка | C36: шт | E36: =0.1*0.15*6*B36 -> 0 | F36: 11500 | G36: =F36*E36 -> 0
A37: 100*200*6 обвязка | C37: шт | E37: =0.1*0.2*6*B37 -> 0 | F37: 11500 | G37: =F37*E37 -> 0
A38: 150*150*6 обвязка | C38: шт | E38: =0.15*0.15*6*B38 -> 0 | F38: 11500 | G38: =F38*E38 -> 0
A39: 150*200*6 обвязка | C39: шт | E39: =0.15*0.2*6*B39 -> 0 | F39: 11500 | G39: =F39*E39 -> 0
A40: 200*200*6 обвязка | C40: шт | E40: =0.2*0.2*6*B40 -> 0 | F40: 11500 | G40: =F40*E40 -> 0
A41: 50*100*6 сухой обвязка | C41: шт | E41: =0.05*0.1*6*B41 -> 0 | F41: 13500 | G41: =F41*E41 -> 0
A42: 50*150*6 сухой обвязка | C42: шт | E42: =0.05*0.15*6*B42 -> 0 | F42: 13500 | G42: =F42*E42 -> 0
A43: 50*200*6 сухой обвязка | C43: шт | E43: =0.05*0.2*6*B43 -> 0 | F43: 13500 | G43: =F43*E43 -> 0
A44: 100*100*6 сухой обвязка | C44: шт | E44: =0.1*0.1*6*B44 -> 0 | F44: 13500 | G44: =F44*E44 -> 0
A45: 100*150*6 сухой обвязка | C45: шт | E45: =0.1*0.15*6*B45 -> 0 | F45: 13500 | G45: =F45*E45 -> 0
A46: 100*200*6 сухой обвязка | C46: шт | E46: =0.1*0.2*6*B46 -> 0 | F46: 13500 | G46: =F46*E46 -> 0
A47: 150*150*6 сухой обвязка | C47: шт | E47: =0.15*0.15*6*B47 -> 0 | F47: 13500 | G47: =F47*E47 -> 0
A48: 150*200*6 сухой обвязка | C48: шт | E48: =0.15*0.2*6*B48 -> 0 | F48: 13500 | G48: =F48*E48 -> 0
A49: 200*200*6 сухой обвязка | C49: шт | E49: =0.2*0.2*6*B49 -> 0 | F49: 13500 | G49: =F49*E49 -> 0
A50: 40*90*6 обвязка | C50: шт | E50: =0.04*0.09*6*B50 -> 0 | F50: 16500 | G50: =F50*E50 -> 0
A51: 35*140*6 обвязка | C51: шт | E51: =0.2*0.2*6*B51 -> 0 | F51: 19500 | G51: =F51*E51 -> 0
A52: 40*140*6 обвязка | C52: шт | E52: =0.04*0.09*6*B52 -> 0 | F52: 22500 | G52: =F52*E52 -> 0 | H52: Заполнить для сметы в налоговую и для большой сметы клиенту!!!
A53: 35*190*6 обвязка | C53: шт | E53: =0.2*0.2*6*B53 -> 0 | F53: 25500 | G53: =F53*E53 -> 0
A54: 40*190*6 обвязка | C54: шт | E54: =0.04*0.19*6*B54 -> 0 | F54: 16500 | G54: =F54*E54 -> 0 | I54: Фундамент
A55: Брус естественной влажности | H55: Устройство каркаса и стропильной системы дома | I55: Пиломатериал
A56: 25*50*3 | C56: шт | E56: =0.025*0.05*3*B56 -> 0 | F56: 11500 | G56: =E56*F56 -> 0 | H56: Устройство обвязочного бруса
A57: 25*100*6 | C57: шт | E57: =0.025*0.1*6*B57 -> 0 | F57: 11500 | G57: =E57*F57 -> 0 | H57: Устройство каркаса наружных стен с ригелями, укосинами и обвязкой
A58: 25*100*6 2-й сорт | C58: шт | E58: =0.025*0.1*6*B58 -> 0 | F58: 7125 | G58: =E58*F58 -> 0 | H58: Устройство бруска для перекрестного утепления
A59: 25*150*6 | C59: шт | E59: =0.025*0.15*6*B59 -> 0 | F59: 11500 | G59: =E59*F59 -> 0 | H59: Устройство контробрешетки по наружному каркасу (наружной)
A60: 25*200*6 | C60: шт | E60: =0.025*0.2*6*B60 -> 0 | F60: 11500 | G60: =E60*F60 -> 0 | H60: Устройство контробрешетки по наружному каркасу (внутренней)
A61: 40*50*3 | C61: шт | E61: =0.04*0.05*3*B61 -> 0 | F61: 11500 | G61: =E61*F61 -> 0 | H61: Устройство каркаса перегородок
A62: 50*50*3 | C62: шт | E62: =0.05*0.05*3*B62 -> 0 | F62: 11500 | G62: =E62*F62 -> 0 | H62: Устройство опорных столбов
A63: 50*100*6 | C63: шт | E63: =0.05*0.1*6*B63 -> 0 | F63: 11500 | G63: =E63*F63 -> 0 | H63: Устройство чернового пола
A64: 50*150*6 | C64: шт | E64: =0.05*0.15*6*B64 -> 0 | F64: 11500 | G64: =E64*F64 -> 0 | H64: Устройство лаг пола
A65: 50*200*6 | C65: шт | E65: =0.05*0.2*6*B65 -> 0 | F65: 11500 | G65: =E65*F65 -> 0 | H65: Устройство лаг перекрытия
A66: 100*100*6 | C66: шт | E66: =0.1*0.1*6*B66 -> 0 | F66: 11500 | G66: =E66*F66 -> 0 | H66: Устройство матицы
A67: 100*150*6 | C67: шт | E67: =0.1*0.15*6*B67 -> 0 | F67: 11500 | G67: =E67*F67 -> 0 | H67: Устройство стропильной системы
A68: 100*200*6 | C68: шт | E68: =0.1*0.2*6*B68 -> 0 | F68: 11500 | G68: =E68*F68 -> 0 | H68: Устройство обрешетки кровли
A69: 150*150*6 | C69: шт | E69: =0.15*0.15*6*B69 -> 0 | F69: 11500 | G69: =E69*F69 -> 0 | H69: Устройство контробрешетки кровли
A70: 150*200*6 | C70: шт | E70: =0.15*0.2*6*B70 -> 0 | F70: 11500 | G70: =E70*F70 -> 0 | H70: Устройство ограждения
A71: 200*200*6 | C71: шт | E71: =0.2*0.2*6*B71 -> 0 | F71: 11500 | G71: =E71*F71 -> 0 | H71: Устройство обрешетки по потолку
A72: Брус сухой нестроганый | H72: Устройство обрешетки по полу
A73: 25*50*3 сухой | C73: шт | E73: =0.025*0.05*3*B73 -> 0 | F73: 13500 | G73: =E73*F73 -> 0 | H73: Устройство обрешетки
A74: 25*100*6 сухой | C74: шт | E74: =0.025*0.1*6*B74 -> 0 | F74: 13500 | G74: =E74*F74 -> 0 | H74: Устройство черепного бруска
A75: 25*100*6 2-й сорт сухой | C75: шт | E75: =0.025*0.1*6*B75 -> 0 | F75: 9125 | G75: =E75*F75 -> 0 | H75: Устройство роек
A76: 25*150*6 сухой | C76: шт | E76: =0.025*0.15*6*B76 -> 0 | F76: 13500 | G76: =E76*F76 -> 0 | H76: Устройство окосячки
A77: 25*200*6 сухой | C77: шт | E77: =0.025*0.2*6*B77 -> 0 | F77: 13500 | G77: =E77*F77 -> 0 | H77: Другое
A78: 40*50*3 сухой | C78: шт | E78: =0.04*0.05*3*B78 -> 0 | F78: 13500 | G78: =E78*F78 -> 0 | H78: Другое
A79: 50*50*3 сухой | C79: шт | E79: =0.05*0.05*3*B79 -> 0 | F79: 13500 | G79: =E79*F79 -> 0 | H79: Устройство подшива карнизов, потолков крыльца, террасы и навеса | I79: Материал
A80: 50*100*6 сухой | C80: шт | E80: =0.05*0.1*6*B80 -> 0 | F80: 13500 | G80: =E80*F80 -> 0 | H80: Отделка карнизов
A81: 50*150*6 сухой | C81: шт | E81: =0.05*0.15*6*B81 -> 0 | F81: 13500 | G81: =E81*F81 -> 0 | H81: Отделка потолка балкона
A82: 50*200*6 сухой | C82: шт | E82: =0.05*0.2*6*B82 -> 0 | F82: 13500 | G82: =E82*F82 -> 0 | H82: Отделка потолка крыльца
A83: 100*100*6 сухой | C83: шт | E83: =0.1*0.1*6*B83 -> 0 | F83: 13500 | G83: =E83*F83 -> 0 | H83: Отделка потолка террасы
A84: 100*150*6 сухой | C84: шт | E84: =0.1*0.15*6*B84 -> 0 | F84: 13500 | G84: =E84*F84 -> 0 | H84: Отделка потолка навеса
A85: 100*200*6 сухой | C85: шт | E85: =0.1*0.2*6*B85 -> 0 | F85: 13500 | G85: =E85*F85 -> 0 | H85: Другое
A86: 150*150*6 сухой | C86: шт | E86: =0.15*0.15*6*B86 -> 0 | F86: 13500 | G86: =E86*F86 -> 0 | H86: Другое
A87: 150*200*6 сухой | C87: шт | E87: =0.15*0.2*6*B87 -> 0 | F87: 13500 | G87: =E87*F87 -> 0 | H87: Утепление | I87: Материал
A88: 200*200*6 сухой | C88: шт | E88: =0.2*0.2*6*B88 -> 0 | F88: 13500 | G88: =E88*F88 -> 0 | H88: Утепление пола
A89: Брус сухой строганый | H89: Утепление перекрытия
A90: 20*40*3 сухой, строганный | C90: шт | E90: =0.02*0.04*3*B90 -> 0 | F90: 16500 | G90: =E90*F90 -> 0 | H90: Утепление потолка
A91: 20*90*6 | B91: 120 | C91: шт | E91: =0.02*0.09*6*B91 -> 1.296 | F91: 16500 | G91: =E91*F91 -> 21384 | H91: Утепление перегородок первого этажа
A92: 25*100*6 2-й сорт сухой | C92: шт | E92: =0.02*0.09*6*B92 -> 0 | F92: 11125 | G92: =E92*F92 -> 0 | H92: Утепление перегородок второго этажа
A93: 40*50*3 сух, строг | B93: 198 | C93: шт | E93: =0.04*0.05*3*B93 -> 1.188 | F93: 16500 | G93: =E93*F93 -> 19602 | H93: Утепление наружных стен первого этажа
A94: 35*90*6 | C94: шт | E94: =0.04*0.05*3*B94 -> 0 | F94: 16501 | G94: =E94*F94 -> 0
A95: 45*90*6 | B95: 25 | C95: шт | E95: =0.04*0.09*6*B95 -> 0.54 | F95: 16500 | G95: =E95*F95 -> 8910 | H95: Утепление наружных стен второго этажа
A96: 35*140*6 | C96: шт | E96: =0.04*0.09*6*B96 -> 0 | F96: 16501 | G96: =E96*F96 -> 0
A97: 45*140*6 | B97: 33 | C97: шт | E97: =0.04*0.09*6*B97 -> 0.7128 | F97: 16502 | G97: =E97*F97 -> 11762.626 | H97: Утепление пола парного помещения
A98: 35*190*6 | C98: шт | E98: =0.04*0.09*6*B98 -> 0 | F98: 16503 | G98: =E98*F98 -> 0
A99: 45*190*6 | C99: шт | E99: =0.04*0.19*6*B99 -> 0 | F99: 16500 | G99: =E99*F99 -> 0 | H99: Другое
A100: Проф.брус в лапу | H100: Другое
A101: 195*145*6 | C101: шт | E101: =0.195*0.145*6*B101 -> 0 | F101: 14125 | G101: =E101*F101 -> 0 | H101: Наружная отделка | I101: Материал
A102: 145*145*6 | C102: шт | E102: =0.145*0.145*6*B102 -> 0 | F102: 14125 | G102: =E102*F102 -> 0 | H102: Наружная отделка стен первого этажа
...

Sheet Накладная
A1: Накладная № | B1: =Просчет!E1 -> № | C1: от "_ _" _______ 2021 г.
A3: Адрес доставки:
A4: Телефон заказчика:
A5: Имя заказчика:
A6: Телефон бригадира:
A7: Имя бригадира:
A8: Доставка, № А/М:
A11: Наименование | B11: =Просчет!B4 -> Кол-во | C11: =Просчет!C4 -> Ед. изм. | D11: Заезд | E11: Довозка №1 | F11: Довозка №2 | G11: Довозка №3
A12: Фундамент | B12: - | C12: -
A13: =Просчет!A6 -> Блоки | B13: =Просчет!B6 -> 0 | C13: =Просчет!C6 -> шт
A14: =Просчет!A7 -> Свая 2000 | B14: =Просчет!B7 -> 0 | C14: =Просчет!C7 -> шт
A15: =Просчет!A8 -> Свая 2500 | B15: =Просчет!B8 -> 0 | C15: =Просчет!C8 -> шт
A16: =Просчет!A9 -> Свайный фундамент (забивные сваи) | B16: =Просчет!B9 -> 0 | C16: =Просчет!C9 -> шт
A17: =Просчет!A10 -> Смесь М150 | B17: =Просчет!B10 -> 0 | C17: =Просчет!C10 -> шт
A18: =Просчет!A11 -> Рубероид | B18: =Просчет!B11 -> 1 | C18: =Просчет!C11 -> шт
A19: =Просчет!A12 -> Антисептик 3TREE BIO 10кг | B19: =Просчет!B12 -> 2 | C19: =Просчет!C12 -> шт
A20: =Просчет!A13 -> Глухарь 8*100 | B20: =Просчет!B13 -> 0 | C20: =Просчет!C13 -> шт
A21: =Просчет!A14 -> Шайба М8 ув | B21: =Просчет!B14 -> 0 | C21: =Просчет!C14 -> шт
A22: =Просчет!A15 -> Шпилька 10*1000 | B22: =Просчет!B15 -> 0 | C22: =Просчет!C15 -> шт
A23: =Просчет!A16 -> Шайба М6 ув | B23: =Просчет!B16 -> 0 | C23: =Просчет!C16 -> шт
A24: =Просчет!A17 -> Гайка М10 | B24: =Просчет!B17 -> 0 | C24: =Просчет!C17 -> шт
... A30: =Просчет!A23 -> Сетка от грызунов 1*10м | B30: =Просчет!B23 -> 0 | C30: =Просчет!C23 -> шт
A31: =Просчет!A24 -> Цоколь | B31: - | C31: -
A32: =Просчет!A25 -> HAUBERK ТЕХНОНИКОЛЬ Терракотовый кирпич | B32: =Просчет!B25 -> 0 | C32: =Просчет!C25 -> м2
A33: =Просчет!A26 -> Пенополистерол 1180х580х50мм | B33: =Просчет!B26 -> 0 | C33: =Просчет!C26 -> шт
A34: =Просчет!A27 -> ЦСП 10 | B34: =Просчет!B27 -> 0 | C34: =Просчет!C27 -> шт
A35: =Просчет!A28 -> Профиль 20*40 | B35: =Просчет!B28 -> 0 | C35: =Просчет!C28 -> пог. М
A36: =Просчет!A29 -> 40*50*3 | B36: =Просчет!B29 -> 0 | C36: =Просчет!C29 -> шт
A37: =Просчет!A30 -> Отливы 10 (на фундамент, цвет - вишня) | B37: =Просчет!B30 -> 0 | C37: =Просчет!C30 -> шт
A38: =Просчет!A31 -> Брус для обвязки | B38: - | C38: -
A39: =Просчет!A32 -> 50*100*6 обвязка | B39: =Просчет!B32 -> 0 | C39: =Просчет!C32 -> шт
A40: =Просчет!A33 -> 50*150*6 обвязка | B40: =Просчет!B33 -> 0 | C40: =Просчет!C33 -> шт
A41: =Просчет!A34 -> 50*200*6 обвязка | B41: =Просчет!B34 -> 0 | C41: =Просчет!C34 -> шт
A42: =Просчет!A35 -> 100*100*6 обвязка | B42: =Просчет!B35 -> 0 | C42: =Просчет!C35 -> шт
A43: =Просчет!A36 -> 100*150*6 обвязка | B43: =Просчет!B36 -> 0 | C43: =Просчет!C36 -> шт
A44: =Просчет!A37 -> 100*200*6 обвязка | B44: =Просчет!B37 -> 0 | C44: =Просчет!C37 -> шт
A45: =Просчет!A38 -> 150*150*6 обвязка | B45: =Просчет!B38 -> 0 | C45: =Просчет!C38 -> шт
A46: =Просчет!A39 -> 150*200*6 обвязка | B46: =Просчет!B39 -> 0 | C46: =Просчет!C39 -> шт
A47: =Просчет!A40 -> 200*200*6 обвязка | B47: =Просчет!B40 -> 0 | C47: =Просчет!C40 -> шт
A48: =Просчет!A41 -> 50*100*6 сухой обвязка | B48: =Просчет!B41 -> 0 | C48: =Просчет!C41 -> шт
A49: =Просчет!A42 -> 50*150*6 сухой обвязка | B49: =Просчет!B42 -> 0 | C49: =Просчет!C42 -> шт
A50: =Просчет!A43 -> 50*200*6 сухой обвязка | B50: =Просчет!B43 -> 0 | C50: =Просчет!C43 -> шт
... A61: =Просчет!A54 -> 40*190*6 обвязка | B61: =Просчет!B54 -> 0 | C61: =Просчет!C54 -> шт
A62: =Просчет!A55 -> Брус естественной влажности | B62: - | C62: -
A63: =Просчет!A56 -> 25*50*3 | B63: =Просчет!B56 -> 0 | C63: =Просчет!C56 -> шт
A64: =Просчет!A57 -> 25*100*6 | B64: =Просчет!B57 -> 0 | C64: =Просчет!C57 -> шт
A65: =Просчет!A58 -> 25*100*6 2-й сорт | B65: =Просчет!B58 -> 0 | C65: =Просчет!C58 -> шт
A66: =Просчет!A59 -> 25*150*6 | B66: =Просчет!B59 -> 0 | C66: =Просчет!C59 -> шт
A67: =Просчет!A60 -> 25*200*6 | B67: =Просчет!B60 -> 0 | C67: =Просчет!C60 -> шт
A68: =Просчет!A61 -> 40*50*3 | B68: =Просчет!B61 -> 0 | C68: =Просчет!C61 -> шт
A69: =Просчет!A62 -> 50*50*3 | B69: =Просчет!B62 -> 0 | C69: =Просчет!C62 -> шт
A70: =Просчет!A63 -> 50*100*6 | B70: =Просчет!B63 -> 0 | C70: =Просчет!C63 -> шт
A71: =Просчет!A64 -> 50*150*6 | B71: =Просчет!B64 -> 0 | C71: =Просчет!C64 -> шт
A72: =Просчет!A65 -> 50*200*6 | B72: =Просчет!B65 -> 0 | C72: =Просчет!C65 -> шт
A73: =Просчет!A66 -> 100*100*6 | B73: =Просчет!B66 -> 0 | C73: =Просчет!C66 -> шт
A74: =Просчет!A67 -> 100*150*6 | B74: =Просчет!B67 -> 0 | C74: =Просчет!C67 -> шт
... A78: =Просчет!A71 -> 200*200*6 | B78: =Просчет!B71 -> 0 | C78: =Просчет!C71 -> шт
A79: =Просчет!A72 -> Брус сухой нестроганый | B79: - | C79: -
A80: =Просчет!A73 -> 25*50*3 сухой | B80: =Просчет!B73 -> 0 | C80: =Просчет!C73 -> шт
A81: =Просчет!A74 -> 25*100*6 сухой | B81: =Просчет!B74 -> 0 | C81: =Просчет!C74 -> шт
A82: =Просчет!A75 -> 25*100*6 2-й сорт сухой | B82: =Просчет!B75 -> 0 | C82: =Просчет!C75 -> шт
A83: =Просчет!A76 -> 25*150*6 сухой | B83: =Просчет!B76 -> 0 | C83: =Просчет!C76 -> шт
A84: =Просчет!A77 -> 25*200*6 сухой | B84: =Просчет!B77 -> 0 | C84: =Просчет!C77 -> шт
A85: =Просчет!A78 -> 40*50*3 сухой | B85: =Просчет!B78 -> 0 | C85: =Просчет!C78 -> шт
A86: =Просчет!A79 -> 50*50*3 сухой | B86: =Просчет!B79 -> 0 | C86: =Просчет!C79 -> шт
A87: =Просчет!A80 -> 50*100*6 сухой | B87: =Просчет!B80 -> 0 | C87: =Просчет!C80 -> шт
A88: =Просчет!A81 -> 50*150*6 сухой | B88: =Просчет!B81 -> 0 | C88: =Просчет!C81 -> шт
A89: =Просчет!A82 -> 50*200*6 сухой | B89: =Просчет!B82 -> 0 | C89: =Просчет!C82 -> шт
A90: =Просчет!A83 -> 100*100*6 сухой | B90: =Просчет!B83 -> 0 | C90: =Просчет!C83 -> шт
A91: =Просчет!A84 -> 100*150*6 сухой | B91: =Просчет!B84 -> 0 | C91: =Просчет!C84 -> шт
... A95: =Просчет!A88 -> 200*200*6 сухой | B95: =Просчет!B88 -> 0 | C95: =Просчет!C88 -> шт
A96: =Просчет!A89 -> Брус сухой строганый | B96: - | C96: -
A97: =Просчет!A90 -> 20*40*3 сухой, строганный | B97: =Просчет!B90 -> 0 | C97: =Просчет!C90 -> шт
A98: =Просчет!A91 -> 20*90*6 | B98: =Просчет!B91 -> 120 | C98: =Просчет!C91 -> шт
A99: =Просчет!A92 -> 25*100*6 2-й сорт сухой | B99: =Просчет!B92 -> 0 | C99: =Просчет!C92 -> шт
A100: =Просчет!A93 -> 40*50*3 сух, строг | B100: =Просчет!B93 -> 198 | C100: =Просчет!C93 -> шт
A101: =Просчет!A94 -> 35*90*6 | B101: =Просчет!B94 -> 0 | C101: =Просчет!C94 -> шт
A102: =Просчет!A95 -> 45*90*6 | B102: =Просчет!B95 -> 25 | C102: =Просчет!C95 -> шт
A103: =Просчет!A96 -> 35*140*6 | B103: =Просчет!B96 -> 0 | C103: =Просчет!C96 -> шт
A104: =Просчет!A97 -> 45*140*6 | B104: =Просчет!B97 -> 33 | C104: =Просчет!C97 -> шт
A105: =Просчет!A98 -> 35*190*6 | B105: =Просчет!B98 -> 0 | C105: =Просчет!C98 -> шт
A106: =Просчет!A99 -> 45*190*6 | B106: =Просчет!B99 -> 0 | C106: =Просчет!C99 -> шт
A107: =Просчет!A100 -> Проф.брус в лапу | B107: - | C107: -
A108: =Просчет!A101 -> 195*145*6 | B108: =Просчет!B101 -> 0 | C108: =Просчет!C101 -> шт
A109: =Просчет!A102 -> 145*145*6 | B109: =Просчет!B102 -> 0 | C109: =Просчет!C102 -> шт
A110: =Просчет!A103 -> 95*145*6 | B110: =Просчет!B103 -> 0 | C110: =Просчет!C103 -> шт
A111: =Просчет!A104 -> 195*145 сухой | B111: =Просчет!B104 -> 0 | C111: =Просчет!C104 -> шт
A112: =Просчет!A105 -> 145*145 сухой | B112: =Просчет!B105 -> 0 | C112: =Просчет!C105 -> шт
A113: =Просчет!A106 -> 95*145 сухой | B113: =Просчет!B106 -> 0 | C113: =Просчет!C106 -> шт
A114: =Просчет!A107 -> ОЦБ и проф.брус в чашу | B114: - | C114: -
A115: =Просчет!A108 -> 195*145 сухой (в чашу) | B115: =Просчет!B108 -> 0 | C115: =Просчет!C108 -> м3
A116: =Просчет!A109 -> 145*145 сухой (в чашу) | B116: =Просчет!B109 -> 0 | C116: =Просчет!C109 -> м3
A117: =Просчет!A110 -> 95*145 сухой (в чашу) | B117: =Просчет!B110 -> 0 | C117: =Просчет!C110 -> м3
A118: =Просчет!A111 -> ОЦБ ф18 | B118: =Просчет!B111 -> 0 | C118: =Просчет!C111 -> м3
A119: =Просчет!A112 -> ОЦБ ф20 | B119: =Просчет!B112 -> 0 | C119: =Просчет!C112 -> м3
A120: =Просчет!A113 -> ОЦБ ф22 | B120: =Просчет!B113 -> 0 | C120: =Просчет!C113 -> м3
A121: =Просчет!A114 -> ОЦБ ф24 | B121: =Просчет!B114 -> 0 | C121: =Просчет!C114 -> м3
A122: =Просчет!A115 -> ОЦБ ф24 (финский профиль) | B122: =Просчет!B115 -> 0 | C122: =Просчет!C115 -> м3
A123: =Просчет!A116 -> ОЦБ ф26 | B123: =Просчет!B116 -> 0 | C123: =Просчет!C116 -> м3
A124: =Просчет!A117 -> Отделочные материалы | B124: - | C124: -
...

Sheet Мини-смета для клиента
A1: Смета для Заказчика | I1: Смета в бухгалтерию | N1: Выбери % - | O1: 15
F3: Приложение № 3 | N3: Приложение № 3
F4: =_xlfn.TEXTJOIN(,,"к Договору ",Просчет!E1) -> к Договору № | N4: =F4 -> к Договору №
F5: от "_____"______________20____г. | N5: =F5 -> от "_____"______________20____г. | R5: Жилой дом
R6: Дача
A7: СВОДНЫЙ СМЕТНЫЙ РАСЧЕТ | I7: СВОДНЫЙ СМЕТНЫЙ РАСЧЕТ | R7: Баня
R8: Гараж
A9: Дата: | E9: 11.12.2020 | I9: Дата: | M9: =E9 -> 11.12.2020 | R9: Сарай
A10: Объект: | E10: Жилой дом | I10: Объект: | M10: =E10 -> Жилой дом | R10: Беседка
A11: Сметная стоимость: | E11: =_xlfn.TEXTJOIN(,,G37," руб.") -> 609099,426864 руб. | I11: Сметная стоимость: | M11: =_xlfn.TEXTJOIN(,,O37," руб.") -> 517734,5128344 руб.
A14: Наименование работ и ресурсов | C14: Кол-во | D14: Ед.изм | E14: Сметная стоимость, руб. | G14: Общая сметная стоимость, руб. | I14: Наименование работ и ресурсов | K14: Кол-во | L14: Ед.изм | M14: Сметная стоимость, руб. | O14: Общая сметная стоимость, руб. | Q14: ПРИМЕЧАНИЕ!!! | R14: % Для бухгалтерии
E15: Материалы | F15: Оплата труда | M15: Материалы | N15: Оплата труда | Q15: В смете не учтены следующие цены (нужно добавить вручную): | R15: 10
A16: 1.Фундамент | I16: 1.Фундамент | R16: 11
A17: 1.1 Устройство фундамента (включая цоколь) | C17: =IF(E17>0,1,0) -> 0 | D17: комплект | E17: 0 | F17: =E17/1.25*0.55 -> 0 | G17: =E17+F17 -> 0 | I17: 1.1 Устройство фундамента (включая цоколь) | K17: =C17 -> 0 | L17: =D17 -> комплект | M17: =E17*((100-O1)*0.01) -> 0 | N17: =F17*((100-O1)*0.01) -> 0 | O17: =M17+N17 -> 0 | Q17: Фундамент, цоколь | R17: 12
A18: 2.Пиломатериал | I18: 2.Пиломатериал | R18: 13
A19: 2.1 Устройство каркаса/сборка сруба | C19: =IF(E19>0,1,0) -> 1 | D19: комплект | E19: =SUM(Просчет!G32:G54)+SUM(Просчет!G56:G71)+SUM(Просчет!G73:G88)+SUM(Просчет!G90:G99)+SUM(Просчет!G101:G106)+SUM(Просчет!G108:G116)+Просчет!G12 -> 62578.626 | F19: =E19/1.25*0.55 -> 27534.595 | G19: =E19+F19 -> 90113.221 | I19: 2.1 Устройство каркаса/сборка сруба | K19: =C19 -> 1 | L19: =D19 -> комплект | M19: =E19*((100-O1)*0.01) -> 53191.832 | N19: =F19*((100-O1)*0.01) -> 23404.406 | O19: =M19+N19 -> 76596.238 | R19: 14
A20: 3.Отделочные материалы | I20: 3.Отделочные материалы | R20: 15
A21: 3.1 Устройство отделки (включая элементы бани) | C21: =IF(E21>0,1,0) -> 1 | D21: комплект | E21: =SUM(Просчет!G118:G149)+SUM(Просчет!G168:G174)+SUM(Просчет!G265:G289)+SUM(Просчет!G291:G299) -> 119250 | F21: =E21/1.25*0.55 -> 52470 | G21: =E21+F21 -> 171720 | I21: 3.1 Устройство отделки (включая элементы бани) | K21: =C21 -> 1 | L21: =D21 -> комплект | M21: =E21*((100-O1)*0.01) -> 101362.5 | N21: =F21*((100-O1)*0.01) -> 44599.5 | O21: =M21+N21 -> 145962 | Q21: Монтаж материалов заказчика, позиции из пункта "Прочее"
A22: 4.Окна и двери | I22: 4.Окна и двери
A23: 4.1 Устройство окон и дверей | C23: =IF(E23>0,1,0) -> 0 | D23: комплект | E23: =SUM(Просчет!G151:G166) -> 0 | F23: =E23/1.25*0.55 -> 0 | G23: =E23+F23 -> 0 | I23: 4.1 Устройство окон и дверей | K23: =C23 -> 0 | L23: =D23 -> комплект | M23: =E23*((100-O1)*0.01) -> 0 | N23: =F23*((100-O1)*0.01) -> 0 | O23: =M23+N23 -> 0 | Q23: Окна, двери мдф и двери браво
A24: 5.Крепеж | I24: 5.Крепеж
A25: 5.1 Устройство крепежа | C25: =IF(E25>0,1,0) -> 1 | D25: комплект | E25: =SUM(Просчет!G176:G225)*1.25+Просчет!G11+Просчет!G23 -> 39002.688 | F25: =E25/1.25*0.55 -> 17161.183 | G25: =E25+F25 -> 56163.87 | I25: 5.1 Устройство крепежа | K25: =C25 -> 1 | L25: =D25 -> комплект | M25: =E25*((100-O1)*0.01) -> 33152.284 | N25: =F25*((100-O1)*0.01) -> 14587.005 | O25: =M25+N25 -> 47739.289
A26: 6.Кровля | I26: 6.Кровля
A27: 6.1 Устройство кровли | C27: =IF(E27>0,1,0) -> 1 | D27: комплект | E27: =SUM(Просчет!G227:G236) -> 139432 | F27: =E27/1.25*0.55 -> 61350.08 | G27: =E27+F27 -> 200782.08 | I27: 6.1 Устройство кровли | K27: =C27 -> 1 | L27: =D27 -> комплект | M27: =E27*((100-O1)*0.01) -> 118517.2 | N27: =F27*((100-O1)*0.01) -> 52147.568 | O27: =M27+N27 -> 170664.77
A28: 7.Пленки и утеплители | I28: 7.Пленки и утеплители
A29: 7.1 Устройство пленок и утепления | C29: =IF(E29>0,1,0) -> 1 | D29: комплект | E29: =SUM(Просчет!G238:G253) -> 60209.9 | F29: =E29/1.25*0.55 -> 26492.356 | G29: =E29+F29 -> 86702.256 | I29: 7.1 Устройство пленок и утепления | K29: =C29 -> 1 | L29: =D29 -> комплект | M29: =E29*((100-O1)*0.01) -> 51178.415 | N29: =F29*((100-O1)*0.01) -> 22518.503 | O29: =M29+N29 -> 73696.918
A30: 8.Погонажные изделия | I30: 8.Погонажные изделия
A31: 8.1 Устройство погонажа | C31: =IF(E31>0,1,0) -> 1 | D31: комплект | E31: =SUM(Просчет!G255:G263)*1.25 -> 2512.5 | F31: =E31/1.25*0.55 -> 1105.5 | G31: =E31+F31 -> 3618 | I31: 8.1 Устройство погонажа | K31: =C31 -> 1 | L31: =D31 -> комплект | M31: =E31*((100-O1)*0.01) -> 2135.625 | N31: =F31*((100-O1)*0.01) -> 939.675 | O31: =M31+N31 -> 3075.3
A32: 9.Покраска | I32: 9.Покраска
A33: 9.1 Устройство покраски | C33: =IF(E33>0,1,0) -> 0 | D33: комплект | E33: 0 | F33: =E33/1.25*0.55 -> 0 | G33: =E33+F33 -> 0 | I33: 9.1 Устройство покраски | K33: =C33 -> 0 | L33: =D33 -> комплект | M33: =E33*((100-O1)*0.01) -> 0 | N33: =F33*((100-O1)*0.01) -> 0 | O33: =M33+N33 -> 0 | Q33: Покраска
A34: 10.Прочие расходы | I34: 10.Прочие расходы
A35: 10.1 Устройство прочих расходов и доставка | C35: =IF(F35>0,1,0) -> 0 | D35: комплект | E35: 0 | F35: 0 | G35: =E35+F35 -> 0 | I35: 10.1 Устройство прочих расходов и доставка | K35: =C35 -> 0 | L35: =D35 -> комплект | M35: =E35*((100-O1)*0.01) -> 0 | N35: =F35*((100-O1)*0.01) -> 0 | O35: =M35+N35 -> 0 | Q35: Разработка эскизного проекта, Разгрузка и погрузка материала,
Q36: такелажные работы, Аренда бытовки, Устройство лесов, Доставка
A37: Итого по смете,руб.: | G37: =SUM(G16:G35) -> 609099.43 | I37: Итого по смете,руб.: | O37: =SUM(O16:O35) -> 517734.51 | P37: = | Q37: =G37*((100-O1)*0.01) -> 517734.51
A41: Заказчик:________________/___________________/ | I41: Заказчик:________________/___________________/
A43: Подрядчик:________________/_________________/ | I43: Подрядчик:________________/_________________/

Sheet Маленькая смета для клиента
A1: Приложение №3 к договору строительного подряда №00/00 от 00.00.2020 г.
A3: № | B3: Работа | C3: Материал | D3: Кол-во | E3: Ед. изм. | F3: Стоимость ед. материал | G3: Стоимость ед. работа | H3: Итого
A4: 1 | B4: Устройство фундамента
B5: Устройство фундамента | C5: ? | D5: =IF(C5>0,1,0) -> 1 | E5: компл. | H5: =(F5+G5)*D5 -> 0
B6: Геология | D6: =IF(Просчет!B9>0,1,0) -> 0 | E6: компл. | G6: =F6/1.25*0.55 -> 0 | H6: =(F6+G6)*D6 -> 0
B7: Устройство цоколя | C7: Материал предоставляет Заказчик | D7: 0 | E7: компл. | F7: 0 | G7: =F7/1.25*0.55 -> 0 | H7: =(F7+G7)*D7 -> 0
B8: Устройство цоколя | C8: =Просчет!A25 -> HAUBERK ТЕХНОНИКОЛЬ Терракотовый кирпич | D8: =Просчет!B25 -> 0 | E8: =Просчет!C25 -> м2 | G8: =F8/1.25*0.55 -> 0 | H8: =(F8+G8)*D8 -> 0
A9: =A4+1 -> 2 | B9: Устройство каркаса и стропильной системы дома
B10: Устройство каркаса и стропильной системы дома | C10: Брус естественной влажности | D10: =SUM(Просчет!E32:E40)+SUM(Просчет!E56:E71) -> 0 | E10: м3 | F10: 11500 | G10: =F10/1.25*0.55 -> 5060 | H10: =(F10+G10)*D10 -> 0
B11: Устройство каркаса и стропильной системы дома | C11: Брус сухой нестроганый | D11: =SUM(Просчет!E41:E49)+SUM(Просчет!E73:E88) -> 0 | E11: м3 | F11: 13500 | G11: =F11/1.25*0.55 -> 5940 | H11: =(F11+G11)*D11 -> 0
B12: Устройство каркаса и стропильной системы дома | C12: Брус сухой строганый | D12: =SUM(Просчет!E50:E54)+SUM(Просчет!E90:E99) -> 3.7368 | E12: м3 | F12: 16500 | G12: =F12/1.25*0.55 -> 7260 | H12: =(F12+G12)*D12 -> 88786.368
B13: Сборка в лапу профилированного бруса | C13: Профрофилированный брус (сборка в лапу) | D13: =SUM(Просчет!E101:E103) -> 0 | E13: м3 | F13: 14125 | G13: =F13/1.25*0.55 -> 6215 | H13: =(F13+G13)*D13 -> 0
B14: Сборка в лапу профилированного бруса | C14: Профрофилированный брус, сухой (сборка в лапу) | D14: =SUM(Просчет!E104:E106) -> 0 | E14: м3 | F14: 17875 | G14: =F14/1.25*0.55 -> 7865 | H14: =(F14+G14)*D14 -> 0
B15: Сборка в чашу профилированного бруса | C15: Профрофилированный брус, сухой (сборка в чашу) | D15: =SUM(Просчет!B108:B110) -> 0 | E15: м3 | F15: 17750 | G15: =F15/1.25*0.55 -> 7810 | H15: =(F15+G15)*D15 -> 0 | J15: сборка в чашу из сырого = 14375р/м3
B16: Сборка оцилиндрованного бревна | C16: Оцилиндрованное бревно ф18 | D16: =Просчет!B111 -> 0 | E16: м3 | F16: 11000 | G16: =F16/1.25*0.55 -> 4840 | H16: =(F16+G16)*D16 -> 0
B17: Сборка оцилиндрованного бревна | C17: Оцилиндрованное бревно ф20 | D17: =Просчет!B112 -> 0 | E17: м3 | F17: 11000 | G17: =F17/1.25*0.55 -> 4840 | H17: =(F17+G17)*D17 -> 0
B18: Сборка оцилиндрованного бревна | C18: Оцилиндрованное бревно ф22 | D18: =Просчет!B113 -> 0 | E18: м3 | F18: 11000 | G18: =F18/1.25*0.55 -> 4840 | H18: =(F18+G18)*D18 -> 0
B19: Сборка оцилиндрованного бревна | C19: Оцилиндрованное бревно ф24 | D19: =Просчет!B114 -> 0 | E19: м3 | F19: 11000 | G19: =F19/1.25*0.55 -> 4840 | H19: =(F19+G19)*D19 -> 0
B20: Сборка оцилиндрованного бревна | C20: Оцилиндрованное бревно ф24 (финский профиль) | D20: =Просчет!B115 -> 0 | E20: м3 | G20: =F20/1.25*0.55 -> 0 | H20: =(F20+G20)*D20 -> 0
B21: Сборка оцилиндрованного бревна | C21: Оцилиндрованное бревно ф26 | D21: =Просчет!B116 -> 0 | E21: м3 | G21: =F21/1.25*0.55 -> 0 | H21: =(F21+G21)*D21 -> 0
B22: Антисептирование пиломатериала | C22: =Просчет!A12 -> Антисептик 3TREE BIO 10кг | D22: =IF(Просчет!B12>0,1,0) -> 1 | E22: компл. | F22: =Просчет!G12 -> 920 | G22: =F22/1.25*0.55 -> 404.8 | H22: =(F22+G22)*D22 -> 1324.8
A23: =A9+1 -> 3 | B23: Устройство кровли
B24: Устройство покрытия кровли | C24: Оцинкованный профнастил | D24: =Просчет!B227 -> 0 | E24: м2 | F24: 488 | G24: =F24/1.25*0.55 -> 214.72 | H24: =(F24+G24)*D24 -> 0
B25: Устройство покрытия кровли | C25: Крашенный профнастил | D25: =Просчет!B228 -> 164 | E25: м2 | F25: 713 | G25: =F25/1.25*0.55 -> 313.72 | H25: =(F25+G25)*D25 -> 168382.08
B26: Устройство покрытия кровли | C26: Металлочерепица | D26: =Просчет!B229 -> 0 | E26: м2 | F26: 750 | G26: =F26/1.25*0.55 -> 330 | H26: =(F26+G26)*D26 -> 0
B27: Устройство покрытия кровли | C27: Гибкая черепица | D27: =Просчет!B230 -> 0 | E27: м2 | G27: =F27/1.25*0.55 -> 0 | H27: =(F27+G27)*D27 -> 0
B28: Устройство водосточной системы | C28: Водосточная система ПВХ на металлических кронштейнах | D28: =IF(Просчет!B231>0,1,0) -> 1 | E28: компл. | G28: =F28/1.25*0.55 -> 0 | H28: =(F28+G28)*D28 -> 0
B29: Устройство водосточной системы | C29: Водосточная система ПВХ на металлических кронштейнах | D29: =IF(Просчет!B232>0,1,0) -> 0 | E29: компл. | G29: =F29/1.25*0.55 -> 0 | H29: =(F29+G29)*D29 -> 0
B30: Устройство снегозадержателя | C30: Снегозадержатель | D30: =IF(Просчет!B233>0,1,0) -> 0 | E30: компл. | G30: =F30/1.25*0.55 -> 0 | H30: =(F30+G30)*D30 -> 0
B31: Устройство подшива карнизов, потолков крыльца, террасы и навеса | C31: Сайдинг | D31: =Просчет!B234 -> 0 | E31: м2 | G31: =F31/1.25*0.55 -> 0 | H31: =(F31+G31)*D31 -> 0
B32: Устройство подшива карнизов, потолков крыльца, террасы и навеса | C32: Вагонка 90х12,5 - 6м, Сорт АВ | D32: =Просчет!B134 -> 0 | E32: м2 | F32: 275 | G32: =F32/1.25*0.55 -> 121 | H32: =(F32+G32)*D32 -> 0
B33: Устройство подшива карнизов, потолков крыльца, террасы и навеса | C33: Вагонка 90х12,5 - 6м, Сорт Эконом | D33: =Просчет!B136 -> 0 | E33: м2 | F33: 194 | G33: =F33/1.25*0.55 -> 85.36 | H33: =(F33+G33)*D33 -> 0
B34: Устройство подшива карнизов, потолков крыльца, террасы и навеса | C34: Рау-хаус 135х16- 6м, Сорт АВ | D34: =Просчет!B137 -> 99 | E34: м2 | F34: 450 | G34: =F34/1.25*0.55 -> 198 | H34: =(F34+G34)*D34 -> 64152
B35: Устройство подшива карнизов, потолков крыльца, террасы и навеса | C35: Софит перфорированный 50/50 | D35: =Просчет!B235 -> 0 | E35: м2 | G35: =F35/1.25*0.55 -> 0 | H35: =(F35+G35)*D35 -> 0
B36: Устройство вентиляционных решеток | C36: Вентиляционная решетка | D36: =Просчет!B236 -> 0 | E36: шт | F36: 500 | G36: =F36/1.25*0.55 -> 220 | H36: =(F36+G36)*D36 -> 0
A37: =A23+1 -> 4 | B37: Паро/гидроизоляция
B38: Гидроизоляция | C38: Спанизол А | D38: =Просчет!B243+Просчет!B244*0.5 -> 0 | E38: шт | F38: 938 | G38: =F38/1.25*0.55 -> 412.72 | H38: =(F38+G38)*D38 -> 0
B39: Пароизоляция | C39: Фольгированная пароизоляция | D39: =Просчет!B278 -> 0 | E39: шт | F39: 900 | G39: =F39/1.25*0.55 -> 396 | H39: =(F39+G39)*D39 -> 0
B40: Пароизоляция | C40: Спанизол В | D40: =Просчет!B245+Просчет!B246*0.5 -> 0 | E40: шт | F40: 788 | G40: =F40/1.25*0.55 -> 346.72 | H40: =(F40+G40)*D40 -> 0
B41: Гидроизоляция кровли | C41: Спанизол АМ | D41: =Просчет!B247+Просчет!B248*0.5 -> 0 | E41: шт | F41: 2313 | G41: =F41/1.25*0.55 -> 1017.72 | H41: =(F41+G41)*D41 -> 0
B42: Гидроизоляция кровли | C42: Спанизол D | D42: =Просчет!B249+Просчет!B250*0.5 -> 0 | E42: шт | F42: 875 | G42: =F42/1.25*0.55 -> 385 | H42: =(F42+G42)*D42 -> 0
B43: Гидроизоляция | C43: Ondutiss Smart A | D43: =Просчет!B251 -> 3 | E43: шт | F43: 2194 | G43: =F43/1.25*0.55 -> 965.36 | H43: =(F43+G43)*D43 -> 9478.08
B44: Пароизоляция | C44: Ondutiss Smart B | D44: =Просчет!B252 -> 0.5 | E44: шт | F44: 1735 | G44: =F44/1.25*0.55 -> 763.4 | H44: =(F44+G44)*D44 -> 1249.2
B45: Гидроизоляция кровли | C45: Ondutiss Smart SA | D45: =Просчет!B253 -> 3 | E45: шт | F45: 3905 | G45: =F45/1.25*0.55 -> 1718.2 | H45: =(F45+G45)*D45 -> 16869.6
A46: =A37+1 -> 5 | B46: Утепление
B47: Устройство утепления | C47: Рулонная минеральная вата (ISOVER, 0,036Вт/м*К) | D47: =Просчет!B238 -> 29.7 | E47: =Просчет!C238 -> м3 | F47: 1382 | G47: =F47/1.25*0.55 -> 608.08 | H47: =(F47+G47)*D47 -> 59105.376
B48: Устройство утепления | C48: Плитная минеральная вата (ISOVER, низкой плотности, 0,035Вт/м*К) | D48: =Просчет!B240 -> 0 | E48: =Просчет!C240 -> м3 | F48: 1680 | G48: =F48/1.25*0.55 -> 739.2 | H48: =(F48+G48)*D48 -> 0
B49: Устройство утепления | C49: Плитная минеральная вата (ISOVER, средней плотности, 0,034Вт/м*К) | D49: =Просчет!B241 -> 0 | E49: =Просчет!C241 -> м3 | F49: 1680 | G49: =F49/1.25*0.55 -> 739.2 | H49: =(F49+G49)*D49 -> 0
B50: Устройство утепления | C50: =Просчет!A242 -> Пенополистерол 1180х580х50мм | D50: =1.2*0.6*0.05*Просчет!B242 -> 0 | E50: м3 | F50: 4862 | G50: =F50/1.25*0.55 -> 2139.28 | H50: =(F50+G50)*D50 -> 0
A51: =A46+1 -> 6 | B51: Наружная и внутренняя отделка
B52: Устройство террасной доски | C52: =Просчет!A118 -> Террасная доска 112х24 - 6м, Сорт АВ | D52: =Просчет!B118 -> 0 | E52: =Просчет!C118 -> м2 | F52: 525 | G52: =F52/1.25*0.55 -> 231 | H52: =(F52+G52)*D52 -> 0
B53: Устройство калиброой доски | C53: =Просчет!A119 -> Калибровка 140х35- 6м | D53: =Просчет!B119 -> 0 | E53: =Просчет!C119 -> шт | F53: 625 | G53: =F53/1.25*0.55 -> 275 | H53: =(F53+G53)*D53 -> 0
B54: Устройство шпунтовой доски | C54: =Просчет!A120 -> Шпунтовка 90х26 - 6м, Сорт АВ | D54: =Просчет!B120 -> 0 | E54: =Просчет!C120 -> м2 | F54: 525 | G54: =F54/1.25*0.55 -> 231 | H54: =(F54+G54)*D54 -> 0
B55: Устройство шпунтовой доски | C55: =Просчет!A121 -> Шпунтовка 135х35 - 6м, Сорт АВ | D55: =Просчет!B121 -> 0 | E55: =Просчет!C121 -> м2 | F55: 700 | G55: =F55/1.25*0.55 -> 308 | H55: =(F55+G55)*D55 -> 0
B56: Устройство ОСБ | C56: =Просчет!A122 -> ОСБ-3 9мм | D56: =Просчет!B122 -> 0 | E56: =Просчет!C122 -> шт | F56: 813 | G56: =F56/1.25*0.55 -> 357.72 | H56: =(F56+G56)*D56 -> 0
B57: Устройство ОСБ | C57: =Просчет!A123 -> ОСБ-3 12мм | D57: =Просчет!B123 -> 0 | E57: =Просчет!C123 -> шт | F57: 1063 | G57: =F57/1.25*0.55 -> 467.72 | H57: =(F57+G57)*D57 -> 0
B58: Устройство Фанеры | C58: =Просчет!A124 -> Фанера 12 | D58: =Просчет!B124 -> 0 | E58: =Просчет!C124 -> шт | F58: 1088 | G58: =F58/1.25*0.55 -> 478.72 | H58: =(F58+G58)*D58 -> 0
B59: Устройство ЦСП | C59: =Просчет!A125 -> ЦСП 10 | D59: =Просчет!B125 -> 0 | E59: =Просчет!C125 -> шт | F59: 1150 | G59: =F59/1.25*0.55 -> 506 | H59: =(F59+G59)*D59 -> 0
B60: Устройство ЦСП | C60: =Просчет!A126 -> ЦСП 12 | D60: =Просчет!B126 -> 0 | E60: =Просчет!C126 -> шт | F60: 1438 | G60: =F60/1.25*0.55 -> 632.72 | H60: =(F60+G60)*D60 -> 0
B61: Устройство Гипрок Стронг | C61: =Просчет!A127 -> Гипрок Стронг 15мм | D61: =Просчет!B127 -> 25 | E61: =Просчет!C127 -> шт | F61: 450 | G61: =F61/1.25*0.55 -> 198 | H61: =(F61+G61)*D61 -> 16200
B62: Устройство Гипрок Стронг Аква | C62: =Просчет!A128 -> Гипрок Стронг Аква 15мм | D62: =Просчет!B128 -> 0 | E62: =Просчет!C128 -> шт | F62: 488 | G62: =F62/1.25*0.55 -> 214.72 | H62: =(F62+G62)*D62 -> 0
B63: Устройство Гипрок Лайт | C63: =Просчет!A129 -> GTS, 9,5мм | D63: =Просчет!B129 -> 0 | E63: =Просчет!C129 -> шт | F63: 338 | G63: =F63/1.25*0.55 -> 148.72 | H63: =(F63+G63)*D63 -> 0
B64: Устройство Гипрок Лайт Аква | C64: =Просчет!A130 -> Гипрок Лайт Аква 9,5мм | D64: =Просчет!B130 -> 0 | E64: =Просчет!C130 -> шт | F64: 375 | G64: =F64/1.25*0.55 -> 165 | H64: =(F64+G64)*D64 -> 0
B65: Устройство сайдинга | C65: =Просчет!A131 -> Сайдинг Docke Lux Блок-Хаус | D65: =Просчет!B131 -> 0 | E65: =Просчет!C131 -> м2 | G65: =F65/1.25*0.55 -> 0 | H65: =(F65+G65)*D65 -> 0
B66: Устройство панелей | C66: =Просчет!A132 -> Панель Vox Solid Brick Regular (цвет - York) | D66: =Просчет!B132 -> 0 | E66: =Просчет!C132 -> м2 | G66: =F66/1.25*0.55 -> 0 | H66: =(F66+G66)*D66 -> 0
B67: Устройство HAUBERK | C67: =Просчет!A133 -> HAUBERK ТЕХНОНИКОЛЬ Терракотовый кирпич | D67: =Просчет!B133 -> 0 | E67: =Просчет!C133 -> м2 | G67: =F67/1.25*0.55 -> 0 | H67: =(F67+G67)*D67 -> 0
B68: Устройство вагонки | C68: =Просчет!A135 -> Вагонка 90х12,5 - 6м, Сорт АВ (внутренняя отделка) | D68: =Просчет!B135 -> 0 | E68: =Просчет!C135 -> м2 | F68: 275 | G68: =F68/1.25*0.55 -> 121 | H68: =(F68+G68)*D68 -> 0
B69: Устройство имитации бруса | C69: =Просчет!A138 -> Планкен 145х19- 6м, Сорт АВ (наружная отделка) | D69: =Просчет!B138 -> 141 | E69: =Просчет!C138 -> м2 | F69: 450 | G69: =F69/1.25*0.55 -> 198 | H69: =(F69+G69)*D69 -> 91368
B70: Устройство имитации бруса | C70: =Просчет!A139 -> Рау-хаус 135х16- 6м, Сорт АВ (внутренняя отделка) | D70: =Просчет!B139 -> 0 | E70: =Просчет!C139 -> м2 | F70: 450 | G70: =F70/1.25*0.55 -> 198 | H70: =(F70+G70)*D70 -> 0
B71: Устройство имитации бруса | C71: =Просчет!A140 -> Рау-хаус 185х21- 6м, Сорт АВ | D71: =Просчет!B140 -> 0 | E71: =Просчет!C140 -> м2 | F71: 500 | G71: =F71/1.25*0.55 -> 220 | H71: =(F71+G71)*D71 -> 0
B72: Устройство имитации бруса | C72: =Просчет!A141 -> Рау-хаус 110х16- 6м, Сорт АВ (наружная отделка) | D72: =Просчет!B141 -> 0 | E72: =Просчет!C141 -> м2 | F72: 450 | G72: =F72/1.25*0.55 -> 198 | H72: =(F72+G72)*D72 -> 0
B73: Устройство имитации бруса | C73: =Просчет!A142 -> Рау-хаус 110х16- 6м, Сорт АВ (внутренняя отделка) | D73: =Просчет!B142 -> 0 | E73: =Просчет!C142 -> м2 | F73: 450 | G73: =F73/1.25*0.55 -> 198 | H73: =(F73+G73)*D73 -> 0
B74: Устройство финского профиля | C74: =Просчет!A143 -> Финский профиль, С (0,135) | D74: =Просчет!B143 -> 0 | E74: =Просчет!C143 -> м2 | G74: =F74/1.25*0.55 -> 0 | H74: =(F74+G74)*D74 -> 0
B75: Устройство блок-хауса | C75: =Просчет!A144 -> Блок-хаус, АВ (0,135) | D75: =Просчет!B144 -> 0 | E75: =Просчет!C144 -> м2 | F75: 688 | G75: =F75/1.25*0.55 -> 302.72 | H75: =(F75+G75)*D75 -> 0
B76: Устройство блок-хауса | C76: =Просчет!A145 -> Блок-хаус, С (0,135) | D76: =Просчет!B145 -> 0 | E76: =Просчет!C145 -> м2 | F76: 688 | G76: =F76/1.25*0.55 -> 302.72 | H76: =(F76+G76)*D76 -> 0
B77: =Просчет!A146 -> Укладка плитки Заказчика | D77: =Просчет!B146 -> 0 | E77: =Просчет!C146 -> компл. | F77: 0 | G77: =F77/1.25*0.55 -> 0 | H77: =(F77+G77)*D77 -> 0
B78: =Просчет!A147 -> Укладка ламината Заказчика | D78: =Просчет!B147 -> 0 | E78: =Просчет!C147 -> компл. | F78: 0 | G78: =F78/1.25*0.55 -> 0 | H78: =(F78+G78)*D78 -> 0
B79: =Просчет!A148 -> Монтаж обоев Заказчика | D79: =Просчет!B148 -> 0 | E79: =Просчет!C148 -> компл. | F79: 0 | G79: =F79/1.25*0.55 -> 0 | H79: =(F79+G79)*D79 -> 0
B80: Устройство натяжного потолка | C80: =Просчет!A149 -> Натяжной потолок (белый, матовый) | D80: =Просчет!B149 -> 0 | E80: =Просчет!C149 -> м2 | G80: =F80/1.25*0.55 -> 0 | H80: =(F80+G80)*D80 -> 0
B81: Устройство вагонки | C81: =Просчет!A267 -> Вагонка осина 90х12,5 - 2м | D81: =Просчет!B267 -> 0 | E81: =Просчет!C267 -> м2 | F81: 438 | G81: =F81/1.25*0.55 -> 192.72 | H81: =(F81+G81)*D81 -> 0
B82: Устройство вагонки | C82: =Просчет!A268 -> Вагонка липа 90х12,5 - 2м | D82: =Просчет!B268 -> 0 | E82: =Просчет!C268 -> м2 | F82: 625 | G82: =F82/1.25*0.55 -> 275 | H82: =(F82+G82)*D82 -> 0
B83: Устройство петель | C83: =Просчет!A287 -> Петли для двери на чердак | D83: =Просчет!B287 -> 0 | E83: =Просчет!C287 -> шт | F83: 250 | G83: =F83/1.25*0.55 -> 110 | H83: =(F83+G83)*D83 -> 0
B84: Устройство петель | C84: =Просчет!A288 -> Петли для люка | D84: =Просчет!B288 -> 0 | E84: =Просчет!C288 -> шт | F84: 250 | G84: =F84/1.25*0.55 -> 110 | H84: =(F84+G84)*D84 -> 0
A85: =A51+1 -> 7 | B85: Окна
B86: Монтаж ПВХ изделий по проекту | C86: ? | D86: =Просчет!B151 -> 0 | E86: компл. | G86: =F86/1.25*0.55 -> 0 | H86: =(F86+G86)*D86 -> 0
A87: =A85+1 -> 8 | B87: Двери
B88: Устройство межкомнатной двери | C88: =Просчет!A152 -> Двери МДФ, белые(полот., пет, ручки, обн. кор.) | D88: =Просчет!B152 -> 0 | E88: =Просчет!C152 -> шт | G88: =F88/1.25*0.55 -> 0 | H88: =(F88+G88)*D88 -> 0
B89: Устройство межкомнатной двери | C89: =Просчет!A153 -> Дверь межкомнатные Браво с фурнитурой | D89: =Просчет!B153 -> 0 | E89: =Просчет!C153 -> шт | G89: =F89/1.25*0.55 -> 0 | H89: =(F89+G89)*D89 -> 0
B90: Устройство межкомнатной двери | C90: =Просчет!A154 -> Дверь филенчатая 60 см (компл.) | D90: =Просчет!B154 -> 0 | E90: =Просчет!C154 -> шт | F90: 3000 | G90: =F90/1.25*0.55 -> 1320 | H90: =(F90+G90)*D90 -> 0
B91: Устройство межкомнатной двери | C91: =Просчет!A155 -> Дверь филенчатая 70 см (компл.) | D91: =Просчет!B155 -> 0 | E91: =Просчет!C155 -> шт | F91: 3000 | G91: =F91/1.25*0.55 -> 1320 | H91: =(F91+G91)*D91 -> 0
B92: Устройство межкомнатной двери | C92: =Просчет!A156 -> Дверь филенчатая 80 см (компл.) | D92: =Просчет!B156 -> 0 | E92: =Просчет!C156 -> шт | F92: 3000 | G92: =F92/1.25*0.55 -> 1320 | H92: =(F92+G92)*D92 -> 0
B93: Устройство межкомнатной двери | C93: =Просчет!A157 -> Дверь филенчатая 90 см (компл.) | D93: =Просчет!B157 -> 0 | E93: =Просчет!C157 -> шт | F93: 3000 | G93: =F93/1.25*0.55 -> 1320 | H93: =(F93+G93)*D93 -> 0
B94: Устройство межкомнатной двери | C94: =Просчет!A158 -> Дверь банная | D94: =Просчет!B158 -> 0 | E94: =Просчет!C158 -> шт | F94: 2250 | G94: =F94/1.25*0.55 -> 990 | H94: =(F94+G94)*D94 -> 0
B95: Устройство межкомнатной двери | C95: =Просчет!A159 -> Дверь банная со стеклом | D95: =Просчет!B159 -> 0 | E95: =Просчет!C159 -> шт | F95: 6250 | G95: =F95/1.25*0.55 -> 2750 | H95: =(F95+G95)*D95 -> 0
B96: Устройство межкомнатной двери | C96: =Просчет!A160 -> Дверь стеклянная | D96: =Просчет!B160 -> 0 | E96: =Просчет!C160 -> шт | F96: 6250 | G96: =F96/1.25*0.55 -> 2750 | H96: =(F96+G96)*D96 -> 0
B97: Устройство межкомнатной двери | C97: Межкомнатная дверь Заказчика | D97: 0 | E97: шт | F97: 0 | G97: =F97/1.25*0.55 -> 0 | H97: =(F97+G97)*D97 -> 0
B98: Устройство входной двери | C98: =Просчет!A161 -> Дверь входная 1,2мм РФ левая не утепленная | D98: =Просчет!B161 -> 0 | E98: =Просчет!C161 -> шт | F98: 10000 | G98: =F98/1.25*0.55 -> 4400 | H98: =(F98+G98)*D98 -> 0
B99: Устройство входной двери | C99: =Просчет!A162 -> Дверь входная 1,2мм РФ правая не утепленная | D99: =Просчет!B162 -> 0 | E99: =Просчет!C162 -> шт | F99: 10000 | G99: =F99/1.25*0.55 -> 4400 | H99: =(F99+G99)*D99 -> 0
B100: Устройство входной двери | C100: =Просчет!A163 -> Дверь входная 1,5мм РФ левая утепленная | D100: =Просчет!B163 -> 0 | E100: =Просчет!C163 -> шт | F100: 13750 | G100: =F100/1.25*0.55 -> 6050 | H100: =(F100+G100)*D100 -> 0
B101: Устройство входной двери | C101: =Просчет!A164 -> Дверь входная 1,5мм РФ правая утепленная | D101: =Просчет!B164 -> 0 | E101: =Просчет!C164 -> шт | F101: 13750 | G101: =F101/1.25*0.55 -> 6050 | H101: =(F101+G101)*D101 -> 0
...

Sheet Смета в налоговую
A1: СОГЛАСОВАНО: | F1: УТВЕРЖДАЮ:
A4: __________ | F4: __________
A5: "____" __________ 20__ г. | F5: "____" __________ 20__ г.
A6: Приложение №3 к договору 00/00 от 00 мая 0000 года на строительство дома
A7: (наименование стройки)
A9: СМЕТНЫЙ РАСЧЕТ
A10: (локальная смета)
A12: на Строительство дома по адресу: 00000
A16: № | B16: Работа | C16: Материал | D16: Кол-во | E16: Ед. изм. | F16: Стоимость ед. материал | G16: Стоимость ед. работа | H16: Итого
A17: 1 | B17: Устройство фундамента
B18: Устройство фундамента | C18: =Просчет!H54 -> 0 | D18: =IF(C18>0,1,0) -> 0 | E18: компл. | H18: =(F18+G18)*D18 -> 0
B19: Устройство сетки от грызунов | C19: =Просчет!A23 -> Сетка от грызунов 1*10м | D19: =Просчет!B23 -> 0 | E19: компл. | F19: 219 | G19: =F19/1.25*0.55 -> 96.36 | H19: =(F19+G19)*D19 -> 0
B20: Геология | D20: =IF(Просчет!B9>0,1,0) -> 0 | E20: компл. | G20: =F20/1.25*0.55 -> 0 | H20: =(F20+G20)*D20 -> 0
B21: Устройство цоколя | C21: Материал предоставляет Заказчик | D21: 0 | E21: компл. | F21: 0 | G21: =F21/1.25*0.55 -> 0 | H21: =(F21+G21)*D21 -> 0
B22: Устройство цоколя | C22: =Просчет!A25 -> HAUBERK ТЕХНОНИКОЛЬ Терракотовый кирпич | D22: =Просчет!B25 -> 0 | E22: =Просчет!C25 -> м2 | G22: =F22/1.25*0.55 -> 0 | H22: =(F22+G22)*D22 -> 0
A23: =A17+1 -> 2 | B23: Устройство каркаса и стропильной системы дома
B24: =_xlfn.TEXTJOIN(", ",,IF(Просчет!I56='Смета в налоговую'!C24,Просчет!H56,""),IF(Просчет!I57='Смета в налоговую'!C24,Просчет!H57,""),IF(Просчет!I58='Смета в налоговую'!C24,Просчет!H58,""),IF(Просчет!I59='Смета в налоговую'!C24,Просчет!H59,""),IF(Просчет!I60='Смета в налоговую'!C24,Просчет!H60,""),IF(Просчет!I61='Смета в налоговую'!C24,Просчет!H61,""),IF(Просчет!I62='Смета в налоговую'!C24,Просчет!H62,""),IF(Просчет!I63='Смета в налоговую'!C24,Просчет!H63,""),IF(Просчет!I64='Смета в налоговую'!C24,Просчет!H64,""),IF(Просчет!I65='Смета в налоговую'!C24,Просчет!H65,""),IF(Просчет!I66='Смета в налоговую'!C24,Просчет!H66,""),IF(Просчет!I67='Смета в налоговую'!C24,Просчет!H67,""),IF(Просчет!I68='Смета в налоговую'!C24,Просчет!H68,""),IF(Просчет!I69='Смета в налоговую'!C24,Просчет!H69,""),IF(Просчет!I70='Смета в налоговую'!C24,Просчет!H70,""),IF(Просчет!I71='Смета в налоговую'!C24,Просчет!H71,""),IF(Просчет!I72='Смета в налоговую'!C24,Просчет!H72,""),IF(Просчет!I73='Смета в налоговую'!C24,Просчет!H73,""),IF(Просчет!I74='Смета в налоговую'!C24,Просчет!H74,""),IF(Просчет!I75='Смета в налоговую'!C24,Просчет!H75,""),IF(Просчет!I76='Смета в налоговую'!C24,Просчет!H76,""),IF(Просчет!I77='Смета в налоговую'!C24,Просчет!H77,""),IF(Просчет!I78='Смета в налоговую'!C24,Просчет!H78,"")) | C24: Брус 25х50 мм | D24: =0.025*0.05*3*Просчет!B56 -> 0 | E24: м3 | F24: 11500 | G24: =F24/1.25*0.55 -> 5060 | H24: =(F24+G24)*D24 -> 0
B25: =_xlfn.TEXTJOIN(", ",,IF(Просчет!I57='Смета в налоговую'!C25,Просчет!H57,""),IF(Просчет!I58='Смета в налоговую'!C25,Просчет!H58,""),IF(Просчет!I59='Смета в налоговую'!C25,Просчет!H59,""),IF(Просчет!I60='Смета в налоговую'!C25,Просчет!H60,""),IF(Просчет!I61='Смета в налоговую'!C25,Просчет!H61,""),IF(Просчет!I62='Смета в налоговую'!C25,Просчет!H62,""),IF(Просчет!I63='Смета в налоговую'!C25,Просчет!H63,""),IF(Просчет!I64='Смета в налоговую'!C25,Просчет!H64,""),IF(Просчет!I65='Смета в налоговую'!C25,Просчет!H65,""),IF(Просчет!I66='Смета в налоговую'!C25,Просчет!H66,""),IF(Просчет!I67='Смета в налоговую'!C25,Просчет!H67,""),IF(Просчет!I68='Смета в налоговую'!C25,Просчет!H68,""),IF(Просчет!I69='Смета в налоговую'!C25,Просчет!H69,""),IF(Просчет!I70='Смета в налоговую'!C25,Просчет!H70,""),IF(Просчет!I71='Смета в налоговую'!C25,Просчет!H71,""),IF(Просчет!I72='Смета в налоговую'!C25,Просчет!H72,""),IF(Просчет!I73='Смета в налоговую'!C25,Просчет!H73,""),IF(Просчет!I74='Смета в налоговую'!C25,Просчет!H74,""),IF(Просчет!I75='Смета в налоговую'!C25,Просчет!H75,""),IF(Просчет!I76='Смета в налоговую'!C25,Просчет!H76,""),IF(Просчет!I77='Смета в налоговую'!C25,Просчет!H77,""),IF(Просчет!I78='Смета в налоговую'!C25,Просчет!H78,""),IF(Просчет!I56='Смета в налоговую'!C25,Просчет!H56,"")) | C25: Брус 25х100 мм | D25: =0.025*0.1*6*Просчет!B57 -> 0 | E25: м3 | F25: 11500 | G25: =F25/1.25*0.55 -> 5060 | H25: =(F25+G25)*D25 -> 0
B26: =_xlfn.TEXTJOIN(", ",,IF(Просчет!I58='Смета в налоговую'!C26,Просчет!H58,""),IF(Просчет!I59='Смета в налоговую'!C26,Просчет!H59,""),IF(Просчет!I60='Смета в налоговую'!C26,Просчет!H60,""),IF(Просчет!I61='Смета в налоговую'!C26,Просчет!H61,""),IF(Просчет!I62='Смета в налоговую'!C26,Просчет!H62,""),IF(Просчет!I63='Смета в налоговую'!C26,Просчет!H63,""),IF(Просчет!I64='Смета в налоговую'!C26,Просчет!H64,""),IF(Просчет!I65='Смета в налоговую'!C26,Просчет!H65,""),IF(Просчет!I66='Смета в налоговую'!C26,Просчет!H66,""),IF(Просчет!I67='Смета в налоговую'!C26,Просчет!H67,""),IF(Просчет!I68='Смета в налоговую'!C26,Просчет!H68,""),IF(Просчет!I69='Смета в налоговую'!C26,Просчет!H69,""),IF(Просчет!I70='Смета в налоговую'!C26,Просчет!H70,""),IF(Просчет!I71='Смета в налоговую'!C26,Просчет!H71,""),IF(Просчет!I72='Смета в налоговую'!C26,Просчет!H72,""),IF(Просчет!I73='Смета в налоговую'!C26,Просчет!H73,""),IF(Просчет!I74='Смета в налоговую'!C26,Просчет!H74,""),IF(Просчет!I75='Смета в налоговую'!C26,Просчет!H75,""),IF(Просчет!I76='Смета в налоговую'!C26,Просчет!H76,""),IF(Просчет!I77='Смета в налоговую'!C26,Просчет!H77,""),IF(Просчет!I78='Смета в налоговую'!C26,Просчет!H78,""),IF(Просчет!I56='Смета в налоговую'!C26,Просчет!H56,""),IF(Просчет!I57='Смета в налоговую'!C26,Просчет!H57,"")) | C26: Брус 2-го сорта 25х100 мм | D26: =0.025*0.1*6*Просчет!B58 -> 0 | E26: м3 | F26: 7125 | G26: =F26/1.25*0.55 -> 3135 | H26: =(F26+G26)*D26 -> 0
B27: =_xlfn.TEXTJOIN(", ",,IF(Просчет!I59='Смета в налоговую'!C27,Просчет!H59,""),IF(Просчет!I60='Смета в налоговую'!C27,Просчет!H60,""),IF(Просчет!I61='Смета в налоговую'!C27,Просчет!H61,""),IF(Просчет!I62='Смета в налоговую'!C27,Просчет!H62,""),IF(Просчет!I63='Смета в налоговую'!C27,Просчет!H63,""),IF(Просчет!I64='Смета в налоговую'!C27,Просчет!H64,""),IF(Просчет!I65='Смета в налоговую'!C27,Просчет!H65,""),IF(Просчет!I66='Смета в налоговую'!C27,Просчет!H66,""),IF(Просчет!I67='Смета в налоговую'!C27,Просчет!H67,""),IF(Просчет!I68='Смета в налоговую'!C27,Просчет!H68,""),IF(Просчет!I69='Смета в налоговую'!C27,Просчет!H69,""),IF(Просчет!I70='Смета в налоговую'!C27,Просчет!H70,""),IF(Просчет!I71='Смета в налоговую'!C27,Просчет!H71,""),IF(Просчет!I72='Смета в налоговую'!C27,Просчет!H72,""),IF(Просчет!I73='Смета в налоговую'!C27,Просчет!H73,""),IF(Просчет!I74='Смета в налоговую'!C27,Просчет!H74,""),IF(Просчет!I75='Смета в налоговую'!C27,Просчет!H75,""),IF(Просчет!I76='Смета в налоговую'!C27,Просчет!H76,""),IF(Просчет!I77='Смета в налоговую'!C27,Просчет!H77,""),IF(Просчет!I78='Смета в налоговую'!C27,Просчет!H78,""),IF(Просчет!I56='Смета в налоговую'!C27,Просчет!H56,""),IF(Просчет!I57='Смета в налоговую'!C27,Просчет!H57,""),IF(Просчет!I58='Смета в налоговую'!C27,Просчет!H58,"")) | C27: Брус 25х150 мм | D27: =0.025*0.15*6*Просчет!B59 -> 0 | E27: м3 | F27: 11500 | G27: =F27/1.25*0.55 -> 5060 | H27: =(F27+G27)*D27 -> 0
B28: =_xlfn.TEXTJOIN(", ",,IF(Просчет!I60='Смета в налоговую'!C28,Просчет!H60,""),IF(Просчет!I61='Смета в налоговую'!C28,Просчет!H61,""),IF(Просчет!I62='Смета в налоговую'!C28,Просчет!H62,""),IF(Просчет!I63='Смета в налоговую'!C28,Просчет!H63,""),IF(Просчет!I64='Смета в налоговую'!C28,Просчет!H64,""),IF(Просчет!I65='Смета в налоговую'!C28,Просчет!H65,""),IF(Просчет!I66='Смета в налоговую'!C28,Просчет!H66,""),IF(Просчет!I67='Смета в налоговую'!C28,Просчет!H67,""),IF(Просчет!I68='Смета в налоговую'!C28,Просчет!H68,""),IF(Просчет!I69='Смета в налоговую'!C28,Просчет!H69,""),IF(Просчет!I70='Смета в налоговую'!C28,Просчет!H70,""),IF(Просчет!I71='Смета в налоговую'!C28,Просчет!H71,""),IF(Просчет!I72='Смета в налоговую'!C28,Просчет!H72,""),IF(Просчет!I73='Смета в налоговую'!C28,Просчет!H73,""),IF(Просчет!I74='Смета в налоговую'!C28,Просчет!H74,""),IF(Просчет!I75='Смета в налоговую'!C28,Просчет!H75,""),IF(Просчет!I76='Смета в налоговую'!C28,Просчет!H76,""),IF(Просчет!I77='Смета в налоговую'!C28,Просчет!H77,""),IF(Просчет!I78='Смета в налоговую'!C28,Просчет!H78,""),IF(Просчет!I56='Смета в налоговую'!C28,Просчет!H56,""),IF(Просчет!I57='Смета в налоговую'!C28,Просчет!H57,""),IF(Просчет!I58='Смета в налоговую'!C28,Просчет!H58,""),IF(Просчет!I59='Смета в налоговую'!C28,Просчет!H59,"")) | C28: Брус 25х200 мм | D28: =0.025*0.2*6*Просчет!B60 -> 0 | E28: м3 | F28: 11500 | G28: =F28/1.25*0.55 -> 5060 | H28: =(F28+G28)*D28 -> 0
B29: =_xlfn.TEXTJOIN(", ",,IF(Просчет!I61='Смета в налоговую'!C29,Просчет!H61,""),IF(Просчет!I62='Смета в налоговую'!C29,Просчет!H62,""),IF(Просчет!I63='Смета в налоговую'!C29,Просчет!H63,""),IF(Просчет!I64='Смета в налоговую'!C29,Просчет!H64,""),IF(Просчет!I65='Смета в налоговую'!C29,Просчет!H65,""),IF(Просчет!I66='Смета в налоговую'!C29,Просчет!H66,""),IF(Просчет!I67='Смета в налоговую'!C29,Просчет!H67,""),IF(Просчет!I68='Смета в налоговую'!C29,Просчет!H68,""),IF(Просчет!I69='Смета в налоговую'!C29,Просчет!H69,""),IF(Просчет!I70='Смета в налоговую'!C29,Просчет!H70,""),IF(Просчет!I71='Смета в налоговую'!C29,Просчет!H71,""),IF(Просчет!I72='Смета в налоговую'!C29,Просчет!H72,""),IF(Просчет!I73='Смета в налоговую'!C29,Просчет!H73,""),IF(Просчет!I74='Смета в налоговую'!C29,Просчет!H74,""),IF(Просчет!I75='Смета в налоговую'!C29,Просчет!H75,""),IF(Просчет!I76='Смета в налоговую'!C29,Просчет!H76,""),IF(Просчет!I77='Смета в налоговую'!C29,Просчет!H77,""),IF(Просчет!I78='Смета в налоговую'!C29,Просчет!H78,""),IF(Просчет!I56='Смета в налоговую'!C29,Просчет!H56,""),IF(Просчет!I57='Смета в налоговую'!C29,Просчет!H57,""),IF(Просчет!I58='Смета в налоговую'!C29,Просчет!H58,""),IF(Просчет!I59='Смета в налоговую'!C29,Просчет!H59,""),IF(Просчет!I60='Смета в налоговую'!C29,Просчет!H60,"")) | C29: Брус 40х50 мм | D29: =0.04*0.05*3*Просчет!B61 -> 0 | E29: м3 | F29: 11500 | G29: =F29/1.25*0.55 -> 5060 | H29: =(F29+G29)*D29 -> 0
B30: =_xlfn.TEXTJOIN(", ",,IF(Просчет!I62='Смета в налоговую'!C30,Просчет!H62,""),IF(Просчет!I63='Смета в налоговую'!C30,Просчет!H63,""),IF(Просчет!I64='Смета в налоговую'!C30,Просчет!H64,""),IF(Просчет!I65='Смета в налоговую'!C30,Просчет!H65,""),IF(Просчет!I66='Смета в налоговую'!C30,Просчет!H66,""),IF(Просчет!I67='Смета в налоговую'!C30,Просчет!H67,""),IF(Просчет!I68='Смета в налоговую'!C30,Просчет!H68,""),IF(Просчет!I69='Смета в налоговую'!C30,Просчет!H69,""),IF(Просчет!I70='Смета в налоговую'!C30,Просчет!H70,""),IF(Просчет!I71='Смета в налоговую'!C30,Просчет!H71,""),IF(Просчет!I72='Смета в налоговую'!C30,Просчет!H72,""),IF(Просчет!I73='Смета в налоговую'!C30,Просчет!H73,""),IF(Просчет!I74='Смета в налоговую'!C30,Просчет!H74,""),IF(Просчет!I75='Смета в налоговую'!C30,Просчет!H75,""),IF(Просчет!I76='Смета в налоговую'!C30,Просчет!H76,""),IF(Просчет!I77='Смета в налоговую'!C30,Просчет!H77,""),IF(Просчет!I78='Смета в налоговую'!C30,Просчет!H78,""),IF(Просчет!I56='Смета в налоговую'!C30,Просчет!H56,""),IF(Просчет!I57='Смета в налоговую'!C30,Просчет!H57,""),IF(Просчет!I58='Смета в налоговую'!C30,Просчет!H58,""),IF(Просчет!I59='Смета в налоговую'!C30,Просчет!H59,""),IF(Просчет!I60='Смета в налоговую'!C30,Просчет!H60,""),IF(Просчет!I61='Смета в налоговую'!C30,Просчет!H61,"")) | C30: Брус 50х50 мм | D30: =0.05*0.05*3*Просчет!B62 -> 0 | E30: м3 | F30: 11500 | G30: =F30/1.25*0.55 -> 5060 | H30: =(F30+G30)*D30 -> 0
B31: =_xlfn.TEXTJOIN(", ",,IF(Просчет!I63='Смета в налоговую'!C31,Просчет!H63,""),IF(Просчет!I64='Смета в налоговую'!C31,Просчет!H64,""),IF(Просчет!I65='Смета в налоговую'!C31,Просчет!H65,""),IF(Просчет!I66='Смета в налоговую'!C31,Просчет!H66,""),IF(Просчет!I67='Смета в налоговую'!C31,Просчет!H67,""),IF(Просчет!I68='Смета в налоговую'!C31,Просчет!H68,""),IF(Просчет!I69='Смета в налоговую'!C31,Просчет!H69,""),IF(Просчет!I70='Смета в налоговую'!C31,Просчет!H70,""),IF(Просчет!I71='Смета в налоговую'!C31,Просчет!H71,""),IF(Просчет!I72='Смета в налоговую'!C31,Просчет!H72,""),IF(Просчет!I73='Смета в налоговую'!C31,Просчет!H73,""),IF(Просчет!I74='Смета в налоговую'!C31,Просчет!H74,""),IF(Просчет!I75='Смета в налоговую'!C31,Просчет!H75,""),IF(Просчет!I76='Смета в налоговую'!C31,Просчет!H76,""),IF(Просчет!I77='Смета в налоговую'!C31,Просчет!H77,""),IF(Просчет!I78='Смета в налоговую'!C31,Просчет!H78,""),IF(Просчет!I56='Смета в налоговую'!C31,Просчет!H56,""),IF(Просчет!I57='Смета в налоговую'!C31,Просчет!H57,""),IF(Просчет!I58='Смета в налоговую'!C31,Просчет!H58,""),IF(Просчет!I59='Смета в налоговую'!C31,Просчет!H59,""),IF(Просчет!I60='Смета в налоговую'!C31,Просчет!H60,""),IF(Просчет!I61='Смета в налоговую'!C31,Просчет!H61,""),IF(Просчет!I62='Смета в налоговую'!C31,Просчет!H62,"")) | C31: Брус 50х100 мм | D31: =0.05*0.1*6*(Просчет!B63+Просчет!B32) -> 0 | E31: м3 | F31: 11500 | G31: =F31/1.25*0.55 -> 5060 | H31: =(F31+G31)*D31 -> 0
B32: =_xlfn.TEXTJOIN(", ",,IF(Просчет!I64='Смета в налоговую'!C32,Просчет!H64,""),IF(Просчет!I65='Смета в налоговую'!C32,Просчет!H65,""),IF(Просчет!I66='Смета в налоговую'!C32,Просчет!H66,""),IF(Просчет!I67='Смета в налоговую'!C32,Просчет!H67,""),IF(Просчет!I68='Смета в налоговую'!C32,Просчет!H68,""),IF(Просчет!I69='Смета в налоговую'!C32,Просчет!H69,""),IF(Просчет!I70='Смета в налоговую'!C32,Просчет!H70,""),IF(Просчет!I71='Смета в налоговую'!C32,Просчет!H71,""),IF(Просчет!I72='Смета в налоговую'!C32,Просчет!H72,""),IF(Просчет!I73='Смета в налоговую'!C32,Просчет!H73,""),IF(Просчет!I74='Смета в налоговую'!C32,Просчет!H74,""),IF(Просчет!I75='Смета в налоговую'!C32,Просчет!H75,""),IF(Просчет!I76='Смета в налоговую'!C32,Просчет!H76,""),IF(Просчет!I77='Смета в налоговую'!C32,Просчет!H77,""),IF(Просчет!I78='Смета в налоговую'!C32,Просчет!H78,""),IF(Просчет!I56='Смета в налоговую'!C32,Просчет!H56,""),IF(Просчет!I57='Смета в налоговую'!C32,Просчет!H57,""),IF(Просчет!I58='Смета в налоговую'!C32,Просчет!H58,""),IF(Просчет!I59='Смета в налоговую'!C32,Просчет!H59,""),IF(Просчет!I60='Смета в налоговую'!C32,Просчет!H60,""),IF(Просчет!I61='Смета в налоговую'!C32,Просчет!H61,""),IF(Просчет!I62='Смета в налоговую'!C32,Просчет!H62,""),IF(Просчет!I63='Смета в налоговую'!C32,Просчет!H63,"")) | C32: Брус 50х150 мм | D32: =0.05*0.15*6*(Просчет!B64+Просчет!B33) -> 0 | E32: м3 | F32: 11500 | G32: =F32/1.25*0.55 -> 5060 | H32: =(F32+G32)*D32 -> 0
B33: =_xlfn.TEXTJOIN(", ",,IF(Просчет!I65='Смета в налоговую'!C33,Просчет!H65,""),IF(Просчет!I66='Смета в налоговую'!C33,Просчет!H66,""),IF(Просчет!I67='Смета в налоговую'!C33,Просчет!H67,""),IF(Просчет!I68='Смета в налоговую'!C33,Просчет!H68,""),IF(Просчет!I69='Смета в налоговую'!C33,Просчет!H69,""),IF(Просчет!I70='Смета в налоговую'!C33,Просчет!H70,""),IF(Просчет!I71='Смета в налоговую'!C33,Просчет!H71,""),IF(Просчет!I72='Смета в налоговую'!C33,Просчет!H72,""),IF(Просчет!I73='Смета в налоговую'!C33,Просчет!H73,""),IF(Просчет!I74='Смета в налоговую'!C33,Просчет!H74,""),IF(Просчет!I75='Смета в налоговую'!C33,Просчет!H75,""),IF(Просчет!I76='Смета в налоговую'!C33,Просчет!H76,""),IF(Просчет!I77='Смета в налоговую'!C33,Просчет!H77,""),IF(Просчет!I78='Смета в налоговую'!C33,Просчет!H78,""),IF(Просчет!I56='Смета в налоговую'!C33,Просчет!H56,""),IF(Просчет!I57='Смета в налоговую'!C33,Просчет!H57,""),IF(Просчет!I58='Смета в налоговую'!C33,Просчет!H58,""),IF(Просчет!I59='Смета в налоговую'!C33,Просчет!H59,""),IF(Просчет!I60='Смета в налоговую'!C33,Просчет!H60,""),IF(Просчет!I61='Смета в налоговую'!C33,Просчет!H61,""),IF(Просчет!I62='Смета в налоговую'!C33,Просчет!H62,""),IF(Просчет!I63='Смета в налоговую'!C33,Просчет!H63,""),IF(Просчет!I64='Смета в налоговую'!C33,Просчет!H64,"")) | C33: Брус 50х200 мм | D33: =0.05*0.2*6*(Просчет!B65+Просчет!B34) -> 0 | E33: м3 | F33: 11500 | G33: =F33/1.25*0.55 -> 5060 | H33: =(F33+G33)*D33 -> 0
B34: =_xlfn.TEXTJOIN(", ",,IF(Просчет!I66='Смета в налоговую'!C34,Просчет!H66,""),IF(Просчет!I67='Смета в налоговую'!C34,Просчет!H67,""),IF(Просчет!I68='Смета в налоговую'!C34,Просчет!H68,""),IF(Просчет!I69='Смета в налоговую'!C34,Просчет!H69,""),IF(Просчет!I70='Смета в налоговую'!C34,Просчет!H70,""),IF(Просчет!I71='Смета в налоговую'!C34,Просчет!H71,""),IF(Просчет!I72='Смета в налоговую'!C34,Просчет!H72,""),IF(Просчет!I73='Смета в налоговую'!C34,Просчет!H73,""),IF(Просчет!I74='Смета в налоговую'!C34,Просчет!H74,""),IF(Просчет!I75='Смета в налоговую'!C34,Просчет!H75,""),IF(Просчет!I76='Смета в налоговую'!C34,Просчет!H76,""),IF(Просчет!I77='Смета в налоговую'!C34,Просчет!H77,""),IF(Просчет!I78='Смета в налоговую'!C34,Просчет!H78,""),IF(Просчет!I56='Смета в налоговую'!C34,Просчет!H56,""),IF(Просчет!I57='Смета в налоговую'!C34,Просчет!H57,""),IF(Просчет!I58='Смета в налоговую'!C34,Просчет!H58,""),IF(Просчет!I59='Смета в налоговую'!C34,Просчет!H59,""),IF(Просчет!I60='Смета в налоговую'!C34,Просчет!H60,""),IF(Просчет!I61='Смета в налоговую'!C34,Просчет!H61,""),IF(Просчет!I62='Смета в налоговую'!C34,Просчет!H62,""),IF(Просчет!I63='Смета в налоговую'!C34,Просчет!H63,""),IF(Просчет!I64='Смета в налоговую'!C34,Просчет!H64,""),IF(Просчет!I65='Смета в налоговую'!C34,Просчет!H65,"")) | C34: Брус 100х100 мм | D34: =0.1*0.1*6*(Просчет!B66+Просчет!B35) -> 0 | E34: м3 | F34: 11500 | G34: =F34/1.25*0.55 -> 5060 | H34: =(F34+G34)*D34 -> 0
B35: =_xlfn.TEXTJOIN(", ",,IF(Просчет!I67='Смета в налоговую'!C35,Просчет!H67,""),IF(Просчет!I68='Смета в налоговую'!C35,Просчет!H68,""),IF(Просчет!I69='Смета в налоговую'!C35,Просчет!H69,""),IF(Просчет!I70='Смета в налоговую'!C35,Просчет!H70,""),IF(Просчет!I71='Смета в налоговую'!C35,Просчет!H71,""),IF(Просчет!I72='Смета в налоговую'!C35,Просчет!H72,""),IF(Просчет!I73='Смета в налоговую'!C35,Просчет!H73,""),IF(Просчет!I74='Смета в налоговую'!C35,Просчет!H74,""),IF(Просчет!I75='Смета в налоговую'!C35,Просчет!H75,""),IF(Просчет!I76='Смета в налоговую'!C35,Просчет!H76,""),IF(Просчет!I77='Смета в налоговую'!C35,Просчет!H77,""),IF(Просчет!I78='Смета в налоговую'!C35,Просчет!H78,""),IF(Просчет!I56='Смета в налоговую'!C35,Просчет!H56,""),IF(Просчет!I57='Смета в налоговую'!C35,Просчет!H57,""),IF(Просчет!I58='Смета в налоговую'!C35,Просчет!H58,""),IF(Просчет!I59='Смета в налоговую'!C35,Просчет!H59,""),IF(Просчет!I60='Смета в налоговую'!C35,Просчет!H60,""),IF(Просчет!I61='Смета в налоговую'!C35,Просчет!H61,""),IF(Просчет!I62='Смета в налоговую'!C35,Просчет!H62,""),IF(Просчет!I63='Смета в налоговую'!C35,Просчет!H63,""),IF(Просчет!I64='Смета в налоговую'!C35,Просчет!H64,""),IF(Просчет!I65='Смета в налоговую'!C35,Просчет!H65,""),IF(Просчет!I66='Смета в налоговую'!C35,Просчет!H66,"")) | C35: Брус 100х150 мм | D35: =0.1*0.15*6*(Просчет!B67+Просчет!B36) -> 0 | E35: м3 | F35: 11500 | G35: =F35/1.25*0.55 -> 5060 | H35: =(F35+G35)*D35 -> 0
B36: =_xlfn.TEXTJOIN(", ",,IF(Просчет!I68='Смета в налоговую'!C36,Просчет!H68,""),IF(Просчет!I69='Смета в налоговую'!C36,Просчет!H69,""),IF(Просчет!I70='Смета в налоговую'!C36,Просчет!H70,""),IF(Просчет!I71='Смета в налоговую'!C36,Просчет!H71,""),IF(Просчет!I72='Смета в налоговую'!C36,Просчет!H72,""),IF(Просчет!I73='Смета в налоговую'!C36,Просчет!H73,""),IF(Просчет!I74='Смета в налоговую'!C36,Просчет!H74,""),IF(Просчет!I75='Смета в налоговую'!C36,Просчет!H75,""),IF(Просчет!I76='Смета в налоговую'!C36,Просчет!H76,""),IF(Просчет!I77='Смета в налоговую'!C36,Просчет!H77,""),IF(Просчет!I78='Смета в налоговую'!C36,Просчет!H78,""),IF(Просчет!I56='Смета в налоговую'!C36,Просчет!H56,""),IF(Просчет!I57='Смета в налоговую'!C36,Просчет!H57,""),IF(Просчет!I58='Смета в налоговую'!C36,Просчет!H58,""),IF(Просчет!I59='Смета в налоговую'!C36,Просчет!H59,""),IF(Просчет!I60='Смета в налоговую'!C36,Просчет!H60,""),IF(Просчет!I61='Смета в налоговую'!C36,Просчет!H61,""),IF(Просчет!I62='Смета в налоговую'!C36,Просчет!H62,""),IF(Просчет!I63='Смета в налоговую'!C36,Просчет!H63,""),IF(Просчет!I64='Смета в налоговую'!C36,Просчет!H64,""),IF(Просчет!I65='Смета в налоговую'!C36,Просчет!H65,""),IF(Просчет!I66='Смета в налоговую'!C36,Просчет!H66,""),IF(Просчет!I67='Смета в налоговую'!C36,Просчет!H67,"")) | C36: Брус 100х200 мм | D36: =0.1*0.2*6*(Просчет!B68+Просчет!B37) -> 0 | E36: м3 | F36: 11500 | G36: =F36/1.25*0.55 -> 5060 | H36: =(F36+G36)*D36 -> 0
B37: =_xlfn.TEXTJOIN(", ",,IF(Просчет!I69='Смета в налоговую'!C37,Просчет!H69,""),IF(Просчет!I70='Смета в налоговую'!C37,Просчет!H70,""),IF(Просчет!I71='Смета в налоговую'!C37,Просчет!H71,""),IF(Просчет!I72='Смета в налоговую'!C37,Просчет!H72,""),IF(Просчет!I73='Смета в налоговую'!C37,Просчет!H73,""),IF(Просчет!I74='Смета в налоговую'!C37,Просчет!H74,""),IF(Просчет!I75='Смета в налоговую'!C37,Просчет!H75,""),IF(Просчет!I76='Смета в налоговую'!C37,Просчет!H76,""),IF(Просчет!I77='Смета в налоговую'!C37,Просчет!H77,""),IF(Просчет!I78='Смета в налоговую'!C37,Просчет!H78,""),IF(Просчет!I56='Смета в налоговую'!C37,Просчет!H56,""),IF(Просчет!I57='Смета в налоговую'!C37,Просчет!H57,""),IF(Просчет!I58='Смета в налоговую'!C37,Просчет!H58,""),IF(Просчет!I59='Смета в налоговую'!C37,Просчет!H59,""),IF(Просчет!I60='Смета в налоговую'!C37,Просчет!H60,""),IF(Просчет!I61='Смета в налоговую'!C37,Просчет!H61,""),IF(Просчет!I62='Смета в налоговую'!C37,Просчет!H62,""),IF(Просчет!I63='Смета в налоговую'!C37,Просчет!H63,""),IF(Просчет!I64='Смета в налоговую'!C37,Просчет!H64,""),IF(Просчет!I65='Смета в налоговую'!C37,Просчет!H65,""),IF(Просчет!I66='Смета в налоговую'!C37,Просчет!H66,""),IF(Просчет!I67='Смета в налоговую'!C37,Просчет!H67,""),IF(Просчет!I68='Смета в налоговую'!C37,Просчет!H68,"")) | C37: Брус 150х150 мм | D37: =0.15*0.15*6*(Просчет!B69+Просчет!B38) -> 0 | E37: м3 | F37: 11500 | G37: =F37/1.25*0.55 -> 5060 | H37: =(F37+G37)*D37 -> 0
B38: =_xlfn.TEXTJOIN(", ",,IF(Просчет!I70='Смета в налоговую'!C38,Просчет!H70,""),IF(Просчет!I71='Смета в налоговую'!C38,Просчет!H71,""),IF(Просчет!I72='Смета в налоговую'!C38,Просчет!H72,""),IF(Просчет!I73='Смета в налоговую'!C38,Просчет!H73,""),IF(Просчет!I74='Смета в налоговую'!C38,Просчет!H74,""),IF(Просчет!I75='Смета в налоговую'!C38,Просчет!H75,""),IF(Просчет!I76='Смета в налоговую'!C38,Просчет!H76,""),IF(Просчет!I77='Смета в налоговую'!C38,Просчет!H77,""),IF(Просчет!I78='Смета в налоговую'!C38,Просчет!H78,""),IF(Просчет!I56='Смета в налоговую'!C38,Просчет!H56,""),IF(Просчет!I57='Смета в налоговую'!C38,Просчет!H57,""),IF(Просчет!I58='Смета в налоговую'!C38,Просчет!H58,""),IF(Просчет!I59='Смета в налоговую'!C38,Просчет!H59,""),IF(Просчет!I60='Смета в налоговую'!C38,Просчет!H60,""),IF(Просчет!I61='Смета в налоговую'!C38,Просчет!H61,""),IF(Просчет!I62='Смета в налоговую'!C38,Просчет!H62,""),IF(Просчет!I63='Смета в налоговую'!C38,Просчет!H63,""),IF(Просчет!I64='Смета в налоговую'!C38,Просчет!H64,""),IF(Просчет!I65='Смета в налоговую'!C38,Просчет!H65,""),IF(Просчет!I66='Смета в налоговую'!C38,Просчет!H66,""),IF(Просчет!I67='Смета в налоговую'!C38,Просчет!H67,""),IF(Просчет!I68='Смета в налоговую'!C38,Просчет!H68,""),IF(Просчет!I69='Смета в налоговую'!C38,Просчет!H69,"")) | C38: Брус 150х200 мм | D38: =0.15*0.2*6*(Просчет!B70+Просчет!B39) -> 0 | E38: м3 | F38: 11500 | G38: =F38/1.25*0.55 -> 5060 | H38: =(F38+G38)*D38 -> 0
B39: =_xlfn.TEXTJOIN(", ",,IF(Просчет!I71='Смета в налоговую'!C39,Просчет!H71,""),IF(Просчет!I72='Смета в налоговую'!C39,Просчет!H72,""),IF(Просчет!I73='Смета в налоговую'!C39,Просчет!H73,""),IF(Просчет!I74='Смета в налоговую'!C39,Просчет!H74,""),IF(Просчет!I75='Смета в налоговую'!C39,Просчет!H75,""),IF(Просчет!I76='Смета в налоговую'!C39,Просчет!H76,""),IF(Просчет!I77='Смета в налоговую'!C39,Просчет!H77,""),IF(Просчет!I78='Смета в налоговую'!C39,Просчет!H78,""),IF(Просчет!I56='Смета в налоговую'!C39,Просчет!H56,""),IF(Просчет!I57='Смета в налоговую'!C39,Просчет!H57,""),IF(Просчет!I58='Смета в налоговую'!C39,Просчет!H58,""),IF(Просчет!I59='Смета в налоговую'!C39,Просчет!H59,""),IF(Просчет!I60='Смета в налоговую'!C39,Просчет!H60,""),IF(Просчет!I61='Смета в налоговую'!C39,Просчет!H61,""),IF(Просчет!I62='Смета в налоговую'!C39,Просчет!H62,""),IF(Просчет!I63='Смета в налоговую'!C39,Просчет!H63,""),IF(Просчет!I64='Смета в налоговую'!C39,Просчет!H64,""),IF(Просчет!I65='Смета в налоговую'!C39,Просчет!H65,""),IF(Просчет!I66='Смета в налоговую'!C39,Просчет!H66,""),IF(Просчет!I67='Смета в налоговую'!C39,Просчет!H67,""),IF(Просчет!I68='Смета в налоговую'!C39,Просчет!H68,""),IF(Просчет!I69='Смета в налоговую'!C39,Просчет!H69,""),IF(Просчет!I70='Смета в налоговую'!C39,Просчет!H70,"")) | C39: Брус 200х200 мм | D39: =0.2*0.2*6*(Просчет!B71+Просчет!B40) -> 0 | E39: м3 | F39: 11500 | G39: =F39/1.25*0.55 -> 5060 | H39: =(F39+G39)*D39 -> 0
B40: =_xlfn.TEXTJOIN(", ",,IF(Просчет!I72='Смета в налоговую'!C40,Просчет!H72,""),IF(Просчет!I73='Смета в налоговую'!C40,Просчет!H73,""),IF(Просчет!I74='Смета в налоговую'!C40,Просчет!H74,""),IF(Просчет!I75='Смета в налоговую'!C40,Просчет!H75,""),IF(Просчет!I76='Смета в налоговую'!C40,Просчет!H76,""),IF(Просчет!I77='Смета в налоговую'!C40,Просчет!H77,""),IF(Просчет!I78='Смета в налоговую'!C40,Просчет!H78,""),IF(Просчет!I56='Смета в налоговую'!C40,Просчет!H56,""),IF(Просчет!I57='Смета в налоговую'!C40,Просчет!H57,""),IF(Просчет!I58='Смета в налоговую'!C40,Просчет!H58,""),IF(Просчет!I59='Смета в налоговую'!C40,Просчет!H59,""),IF(Просчет!I60='Смета в налоговую'!C40,Просчет!H60,""),IF(Просчет!I61='Смета в налоговую'!C40,Просчет!H61,""),IF(Просчет!I62='Смета в налоговую'!C40,Просчет!H62,""),IF(Просчет!I63='Смета в налоговую'!C40,Просчет!H63,""),IF(Просчет!I64='Смета в налоговую'!C40,Просчет!H64,""),IF(Просчет!I65='Смета в налоговую'!C40,Просчет!H65,""),IF(Просчет!I66='Смета в налоговую'!C40,Просчет!H66,""),IF(Просчет!I67='Смета в налоговую'!C40,Просчет!H67,""),IF(Просчет!I68='Смета в налоговую'!C40,Просчет!H68,""),IF(Просчет!I69='Смета в налоговую'!C40,Просчет!H69,""),IF(Просчет!I70='Смета в налоговую'!C40,Просчет!H70,""),IF(Просчет!I71='Смета в налоговую'!C40,Просчет!H71,"")) | C40: Брус сухой, нестроганый 25х50 мм | D40: =0.025*0.05*3*Просчет!B73 -> 0 | E40: м3 | F40: 13500 | G40: =F40/1.25*0.55 -> 5940 | H40: =(F40+G40)*D40 -> 0
B41: =_xlfn.TEXTJOIN(", ",,IF(Просчет!I73='Смета в налоговую'!C41,Просчет!H73,""),IF(Просчет!I74='Смета в налоговую'!C41,Просчет!H74,""),IF(Просчет!I75='Смета в налоговую'!C41,Просчет!H75,""),IF(Просчет!I76='Смета в налоговую'!C41,Просчет!H76,""),IF(Просчет!I77='Смета в налоговую'!C41,Просчет!H77,""),IF(Просчет!I78='Смета в налоговую'!C41,Просчет!H78,""),IF(Просчет!I56='Смета в налоговую'!C41,Просчет!H56,""),IF(Просчет!I57='Смета в налоговую'!C41,Просчет!H57,""),IF(Просчет!I58='Смета в налоговую'!C41,Просчет!H58,""),IF(Просчет!I59='Смета в налоговую'!C41,Просчет!H59,""),IF(Просчет!I60='Смета в налоговую'!C41,Просчет!H60,""),IF(Просчет!I61='Смета в налоговую'!C41,Просчет!H61,""),IF(Просчет!I62='Смета в налоговую'!C41,Просчет!H62,""),IF(Просчет!I63='Смета в налоговую'!C41,Просчет!H63,""),IF(Просчет!I64='Смета в налоговую'!C41,Просчет!H64,""),IF(Просчет!I65='Смета в налоговую'!C41,Просчет!H65,""),IF(Просчет!I66='Смета в налоговую'!C41,Просчет!H66,""),IF(Просчет!I67='Смета в налоговую'!C41,Просчет!H67,""),IF(Просчет!I68='Смета в налоговую'!C41,Просчет!H68,""),IF(Просчет!I69='Смета в налоговую'!C41,Просчет!H69,""),IF(Просчет!I70='Смета в налоговую'!C41,Просчет!H70,""),IF(Просчет!I71='Смета в налоговую'!C41,Просчет!H71,""),IF(Просчет!I72='Смета в налоговую'!C41,Просчет!H72,"")) | C41: Брус сухой, нестроганый 25х100 мм | D41: =0.025*0.1*6*Просчет!B74 -> 0 | E41: м3 | F41: 13500 | G41: =F41/1.25*0.55 -> 5940 | H41: =(F41+G41)*D41 -> 0
B42: =_xlfn.TEXTJOIN(", ",,IF(Просчет!I74='Смета в налоговую'!C42,Просчет!H74,""),IF(Просчет!I75='Смета в налоговую'!C42,Просчет!H75,""),IF(Просчет!I76='Смета в налоговую'!C42,Просчет!H76,""),IF(Просчет!I77='Смета в налоговую'!C42,Просчет!H77,""),IF(Просчет!I78='Смета в налоговую'!C42,Просчет!H78,""),IF(Просчет!I56='Смета в налоговую'!C42,Просчет!H56,""),IF(Просчет!I57='Смета в налоговую'!C42,Просчет!H57,""),IF(Просчет!I58='Смета в налоговую'!C42,Просчет!H58,""),IF(Просчет!I59='Смета в налоговую'!C42,Просчет!H59,""),IF(Просчет!I60='Смета в налоговую'!C42,Просчет!H60,""),IF(Просчет!I61='Смета в налоговую'!C42,Просчет!H61,""),IF(Просчет!I62='Смета в налоговую'!C42,Просчет!H62,""),IF(Просчет!I63='Смета в налоговую'!C42,Просчет!H63,""),IF(Просчет!I64='Смета в налоговую'!C42,Просчет!H64,""),IF(Просчет!I65='Смета в налоговую'!C42,Просчет!H65,""),IF(Просчет!I66='Смета в налоговую'!C42,Просчет!H66,""),IF(Просчет!I67='Смета в налоговую'!C42,Просчет!H67,""),IF(Просчет!I68='Смета в налоговую'!C42,Просчет!H68,""),IF(Просчет!I69='Смета в налоговую'!C42,Просчет!H69,""),IF(Просчет!I70='Смета в налоговую'!C42,Просчет!H70,""),IF(Просчет!I71='Смета в налоговую'!C42,Просчет!H71,""),IF(Просчет!I72='Смета в налоговую'!C42,Просчет!H72,""),IF(Просчет!I73='Смета в налоговую'!C42,Просчет!H73,"")) | C42: Брус 2-го сорта, сухой, нестроганый 25х100 мм | D42: =0.025*0.1*6*Просчет!B75 -> 0 | E42: м3 | F42: 9125 | G42: =F42/1.25*0.55 -> 4015 | H42: =(F42+G42)*D42 -> 0
B43: =_xlfn.TEXTJOIN(", ",,IF(Просчет!I75='Смета в налоговую'!C43,Просчет!H75,""),IF(Просчет!I76='Смета в налоговую'!C43,Просчет!H76,""),IF(Просчет!I77='Смета в налоговую'!C43,Просчет!H77,""),IF(Просчет!I78='Смета в налоговую'!C43,Просчет!H78,""),IF(Просчет!I56='Смета в налоговую'!C43,Просчет!H56,""),IF(Просчет!I57='Смета в налоговую'!C43,Просчет!H57,""),IF(Просчет!I58='Смета в налоговую'!C43,Просчет!H58,""),IF(Просчет!I59='Смета в налоговую'!C43,Просчет!H59,""),IF(Просчет!I60='Смета в налоговую'!C43,Просчет!H60,""),IF(Просчет!I61='Смета в налоговую'!C43,Просчет!H61,""),IF(Просчет!I62='Смета в налоговую'!C43,Просчет!H62,""),IF(Просчет!I63='Смета в налоговую'!C43,Просчет!H63,""),IF(Просчет!I64='Смета в налоговую'!C43,Просчет!H64,""),IF(Просчет!I65='Смета в налоговую'!C43,Просчет!H65,""),IF(Просчет!I66='Смета в налоговую'!C43,Просчет!H66,""),IF(Просчет!I67='Смета в налоговую'!C43,Просчет!H67,""),IF(Просчет!I68='Смета в налоговую'!C43,Просчет!H68,""),IF(Просчет!I69='Смета в налоговую'!C43,Просчет!H69,""),IF(Просчет!I70='Смета в налоговую'!C43,Просчет!H70,""),IF(Просчет!I71='Смета в налоговую'!C43,Просчет!H71,""),IF(Просчет!I72='Смета в налоговую'!C43,Просчет!H72,""),IF(Просчет!I73='Смета в налоговую'!C43,Просчет!H73,""),IF(Просчет!I74='Смета в налоговую'!C43,Просчет!H74,"")) | C43: Брус сухой, нестроганый 25х150 мм | D43: =0.025*0.15*6*Просчет!B76 -> 0 | E43: м3 | F43: 13500 | G43: =F43/1.25*0.55 -> 5940 | H43: =(F43+G43)*D43 -> 0
B44: =_xlfn.TEXTJOIN(", ",,IF(Просчет!I76='Смета в налоговую'!C44,Просчет!H76,""),IF(Просчет!I77='Смета в налоговую'!C44,Просчет!H77,""),IF(Просчет!I78='Смета в налоговую'!C44,Просчет!H78,""),IF(Просчет!I56='Смета в налоговую'!C44,Просчет!H56,""),IF(Просчет!I57='Смета в налоговую'!C44,Просчет!H57,""),IF(Просчет!I58='Смета в налоговую'!C44,Просчет!H58,""),IF(Просчет!I59='Смета в налоговую'!C44,Просчет!H59,""),IF(Просчет!I60='Смета в налоговую'!C44,Просчет!H60,""),IF(Просчет!I61='Смета в налоговую'!C44,Просчет!H61,""),IF(Просчет!I62='Смета в налоговую'!C44,Просчет!H62,""),IF(Просчет!I63='Смета в налоговую'!C44,Просчет!H63,""),IF(Просчет!I64='Смета в налоговую'!C44,Просчет!H64,""),IF(Просчет!I65='Смета в налоговую'!C44,Просчет!H65,""),IF(Просчет!I66='Смета в налоговую'!C44,Просчет!H66,""),IF(Просчет!I67='Смета в налоговую'!C44,Просчет!H67,""),IF(Просчет!I68='Смета в налоговую'!C44,Просчет!H68,""),IF(Просчет!I69='Смета в налоговую'!C44,Просчет!H69,""),IF(Просчет!I70='Смета в налоговую'!C44,Просчет!H70,""),IF(Просчет!I71='Смета в налоговую'!C44,Просчет!H71,""),IF(Просчет!I72='Смета в налоговую'!C44,Просчет!H72,""),IF(Просчет!I73='Смета в налоговую'!C44,Просчет!H73,""),IF(Просчет!I74='Смета в налоговую'!C44,Просчет!H74,""),IF(Просчет!I75='Смета в налоговую'!C44,Просчет!H75,"")) | C44: Брус сухой, нестроганый 25х200 мм | D44: =0.025*0.2*6*Просчет!B77 -> 0 | E44: м3 | F44: 13500 | G44: =F44/1.25*0.55 -> 5940 | H44: =(F44+G44)*D44 -> 0
B45: =_xlfn.TEXTJOIN(", ",,IF(Просчет!I77='Смета в налоговую'!C45,Просчет!H77,""),IF(Просчет!I78='Смета в налоговую'!C45,Просчет!H78,""),IF(Просчет!I56='Смета в налоговую'!C45,Просчет!H56,""),IF(Просчет!I57='Смета в налоговую'!C45,Просчет!H57,""),IF(Просчет!I58='Смета в налоговую'!C45,Просчет!H58,""),IF(Просчет!I59='Смета в налоговую'!C45,Просчет!H59,""),IF(Просчет!I60='Смета в налоговую'!C45,Просчет!H60,""),IF(Просчет!I61='Смета в налоговую'!C45,Просчет!H61,""),IF(Просчет!I62='Смета в налоговую'!C45,Просчет!H62,""),IF(Просчет!I63='Смета в налоговую'!C45,Просчет!H63,""),IF(Просчет!I64='Смета в налоговую'!C45,Просчет!H64,""),IF(Просчет!I65='Смета в налоговую'!C45,Просчет!H65,""),IF(Просчет!I66='Смета в налоговую'!C45,Просчет!H66,""),IF(Просчет!I67='Смета в налоговую'!C45,Просчет!H67,""),IF(Просчет!I68='Смета в налоговую'!C45,Просчет!H68,""),IF(Просчет!I69='Смета в налоговую'!C45,Просчет!H69,""),IF(Просчет!I70='Смета в налоговую'!C45,Просчет!H70,""),IF(Просчет!I71='Смета в налоговую'!C45,Просчет!H71,""),IF(Просчет!I72='Смета в налоговую'!C45,Просчет!H72,""),IF(Просчет!I73='Смета в налоговую'!C45,Просчет!H73,""),IF(Просчет!I74='Смета в налоговую'!C45,Просчет!H74,""),IF(Просчет!I75='Смета в налоговую'!C45,Просчет!H75,""),IF(Просчет!I76='Смета в налоговую'!C45,Просчет!H76,"")) | C45: Брус сухой, нестроганый 40х50 мм | D45: =0.04*0.05*3*Просчет!B78 -> 0 | E45: м3 | F45: 13500 | G45: =F45/1.25*0.55 -> 5940 | H45: =(F45+G45)*D45 -> 0
B46: =_xlfn.TEXTJOIN(", ",,IF(Просчет!I78='Смета в налоговую'!C46,Просчет!H78,""),IF(Просчет!I56='Смета в налоговую'!C46,Просчет!H56,""),IF(Просчет!I57='Смета в налоговую'!C46,Просчет!H57,""),IF(Просчет!I58='Смета в налоговую'!C46,Просчет!H58,""),IF(Просчет!I59='Смета в налоговую'!C46,Просчет!H59,""),IF(Просчет!I60='Смета в налоговую'!C46,Просчет!H60,""),IF(Просчет!I61='Смета в налоговую'!C46,Просчет!H61,""),IF(Просчет!I62='Смета в налоговую'!C46,Просчет!H62,""),IF(Просчет!I63='Смета в налоговую'!C46,Просчет!H63,""),IF(Просчет!I64='Смета в налоговую'!C46,Просчет!H64,""),IF(Просчет!I65='Смета в налоговую'!C46,Просчет!H65,""),IF(Просчет!I66='Смета в налоговую'!C46,Просчет!H66,""),IF(Просчет!I67='Смета в налоговую'!C46,Просчет!H67,""),IF(Просчет!I68='Смета в налоговую'!C46,Просчет!H68,""),IF(Просчет!I69='Смета в налоговую'!C46,Просчет!H69,""),IF(Просчет!I70='Смета в налоговую'!C46,Просчет!H70,""),IF(Просчет!I71='Смета в налоговую'!C46,Просчет!H71,""),IF(Просчет!I72='Смета в налоговую'!C46,Просчет!H72,""),IF(Просчет!I73='Смета в налоговую'!C46,Просчет!H73,""),IF(Просчет!I74='Смета в налоговую'!C46,Просчет!H74,""),IF(Просчет!I75='Смета в налоговую'!C46,Просчет!H75,""),IF(Просчет!I76='Смета в налоговую'!C46,Просчет!H76,""),IF(Просчет!I77='Смета в налоговую'!C46,Просчет!H77,"")) | C46: Брус сухой, нестроганый 50х50 мм | D46: =0.05*0.05*3*Просчет!B79 -> 0 | E46: м3 | F46: 13500 | G46: =F46/1.25*0.55 -> 5940 | H46: =(F46+G46)*D46 -> 0
B47: =_xlfn.TEXTJOIN(", ",,IF(Просчет!I56='Смета в налоговую'!C47,Просчет!H56,""),IF(Просчет!I57='Смета в налоговую'!C47,Просчет!H57,""),IF(Просчет!I58='Смета в налоговую'!C47,Просчет!H58,""),IF(Просчет!I59='Смета в налоговую'!C47,Просчет!H59,""),IF(Просчет!I60='Смета в налоговую'!C47,Просчет!H60,""),IF(Просчет!I61='Смета в налоговую'!C47,Просчет!H61,""),IF(Просчет!I62='Смета в налоговую'!C47,Просчет!H62,""),IF(Просчет!I63='Смета в налоговую'!C47,Просчет!H63,""),IF(Просчет!I64='Смета в налоговую'!C47,Просчет!H64,""),IF(Просчет!I65='Смета в налоговую'!C47,Просчет!H65,""),IF(Просчет!I66='Смета в налоговую'!C47,Просчет!H66,""),IF(Просчет!I67='Смета в налоговую'!C47,Просчет!H67,""),IF(Просчет!I68='Смета в налоговую'!C47,Просчет!H68,""),IF(Просчет!I69='Смета в налоговую'!C47,Просчет!H69,""),IF(Просчет!I70='Смета в налоговую'!C47,Просчет!H70,""),IF(Просчет!I71='Смета в налоговую'!C47,Просчет!H71,""),IF(Просчет!I72='Смета в налоговую'!C47,Просчет!H72,""),IF(Просчет!I73='Смета в налоговую'!C47,Просчет!H73,""),IF(Просчет!I74='Смета в налоговую'!C47,Просчет!H74,""),IF(Просчет!I75='Смета в налоговую'!C47,Просчет!H75,""),IF(Просчет!I76='Смета в налоговую'!C47,Просчет!H76,""),IF(Просчет!I77='Смета в налоговую'!C47,Просчет!H77,""),IF(Просчет!I78='Смета в налоговую'!C47,Просчет!H78,"")) | C47: Брус сухой, нестроганый 50х100 мм | D47: =0.05*0.1*6*(Просчет!B80+Просчет!B41) -> 0 | E47: м3 | F47: 13500 | G47: =F47/1.25*0.55 -> 5940 | H47: =(F47+G47)*D47 -> 0
B48: =_xlfn.TEXTJOIN(", ",,IF(Просчет!I57='Смета в налоговую'!C48,Просчет!H57,""),IF(Просчет!I58='Смета в налоговую'!C48,Просчет!H58,""),IF(Просчет!I59='Смета в налоговую'!C48,Просчет!H59,""),IF(Просчет!I60='Смета в налоговую'!C48,Просчет!H60,""),IF(Просчет!I61='Смета в налоговую'!C48,Просчет!H61,""),IF(Просчет!I62='Смета в налоговую'!C48,Просчет!H62,""),IF(Просчет!I63='Смета в налоговую'!C48,Просчет!H63,""),IF(Просчет!I64='Смета в налоговую'!C48,Просчет!H64,""),IF(Просчет!I65='Смета в налоговую'!C48,Просчет!H65,""),IF(Просчет!I66='Смета в налоговую'!C48,Просчет!H66,""),IF(Просчет!I67='Смета в налоговую'!C48,Просчет!H67,""),IF(Просчет!I68='Смета в налоговую'!C48,Просчет!H68,""),IF(Просчет!I69='Смета в налоговую'!C48,Просчет!H69,""),IF(Просчет!I70='Смета в налоговую'!C48,Просчет!H70,""),IF(Просчет!I71='Смета в налоговую'!C48,Просчет!H71,""),IF(Просчет!I72='Смета в налоговую'!C48,Просчет!H72,""),IF(Просчет!I73='Смета в налоговую'!C48,Просчет!H73,""),IF(Просчет!I74='Смета в налоговую'!C48,Просчет!H74,""),IF(Просчет!I75='Смета в налоговую'!C48,Просчет!H75,""),IF(Просчет!I76='Смета в налоговую'!C48,Просчет!H76,""),IF(Просчет!I77='Смета в налоговую'!C48,Просчет!H77,""),IF(Просчет!I78='Смета в налоговую'!C48,Просчет!H78,""),IF(Просчет!I56='Смета в налоговую'!C48,Просчет!H56,"")) | C48: Брус сухой, нестроганый 50х150 мм | D48: =0.05*0.15*6*(Просчет!B81+Просчет!B42) -> 0 | E48: м3 | F48: 13500 | G48: =F48/1.25*0.55 -> 5940 | H48: =(F48+G48)*D48 -> 0
B49: =_xlfn.TEXTJOIN(", ",,IF(Просчет!I58='Смета в налоговую'!C49,Просчет!H58,""),IF(Просчет!I59='Смета в налоговую'!C49,Просчет!H59,""),IF(Просчет!I60='Смета в налоговую'!C49,Просчет!H60,""),IF(Просчет!I61='Смета в налоговую'!C49,Просчет!H61,""),IF(Просчет!I62='Смета в налоговую'!C49,Просчет!H62,""),IF(Просчет!I63='Смета в налоговую'!C49,Просчет!H63,""),IF(Просчет!I64='Смета в налоговую'!C49,Просчет!H64,""),IF(Просчет!I65='Смета в налоговую'!C49,Просчет!H65,""),IF(Просчет!I66='Смета в налоговую'!C49,Просчет!H66,""),IF(Просчет!I67='Смета в налоговую'!C49,Просчет!H67,""),IF(Просчет!I68='Смета в налоговую'!C49,Просчет!H68,""),IF(Просчет!I69='Смета в налоговую'!C49,Просчет!H69,""),IF(Просчет!I70='Смета в налоговую'!C49,Просчет!H70,""),IF(Просчет!I71='Смета в налоговую'!C49,Просчет!H71,""),IF(Просчет!I72='Смета в налоговую'!C49,Просчет!H72,""),IF(Просчет!I73='Смета в налоговую'!C49,Просчет!H73,""),IF(Просчет!I74='Смета в налоговую'!C49,Просчет!H74,""),IF(Просчет!I75='Смета в налоговую'!C49,Просчет!H75,""),IF(Просчет!I76='Смета в налоговую'!C49,Просчет!H76,""),IF(Просчет!I77='Смета в налоговую'!C49,Просчет!H77,""),IF(Просчет!I78='Смета в налоговую'!C49,Просчет!H78,""),IF(Просчет!I56='Смета в налоговую'!C49,Просчет!H56,""),IF(Просчет!I57='Смета в налоговую'!C49,Просчет!H57,"")) | C49: Брус сухой, нестроганый 50х200 мм | D49: =0.05*0.2*6*(Просчет!B82+Просчет!B43) -> 0 | E49: м3 | F49: 13500 | G49: =F49/1.25*0.55 -> 5940 | H49: =(F49+G49)*D49 -> 0
B50: =_xlfn.TEXTJOIN(", ",,IF(Просчет!I59='Смета в налоговую'!C50,Просчет!H59,""),IF(Просчет!I60='Смета в налоговую'!C50,Просчет!H60,""),IF(Просчет!I61='Смета в налоговую'!C50,Просчет!H61,""),IF(Просчет!I62='Смета в налоговую'!C50,Просчет!H62,""),IF(Просчет!I63='Смета в налоговую'!C50,Просчет!H63,""),IF(Просчет!I64='Смета в налоговую'!C50,Просчет!H64,""),IF(Просчет!I65='Смета в налоговую'!C50,Просчет!H65,""),IF(Просчет!I66='Смета в налоговую'!C50,Просчет!H66,""),IF(Просчет!I67='Смета в налоговую'!C50,Просчет!H67,""),IF(Просчет!I68='Смета в налоговую'!C50,Просчет!H68,""),IF(Просчет!I69='Смета в налоговую'!C50,Просчет!H69,""),IF(Просчет!I70='Смета в налоговую'!C50,Просчет!H70,""),IF(Просчет!I71='Смета в налоговую'!C50,Просчет!H71,""),IF(Просчет!I72='Смета в налоговую'!C50,Просчет!H72,""),IF(Просчет!I73='Смета в налоговую'!C50,Просчет!H73,""),IF(Просчет!I74='Смета в налоговую'!C50,Просчет!H74,""),IF(Просчет!I75='Смета в налоговую'!C50,Просчет!H75,""),IF(Просчет!I76='Смета в налоговую'!C50,Просчет!H76,""),IF(Просчет!I77='Смета в налоговую'!C50,Просчет!H77,""),IF(Просчет!I78='Смета в налоговую'!C50,Просчет!H78,""),IF(Просчет!I56='Смета в налоговую'!C50,Просчет!H56,""),IF(Просчет!I57='Смета в налоговую'!C50,Просчет!H57,""),IF(Просчет!I58='Смета в налоговую'!C50,Просчет!H58,"")) | C50: Брус сухой, нестроганый 100х100 мм | D50: =0.1*0.1*6*(Просчет!B83+Просчет!B44) -> 0 | E50: м3 | F50: 13500 | G50: =F50/1.25*0.55 -> 5940 | H50: =(F50+G50)*D50 -> 0
B51: =_xlfn.TEXTJOIN(", ",,IF(Просчет!I60='Смета в налоговую'!C51,Просчет!H60,""),IF(Просчет!I61='Смета в налоговую'!C51,Просчет!H61,""),IF(Просчет!I62='Смета в налоговую'!C51,Просчет!H62,""),IF(Просчет!I63='Смета в налоговую'!C51,Просчет!H63,""),IF(Просчет!I64='Смета в налоговую'!C51,Просчет!H64,""),IF(Просчет!I65='Смета в налоговую'!C51,Просчет!H65,""),IF(Просчет!I66='Смета в налоговую'!C51,Просчет!H66,""),IF(Просчет!I67='Смета в налоговую'!C51,Просчет!H67,""),IF(Просчет!I68='Смета в налоговую'!C51,Просчет!H68,""),IF(Просчет!I69='Смета в налоговую'!C51,Просчет!H69,""),IF(Просчет!I70='Смета в налоговую'!C51,Просчет!H70,""),IF(Просчет!I71='Смета в налоговую'!C51,Просчет!H71,""),IF(Просчет!I72='Смета в налоговую'!C51,Просчет!H72,""),IF(Просчет!I73='Смета в налоговую'!C51,Просчет!H73,""),IF(Просчет!I74='Смета в налоговую'!C51,Просчет!H74,""),IF(Просчет!I75='Смета в налоговую'!C51,Просчет!H75,""),IF(Просчет!I76='Смета в налоговую'!C51,Просчет!H76,""),IF(Просчет!I77='Смета в налоговую'!C51,Просчет!H77,""),IF(Просчет!I78='Смета в налоговую'!C51,Просчет!H78,""),IF(Просчет!I56='Смета в налоговую'!C51,Просчет!H56,""),IF(Просчет!I57='Смета в налоговую'!C51,Просчет!H57,""),IF(Просчет!I58='Смета в налоговую'!C51,Просчет!H58,""),IF(Просчет!I59='Смета в налоговую'!C51,Просчет!H59,"")) | C51: Брус сухой, нестроганый 100х150 мм | D51: =0.1*0.15*6*(Просчет!B84+Просчет!B45) -> 0 | E51: м3 | F51: 13500 | G51: =F51/1.25*0.55 -> 5940 | H51: =(F51+G51)*D51 -> 0
B52: =_xlfn.TEXTJOIN(", ",,IF(Просчет!I61='Смета в налоговую'!C52,Просчет!H61,""),IF(Просчет!I62='Смета в налоговую'!C52,Просчет!H62,""),IF(Просчет!I63='Смета в налоговую'!C52,Просчет!H63,""),IF(Просчет!I64='Смета в налоговую'!C52,Просчет!H64,""),IF(Просчет!I65='Смета в налоговую'!C52,Просчет!H65,""),IF(Просчет!I66='Смета в налоговую'!C52,Просчет!H66,""),IF(Просчет!I67='Смета в налоговую'!C52,Просчет!H67,""),IF(Просчет!I68='Смета в налоговую'!C52,Просчет!H68,""),IF(Просчет!I69='Смета в налоговую'!C52,Просчет!H69,""),IF(Просчет!I70='Смета в налоговую'!C52,Просчет!H70,""),IF(Просчет!I71='Смета в налоговую'!C52,Просчет!H71,""),IF(Просчет!I72='Смета в налоговую'!C52,Просчет!H72,""),IF(Просчет!I73='Смета в налоговую'!C52,Просчет!H73,""),IF(Просчет!I74='Смета в налоговую'!C52,Просчет!H74,""),IF(Просчет!I75='Смета в налоговую'!C52,Просчет!H75,""),IF(Просчет!I76='Смета в налоговую'!C52,Просчет!H76,""),IF(Просчет!I77='Смета в налоговую'!C52,Просчет!H77,""),IF(Просчет!I78='Смета в налоговую'!C52,Просчет!H78,""),IF(Просчет!I56='Смета в налоговую'!C52,Просчет!H56,""),IF(Просчет!I57='Смета в налоговую'!C52,Просчет!H57,""),IF(Просчет!I58='Смета в налоговую'!C52,Просчет!H58,""),IF(Просчет!I59='Смета в налоговую'!C52,Просчет!H59,""),IF(Просчет!I60='Смета в налоговую'!C52,Просчет!H60,"")) | C52: Брус сухой, нестроганый 100х200 мм | D52: =0.1*0.2*6*(Просчет!B85+Просчет!B46) -> 0 | E52: м3 | F52: 13500 | G52: =F52/1.25*0.55 -> 5940 | H52: =(F52+G52)*D52 -> 0
B53: =_xlfn.TEXTJOIN(", ",,IF(Просчет!I62='Смета в налоговую'!C53,Просчет!H62,""),IF(Просчет!I63='Смета в налоговую'!C53,Просчет!H63,""),IF(Просчет!I64='Смета в налоговую'!C53,Просчет!H64,""),IF(Просчет!I65='Смета в налоговую'!C53,Просчет!H65,""),IF(Просчет!I66='Смета в налоговую'!C53,Просчет!H66,""),IF(Просчет!I67='Смета в налоговую'!C53,Просчет!H67,""),IF(Просчет!I68='Смета в налоговую'!C53,Просчет!H68,""),IF(Просчет!I69='Смета в налоговую'!C53,Просчет!H69,""),IF(Просчет!I70='Смета в налоговую'!C53,Просчет!H70,""),IF(Просчет!I71='Смета в налоговую'!C53,Просчет!H71,""),IF(Просчет!I72='Смета в налоговую'!C53,Просчет!H72,""),IF(Просчет!I73='Смета в налоговую'!C53,Просчет!H73,""),IF(Просчет!I74='Смета в налоговую'!C53,Просчет!H74,""),IF(Просчет!I75='Смета в налоговую'!C53,Просчет!H75,""),IF(Просчет!I76='Смета в налоговую'!C53,Просчет!H76,""),IF(Просчет!I77='Смета в налоговую'!C53,Просчет!H77,""),IF(Просчет!I78='Смета в налоговую'!C53,Просчет!H78,""),IF(Просчет!I56='Смета в налоговую'!C53,Просчет!H56,""),IF(Просчет!I57='Смета в налоговую'!C53,Просчет!H57,""),IF(Просчет!I58='Смета в налоговую'!C53,Просчет!H58,""),IF(Просчет!I59='Смета в налоговую'!C53,Просчет!H59,""),IF(Просчет!I60='Смета в налоговую'!C53,Просчет!H60,""),IF(Просчет!I61='Смета в налоговую'!C53,Просчет!H61,"")) | C53: Брус сухой, нестроганый 150х150 мм | D53: =0.15*0.15*6*(Просчет!B86+Просчет!B47) -> 0 | E53: м3 | F53: 13500 | G53: =F53/1.25*0.55 -> 5940 | H53: =(F53+G53)*D53 -> 0
B54: =_xlfn.TEXTJOIN(", ",,IF(Просчет!I63='Смета в налоговую'!C54,Просчет!H63,""),IF(Просчет!I64='Смета в налоговую'!C54,Просчет!H64,""),IF(Просчет!I65='Смета в налоговую'!C54,Просчет!H65,""),IF(Просчет!I66='Смета в налоговую'!C54,Просчет!H66,""),IF(Просчет!I67='Смета в налоговую'!C54,Просчет!H67,""),IF(Просчет!I68='Смета в налоговую'!C54,Просчет!H68,""),IF(Просчет!I69='Смета в налоговую'!C54,Просчет!H69,""),IF(Просчет!I70='Смета в налоговую'!C54,Просчет!H70,""),IF(Просчет!I71='Смета в налоговую'!C54,Просчет!H71,""),IF(Просчет!I72='Смета в налоговую'!C54,Просчет!H72,""),IF(Просчет!I73='Смета в налоговую'!C54,Просчет!H73,""),IF(Просчет!I74='Смета в налоговую'!C54,Просчет!H74,""),IF(Просчет!I75='Смета в налоговую'!C54,Просчет!H75,""),IF(Просчет!I76='Смета в налоговую'!C54,Просчет!H76,""),IF(Просчет!I77='Смета в налоговую'!C54,Просчет!H77,""),IF(Просчет!I78='Смета в налоговую'!C54,Просчет!H78,""),IF(Просчет!I56='Смета в налоговую'!C54,Просчет!H56,""),IF(Просчет!I57='Смета в налоговую'!C54,Просчет!H57,""),IF(Просчет!I58='Смета в налоговую'!C54,Просчет!H58,""),IF(Просчет!I59='Смета в налоговую'!C54,Просчет!H59,""),IF(Просчет!I60='Смета в налоговую'!C54,Просчет!H60,""),IF(Просчет!I61='Смета в налоговую'!C54,Просчет!H61,""),IF(Просчет!I62='Смета в налоговую'!C54,Просчет!H62,"")) | C54: Брус сухой, нестроганый 150х200 мм | D54: =0.15*0.2*6*(Просчет!B87+Просчет!B48) -> 0 | E54: м3 | F54: 13500 | G54: =F54/1.25*0.55 -> 5940 | H54: =(F54+G54)*D54 -> 0
B55: =_xlfn.TEXTJOIN(", ",,IF(Просчет!I64='Смета в налоговую'!C55,Просчет!H64,""),IF(Просчет!I65='Смета в налоговую'!C55,Просчет!H65,""),IF(Просчет!I66='Смета в налоговую'!C55,Просчет!H66,""),IF(Просчет!I67='Смета в налоговую'!C55,Просчет!H67,""),IF(Просчет!I68='Смета в налоговую'!C55,Просчет!H68,""),IF(Просчет!I69='Смета в налоговую'!C55,Просчет!H69,""),IF(Просчет!I70='Смета в налоговую'!C55,Просчет!H70,""),IF(Просчет!I71='Смета в налоговую'!C55,Просчет!H71,""),IF(Просчет!I72='Смета в налоговую'!C55,Просчет!H72,""),IF(Просчет!I73='Смета в налоговую'!C55,Просчет!H73,""),IF(Просчет!I74='Смета в налоговую'!C55,Просчет!H74,""),IF(Просчет!I75='Смета в налоговую'!C55,Просчет!H75,""),IF(Просчет!I76='Смета в налоговую'!C55,Просчет!H76,""),IF(Просчет!I77='Смета в налоговую'!C55,Просчет!H77,""),IF(Просчет!I78='Смета в налоговую'!C55,Просчет!H78,""),IF(Просчет!I56='Смета в налоговую'!C55,Просчет!H56,""),IF(Просчет!I57='Смета в налоговую'!C55,Просчет!H57,""),IF(Просчет!I58='Смета в налоговую'!C55,Просчет!H58,""),IF(Просчет!I59='Смета в налоговую'!C55,Просчет!H59,""),IF(Просчет!I60='Смета в налоговую'!C55,Просчет!H60,""),IF(Просчет!I61='Смета в налоговую'!C55,Просчет!H61,""),IF(Просчет!I62='Смета в налоговую'!C55,Просчет!H62,""),IF(Просчет!I63='Смета в налоговую'!C55,Просчет!H63,"")) | C55: Брус сухой, нестроганый 200х200 мм | D55: =0.2*0.2*6*(Просчет!B88+Просчет!B49) -> 0 | E55: м3 | F55: 13500 | G55: =F55/1.25*0.55 -> 5940 | H55: =(F55+G55)*D55 -> 0
B56: =_xlfn.TEXTJOIN(", ",,IF(Просчет!I65='Смета в налоговую'!C56,Просчет!H65,""),IF(Просчет!I66='Смета в налоговую'!C56,Просчет!H66,""),IF(Просчет!I67='Смета в налоговую'!C56,Просчет!H67,""),IF(Просчет!I68='Смета в налоговую'!C56,Просчет!H68,""),IF(Просчет!I69='Смета в налоговую'!C56,Просчет!H69,""),IF(Просчет!I70='Смета в налоговую'!C56,Просчет!H70,""),IF(Просчет!I71='Смета в налоговую'!C56,Просчет!H71,""),IF(Просчет!I72='Смета в налоговую'!C56,Просчет!H72,""),IF(Просчет!I73='Смета в налоговую'!C56,Просчет!H73,""),IF(Просчет!I74='Смета в налоговую'!C56,Просчет!H74,""),IF(Просчет!I75='Смета в налоговую'!C56,Просчет!H75,""),IF(Просчет!I76='Смета в налоговую'!C56,Просчет!H76,""),IF(Просчет!I77='Смета в налоговую'!C56,Просчет!H77,""),IF(Просчет!I78='Смета в налоговую'!C56,Просчет!H78,""),IF(Просчет!I56='Смета в налоговую'!C56,Просчет!H56,""),IF(Просчет!I57='Смета в налоговую'!C56,Просчет!H57,""),IF(Просчет!I58='Смета в налоговую'!C56,Просчет!H58,""),IF(Просчет!I59='Смета в налоговую'!C56,Просчет!H59,""),IF(Просчет!I60='Смета в налоговую'!C56,Просчет!H60,""),IF(Просчет!I61='Смета в налоговую'!C56,Просчет!H61,""),IF(Просчет!I62='Смета в налоговую'!C56,Просчет!H62,""),IF(Просчет!I63='Смета в налоговую'!C56,Просчет!H63,""),IF(Просчет!I64='Смета в налоговую'!C56,Просчет!H64,"")) | C56: Брус сухой, строганый 20х40 мм | D56: =0.02*0.04*3*Просчет!B90 -> 0 | E56: м3 | F56: 16500 | G56: =F56/1.25*0.55 -> 7260 | H56: =(F56+G56)*D56 -> 0
B57: =_xlfn.TEXTJOIN(", ",,IF(Просчет!I66='Смета в налоговую'!C57,Просчет!H66,""),IF(Просчет!I67='Смета в налоговую'!C57,Просчет!H67,""),IF(Просчет!I68='Смета в налоговую'!C57,Просчет!H68,""),IF(Просчет!I69='Смета в налоговую'!C57,Просчет!H69,""),IF(Просчет!I70='Смета в налоговую'!C57,Просчет!H70,""),IF(Просчет!I71='Смета в налоговую'!C57,Просчет!H71,""),IF(Просчет!I72='Смета в налоговую'!C57,Просчет!H72,""),IF(Просчет!I73='Смета в налоговую'!C57,Просчет!H73,""),IF(Просчет!I74='Смета в налоговую'!C57,Просчет!H74,""),IF(Просчет!I75='Смета в налоговую'!C57,Просчет!H75,""),IF(Просчет!I76='Смета в налоговую'!C57,Просчет!H76,""),IF(Просчет!I77='Смета в налоговую'!C57,Просчет!H77,""),IF(Просчет!I78='Смета в налоговую'!C57,Просчет!H78,""),IF(Просчет!I56='Смета в налоговую'!C57,Просчет!H56,""),IF(Просчет!I57='Смета в налоговую'!C57,Просчет!H57,""),IF(Просчет!I58='Смета в налоговую'!C57,Просчет!H58,""),IF(Просчет!I59='Смета в налоговую'!C57,Просчет!H59,""),IF(Просчет!I60='Смета в налоговую'!C57,Просчет!H60,""),IF(Просчет!I61='Смета в налоговую'!C57,Просчет!H61,""),IF(Просчет!I62='Смета в налоговую'!C57,Просчет!H62,""),IF(Просчет!I63='Смета в налоговую'!C57,Просчет!H63,""),IF(Просчет!I64='Смета в налоговую'!C57,Просчет!H64,""),IF(Просчет!I65='Смета в налоговую'!C57,Просчет!H65,"")) | C57: Брус сухой, строганый 20х90 мм | D57: =0.02*0.09*6*Просчет!B91 -> 1.296 | E57: м3 | F57: 16500 | G57: =F57/1.25*0.55 -> 7260 | H57: =(F57+G57)*D57 -> 30792.96
B58: =_xlfn.TEXTJOIN(", ",,IF(Просчет!I67='Смета в налоговую'!C58,Просчет!H67,""),IF(Просчет!I68='Смета в налоговую'!C58,Просчет!H68,""),IF(Просчет!I69='Смета в налоговую'!C58,Просчет!H69,""),IF(Просчет!I70='Смета в налоговую'!C58,Просчет!H70,""),IF(Просчет!I71='Смета в налоговую'!C58,Просчет!H71,""),IF(Просчет!I72='Смета в налоговую'!C58,Просчет!H72,""),IF(Просчет!I73='Смета в налоговую'!C58,Просчет!H73,""),IF(Просчет!I74='Смета в налоговую'!C58,Просчет!H74,""),IF(Просчет!I75='Смета в налоговую'!C58,Просчет!H75,""),IF(Просчет!I76='Смета в налоговую'!C58,Просчет!H76,""),IF(Просчет!I77='Смета в налоговую'!C58,Просчет!H77,""),IF(Просчет!I78='Смета в налоговую'!C58,Просчет!H78,""),IF(Просчет!I56='Смета в налоговую'!C58,Просчет!H56,""),IF(Просчет!I57='Смета в налоговую'!C58,Просчет!H57,""),IF(Просчет!I58='Смета в налоговую'!C58,Просчет!H58,""),IF(Просчет!I59='Смета в налоговую'!C58,Просчет!H59,""),IF(Просчет!I60='Смета в налоговую'!C58,Просчет!H60,""),IF(Просчет!I61='Смета в налоговую'!C58,Просчет!H61,""),IF(Просчет!I62='Смета в налоговую'!C58,Просчет!H62,""),IF(Просчет!I63='Смета в налоговую'!C58,Просчет!H63,""),IF(Просчет!I64='Смета в налоговую'!C58,Просчет!H64,""),IF(Просчет!I65='Смета в налоговую'!C58,Просчет!H65,""),IF(Просчет!I66='Смета в налоговую'!C58,Просчет!H66,"")) | C58: Брус 2-го сорта,сухой, строганый 20х90 мм | D58: =0.02*0.09*6*Просчет!B92 -> 0 | E58: м3 | F58: 11125 | G58: =F58/1.25*0.55 -> 4895 | H58: =(F58+G58)*D58 -> 0
B59: =_xlfn.TEXTJOIN(", ",,IF(Просчет!I68='Смета в налоговую'!C59,Просчет!H68,""),IF(Просчет!I69='Смета в налоговую'!C59,Просчет!H69,""),IF(Просчет!I70='Смета в налоговую'!C59,Просчет!H70,""),IF(Просчет!I71='Смета в налоговую'!C59,Просчет!H71,""),IF(Просчет!I72='Смета в налоговую'!C59,Просчет!H72,""),IF(Просчет!I73='Смета в налоговую'!C59,Просчет!H73,""),IF(Просчет!I74='Смета в налоговую'!C59,Просчет!H74,""),IF(Просчет!I75='Смета в налоговую'!C59,Просчет!H75,""),IF(Просчет!I76='Смета в налоговую'!C59,Просчет!H76,""),IF(Просчет!I77='Смета в налоговую'!C59,Просчет!H77,""),IF(Просчет!I78='Смета в налоговую'!C59,Просчет!H78,""),IF(Просчет!I56='Смета в налоговую'!C59,Просчет!H56,""),IF(Просчет!I57='Смета в налоговую'!C59,Просчет!H57,""),IF(Просчет!I58='Смета в налоговую'!C59,Просчет!H58,""),IF(Просчет!I59='Смета в налоговую'!C59,Просчет!H59,""),IF(Просчет!I60='Смета в налоговую'!C59,Просчет!H60,""),IF(Просчет!I61='Смета в налоговую'!C59,Просчет!H61,""),IF(Просчет!I62='Смета в налоговую'!C59,Просчет!H62,""),IF(Просчет!I63='Смета в налоговую'!C59,Просчет!H63,""),IF(Просчет!I64='Смета в налоговую'!C59,Просчет!H64,""),IF(Просчет!I65='Смета в налоговую'!C59,Просчет!H65,""),IF(Просчет!I66='Смета в налоговую'!C59,Просчет!H66,""),IF(Просчет!I67='Смета в налоговую'!C59,Просчет!H67,"")) | C59: Брус сухой, строганый 40х50 мм | D59: =0.04*0.05*3*Просчет!B93 -> 1.188 | E59: м3 | F59: 16500 | G59: =F59/1.25*0.55 -> 7260 | H59: =(F59+G59)*D59 -> 28226.88
B60: =_xlfn.TEXTJOIN(", ",,IF(Просчет!I69='Смета в налоговую'!C60,Просчет!H69,""),IF(Просчет!I70='Смета в налоговую'!C60,Просчет!H70,""),IF(Просчет!I71='Смета в налоговую'!C60,Просчет!H71,""),IF(Просчет!I72='Смета в налоговую'!C60,Просчет!H72,""),IF(Просчет!I73='Смета в налоговую'!C60,Просчет!H73,""),IF(Просчет!I74='Смета в налоговую'!C60,Просчет!H74,""),IF(Просчет!I75='Смета в налоговую'!C60,Просчет!H75,""),IF(Просчет!I76='Смета в налоговую'!C60,Просчет!H76,""),IF(Просчет!I77='Смета в налоговую'!C60,Просчет!H77,""),IF(Просчет!I78='Смета в налоговую'!C60,Просчет!H78,""),IF(Просчет!I56='Смета в налоговую'!C60,Просчет!H56,""),IF(Просчет!I57='Смета в налоговую'!C60,Просчет!H57,""),IF(Просчет!I58='Смета в налоговую'!C60,Просчет!H58,""),IF(Просчет!I59='Смета в налоговую'!C60,Просчет!H59,""),IF(Просчет!I60='Смета в налоговую'!C60,Просчет!H60,""),IF(Просчет!I61='Смета в налоговую'!C60,Просчет!H61,""),IF(Просчет!I62='Смета в налоговую'!C60,Просчет!H62,""),IF(Просчет!I63='Смета в налоговую'!C60,Просчет!H63,""),IF(Просчет!I64='Смета в налоговую'!C60,Просчет!H64,""),IF(Просчет!I65='Смета в налоговую'!C60,Просчет!H65,""),IF(Просчет!I66='Смета в налоговую'!C60,Просчет!H66,""),IF(Просчет!I67='Смета в налоговую'!C60,Просчет!H67,""),IF(Просчет!I68='Смета в налоговую'!C60,Просчет!H68,"")) | C60: Брус сухой, строганый 40х90 мм | D60: =0.04*0.09*6*(Просчет!B95+Просчет!B50) -> 0.54 | E60: м3 | F60: 16500 | G60: =F60/1.25*0.55 -> 7260 | H60: =(F60+G60)*D60 -> 12830.4
B61: =_xlfn.TEXTJOIN(", ",,IF(Просчет!I70='Смета в налоговую'!C61,Просчет!H70,""),IF(Просчет!I71='Смета в налоговую'!C61,Просчет!H71,""),IF(Просчет!I72='Смета в налоговую'!C61,Просчет!H72,""),IF(Просчет!I73='Смета в налоговую'!C61,Просчет!H73,""),IF(Просчет!I74='Смета в налоговую'!C61,Просчет!H74,""),IF(Просчет!I75='Смета в налоговую'!C61,Просчет!H75,""),IF(Просчет!I76='Смета в налоговую'!C61,Просчет!H76,""),IF(Просчет!I77='Смета в налоговую'!C61,Просчет!H77,""),IF(Просчет!I78='Смета в налоговую'!C61,Просчет!H78,""),IF(Просчет!I56='Смета в налоговую'!C61,Просчет!H56,""),IF(Просчет!I57='Смета в налоговую'!C61,Просчет!H57,""),IF(Просчет!I58='Смета в налоговую'!C61,Просчет!H58,""),IF(Просчет!I59='Смета в налоговую'!C61,Просчет!H59,""),IF(Просчет!I60='Смета в налоговую'!C61,Просчет!H60,""),IF(Просчет!I61='Смета в налоговую'!C61,Просчет!H61,""),IF(Просчет!I62='Смета в налоговую'!C61,Просчет!H62,""),IF(Просчет!I63='Смета в налоговую'!C61,Просчет!H63,""),IF(Просчет!I64='Смета в налоговую'!C61,Просчет!H64,""),IF(Просчет!I65='Смета в налоговую'!C61,Просчет!H65,""),IF(Просчет!I66='Смета в налоговую'!C61,Просчет!H66,""),IF(Просчет!I67='Смета в налоговую'!C61,Просчет!H67,""),IF(Просчет!I68='Смета в налоговую'!C61,Просчет!H68,""),IF(Просчет!I69='Смета в налоговую'!C61,Просчет!H69,"")) | C61: Брус сухой, строганый 40х140 мм | D61: =0.04*0.14*6*(Просчет!B97+Просчет!B52) -> 1.1088 | E61: м3 | F61: 16500 | G61: =F61/1.25*0.55 -> 7260 | H61: =(F61+G61)*D61 -> 26345.088
B62: =_xlfn.TEXTJOIN(", ",,IF(Просчет!I71='Смета в налоговую'!C62,Просчет!H71,""),IF(Просчет!I72='Смета в налоговую'!C62,Просчет!H72,""),IF(Просчет!I73='Смета в налоговую'!C62,Просчет!H73,""),IF(Просчет!I74='Смета в налоговую'!C62,Просчет!H74,""),IF(Просчет!I75='Смета в налоговую'!C62,Просчет!H75,""),IF(Просчет!I76='Смета в налоговую'!C62,Просчет!H76,""),IF(Просчет!I77='Смета в налоговую'!C62,Просчет!H77,""),IF(Просчет!I78='Смета в налоговую'!C62,Просчет!H78,""),IF(Просчет!I56='Смета в налоговую'!C62,Просчет!H56,""),IF(Просчет!I57='Смета в налоговую'!C62,Просчет!H57,""),IF(Просчет!I58='Смета в налоговую'!C62,Просчет!H58,""),IF(Просчет!I59='Смета в налоговую'!C62,Просчет!H59,""),IF(Просчет!I60='Смета в налоговую'!C62,Просчет!H60,""),IF(Просчет!I61='Смета в налоговую'!C62,Просчет!H61,""),IF(Просчет!I62='Смета в налоговую'!C62,Просчет!H62,""),IF(Просчет!I63='Смета в налоговую'!C62,Просчет!H63,""),IF(Просчет!I64='Смета в налоговую'!C62,Просчет!H64,""),IF(Просчет!I65='Смета в налоговую'!C62,Просчет!H65,""),IF(Просчет!I66='Смета в налоговую'!C62,Просчет!H66,""),IF(Просчет!I67='Смета в налоговую'!C62,Просчет!H67,""),IF(Просчет!I68='Смета в налоговую'!C62,Просчет!H68,""),IF(Просчет!I69='Смета в налоговую'!C62,Просчет!H69,""),IF(Просчет!I70='Смета в налоговую'!C62,Просчет!H70,"")) | C62: Брус сухой, строганый 40х190 мм | D62: =0.04*0.19*6*(Просчет!B99+Просчет!B54) -> 0 | E62: м3 | F62: 16500 | G62: =F62/1.25*0.55 -> 7260 | H62: =(F62+G62)*D62 -> 0
B63: Сборка в лапу профилированного бруса | C63: Профрофилированный брус (сборка в лапу) 195х145 мм | D63: =0.195*0.145*6*Просчет!B101 -> 0 | E63: м3 | F63: 14125 | G63: =F63/1.25*0.55 -> 6215 | H63: =(F63+G63)*D63 -> 0
B64: Сборка в лапу профилированного бруса | C64: Профрофилированный брус (сборка в лапу) 145х145 мм | D64: =0.145*0.145*6*Просчет!B102 -> 0 | E64: м3 | F64: 14125 | G64: =F64/1.25*0.55 -> 6215 | H64: =(F64+G64)*D64 -> 0
B65: Сборка в лапу профилированного бруса | C65: Профрофилированный брус (сборка в лапу) 95х145 мм | D65: =0.095*0.145*6*Просчет!B103 -> 0 | E65: м3 | F65: 14125 | G65: =F65/1.25*0.55 -> 6215 | H65: =(F65+G65)*D65 -> 0
B66: Сборка в лапу профилированного бруса | C66: Профрофилированный брус (сборка в лапу), сухой 195х145 мм | D66: =0.195*0.145*6*Просчет!B104 -> 0 | E66: м3 | F66: 17875 | G66: =F66/1.25*0.55 -> 7865 | H66: =(F66+G66)*D66 -> 0
B67: Сборка в лапу профилированного бруса | C67: Профрофилированный брус (сборка в лапу), сухой 145х145 мм | D67: =0.145*0.145*6*Просчет!B105 -> 0 | E67: м3 | F67: 17875 | G67: =F67/1.25*0.55 -> 7865 | H67: =(F67+G67)*D67 -> 0
B68: Сборка в лапу профилированного бруса | C68: Профрофилированный брус (сборка в лапу), сухой 95х145 мм | D68: =0.095*0.145*6*Просчет!B106 -> 0 | E68: м3 | F68: 17875 | G68: =F68/1.25*0.55 -> 7865 | H68: =(F68+G68)*D68 -> 0
B69: Сборка в чашу профилированного бруса | C69: Профрофилированный брус (сборка в чашу), сухой 195х145 мм | D69: =Просчет!B108 -> 0 | E69: м3 | F69: 17750 | G69: =F69/1.25*0.55 -> 7810 | H69: =(F69+G69)*D69 -> 0 | J69: сборка в чашу из сырого = 14375р/м3
B70: Сборка в чашу профилированного бруса | C70: Профрофилированный брус (сборка в чашу), сухой 145х145 мм | D70: =Просчет!B109 -> 0 | E70: м3 | F70: 17750 | G70: =F70/1.25*0.55 -> 7810 | H70: =(F70+G70)*D70 -> 0
B71: Сборка в чашу профилированного бруса | C71: Профрофилированный брус (сборка в чашу), сухой 95х145 мм | D71: =Просчет!B110 -> 0 | E71: м3 | F71: 17750 | G71: =F71/1.25*0.55 -> 7810 | H71: =(F71+G71)*D71 -> 0
B72: Сборка оцилиндрованного бревна | C72: Оцилиндрованное бревно ф18 | D72: =Просчет!B111 -> 0 | E72: м3 | F72: 11000 | G72: =F72/1.25*0.55 -> 4840 | H72: =(F72+G72)*D72 -> 0
B73: Сборка оцилиндрованного бревна | C73: Оцилиндрованное бревно ф20 | D73: =Просчет!B112 -> 0 | E73: м3 | F73: 11000 | G73: =F73/1.25*0.55 -> 4840 | H73: =(F73+G73)*D73 -> 0
B74: Сборка оцилиндрованного бревна | C74: Оцилиндрованное бревно ф22 | D74: =Просчет!B113 -> 0 | E74: м3 | F74: 11000 | G74: =F74/1.25*0.55 -> 4840 | H74: =(F74+G74)*D74 -> 0
B75: Сборка оцилиндрованного бревна | C75: Оцилиндрованное бревно ф24 | D75: =Просчет!B114 -> 0 | E75: м3 | F75: 11000 | G75: =F75/1.25*0.55 -> 4840 | H75: =(F75+G75)*D75 -> 0
B76: Сборка оцилиндрованного бревна | C76: Оцилиндрованное бревно ф24 (финский профиль) | D76: =Просчет!B115 -> 0 | E76: м3 | G76: =F76/1.25*0.55 -> 0 | H76: =(F76+G76)*D76 -> 0
B77: Сборка оцилиндрованного бревна | C77: Оцилиндрованное бревно ф26 | D77: =Просчет!B116 -> 0 | E77: м3 | G77: =F77/1.25*0.55 -> 0 | H77: =(F77+G77)*D77 -> 0
B78: Антисептирование пиломатериала | C78: =Просчет!A12 -> Антисептик 3TREE BIO 10кг | D78: =IF(Просчет!B12>0,1,0) -> 1 | E78: компл. | F78: =Просчет!G12 -> 920 | G78: =F78/1.25*0.55 -> 404.8 | H78: =(F78+G78)*D78 -> 1324.8
A79: =A23+1 -> 3 | B79: Устройство кровли
B80: Устройство покрытия кровли | C80: Оцинкованный профнастил | D80: =Просчет!B227 -> 0 | E80: м2 | F80: 488 | G80: =F80/1.25*0.55 -> 214.72 | H80: =(F80+G80)*D80 -> 0
B81: Устройство покрытия кровли | C81: Крашенный профнастил | D81: =Просчет!B228 -> 164 | E81: м2 | F81: 713 | G81: =F81/1.25*0.55 -> 313.72 | H81: =(F81+G81)*D81 -> 168382.08
B82: Устройство покрытия кровли | C82: Металлочерепица | D82: =Просчет!B229 -> 0 | E82: м2 | F82: 750 | G82: =F82/1.25*0.55 -> 330 | H82: =(F82+G82)*D82 -> 0
B83: Устройство покрытия кровли | C83: Гибкая черепица | D83: =Просчет!B230 -> 0 | E83: м2 | G83: =F83/1.25*0.55 -> 0 | H83: =(F83+G83)*D83 -> 0
B84: Устройство водосточной системы | C84: Водосточная система ПВХ на металлических кронштейнах | D84: =IF(Просчет!B231>0,1,0) -> 1 | E84: компл. | G84: =F84/1.25*0.55 -> 0 | H84: =(F84+G84)*D84 -> 0
B85: Устройство водосточной системы | C85: Водосточная система ПВХ на металлических кронштейнах | D85: =IF(Просчет!B232>0,1,0) -> 0 | E85: компл. | G85: =F85/1.25*0.55 -> 0 | H85: =(F85+G85)*D85 -> 0
B86: Устройство снегозадержателя | C86: Снегозадержатель | D86: =IF(Просчет!B233>0,1,0) -> 0 | E86: компл. | G86: =F86/1.25*0.55 -> 0 | H86: =(F86+G86)*D86 -> 0
B87: =_xlfn.TEXTJOIN(", ",,IF(Просчет!I80='Смета в налоговую'!C87,Просчет!H80,""),IF(Просчет!I81='Смета в налоговую'!C87,Просчет!H81,""),IF(Просчет!I82='Смета в налоговую'!C87,Просчет!H82,""),IF(Просчет!I83='Смета в налоговую'!C87,Просчет!H83,""),IF(Просчет!I84='Смета в налоговую'!C87,Просчет!H84,""),IF(Просчет!I85='Смета в налоговую'!C87,Просчет!H85,""),IF(Просчет!I86='Смета в налоговую'!C87,Просчет!H86,"")) | C87: Сайдинг | D87: =Просчет!B234 -> 0 | E87: м2 | G87: =F87/1.25*0.55 -> 0 | H87: =(F87+G87)*D87 -> 0
B88: =_xlfn.TEXTJOIN(", ",,IF(Просчет!I81='Смета в налоговую'!C88,Просчет!H81,""),IF(Просчет!I82='Смета в налоговую'!C88,Просчет!H82,""),IF(Просчет!I83='Смета в налоговую'!C88,Просчет!H83,""),IF(Просчет!I84='Смета в налоговую'!C88,Просчет!H84,""),IF(Просчет!I85='Смета в налоговую'!C88,Просчет!H85,""),IF(Просчет!I86='Смета в налоговую'!C88,Просчет!H86,""),IF(Просчет!I80='Смета в налоговую'!C88,Просчет!H80,"")) | C88: Вагонка 90х12,5 - 6м, Сорт АВ | D88: =Просчет!B134 -> 0 | E88: м2 | F88: 275 | G88: =F88/1.25*0.55 -> 121 | H88: =(F88+G88)*D88 -> 0
B89: =_xlfn.TEXTJOIN(", ",,IF(Просчет!I82='Смета в налоговую'!C89,Просчет!H82,""),IF(Просчет!I83='Смета в налоговую'!C89,Просчет!H83,""),IF(Просчет!I84='Смета в налоговую'!C89,Просчет!H84,""),IF(Просчет!I85='Смета в налоговую'!C89,Просчет!H85,""),IF(Просчет!I86='Смета в налоговую'!C89,Просчет!H86,""),IF(Просчет!I80='Смета в налоговую'!C89,Просчет!H80,""),IF(Просчет!I81='Смета в налоговую'!C89,Просчет!H81,"")) | C89: Вагонка 90х12,5 - 6м, Сорт Эконом | D89: =Просчет!B136 -> 0 | E89: м2 | F89: 194 | G89: =F89/1.25*0.55 -> 85.36 | H89: =(F89+G89)*D89 -> 0
B90: =_xlfn.TEXTJOIN(", ",,IF(Просчет!I83='Смета в налоговую'!C90,Просчет!H83,""),IF(Просчет!I84='Смета в налоговую'!C90,Просчет!H84,""),IF(Просчет!I85='Смета в налоговую'!C90,Просчет!H85,""),IF(Просчет!I86='Смета в налоговую'!C90,Просчет!H86,""),IF(Просчет!I80='Смета в налоговую'!C90,Просчет!H80,""),IF(Просчет!I81='Смета в налоговую'!C90,Просчет!H81,""),IF(Просчет!I82='Смета в налоговую'!C90,Просчет!H82,"")) | C90: Рау-хаус 135х16- 6м, Сорт АВ | D90: =Просчет!B137 -> 99 | E90: м2 | F90: 450 | G90: =F90/1.25*0.55 -> 198 | H90: =(F90+G90)*D90 -> 64152
B91: =_xlfn.TEXTJOIN(", ",,IF(Просчет!I84='Смета в налоговую'!C91,Просчет!H84,""),IF(Просчет!I85='Смета в налоговую'!C91,Просчет!H85,""),IF(Просчет!I86='Смета в налоговую'!C91,Просчет!H86,""),IF(Просчет!I80='Смета в налоговую'!C91,Просчет!H80,""),IF(Просчет!I81='Смета в налоговую'!C91,Просчет!H81,""),IF(Просчет!I82='Смета в налоговую'!C91,Просчет!H82,""),IF(Просчет!I83='Смета в налоговую'!C91,Просчет!H83,"")) | C91: Софит перфорированный 50/50 | D91: =Просчет!B235 -> 0 | E91: м2 | G91: =F91/1.25*0.55 -> 0 | H91: =(F91+G91)*D91 -> 0
B92: Устройство вентиляционных решеток | C92: Вентиляционная решетка | D92: =Просчет!B236 -> 0 | E92: шт | F92: 500 | G92: =F92/1.25*0.55 -> 220 | H92: =(F92+G92)*D92 -> 0
A93: =A79+1 -> 4 | B93: Паро/гидроизоляция
B94: Гидроизоляция | C94: Спанизол А | D94: =Просчет!B243+Просчет!B244*0.5 -> 0 | E94: шт | F94: 938 | G94: =F94/1.25*0.55 -> 412.72 | H94: =(F94+G94)*D94 -> 0
B95: Пароизоляция | C95: Фольгированная пароизоляция | D95: =Просчет!B278 -> 0 | E95: шт | F95: 900 | G95: =F95/1.25*0.55 -> 396 | H95: =(F95+G95)*D95 -> 0
B96: Пароизоляция | C96: Спанизол В | D96: =Просчет!B245+Просчет!B246*0.5 -> 0 | E96: шт | F96: 788 | G96: =F96/1.25*0.55 -> 346.72 | H96: =(F96+G96)*D96 -> 0
B97: Гидроизоляция кровли | C97: Спанизол АМ | D97: =Просчет!B247+Просчет!B248*0.5 -> 0 | E97: шт | F97: 2313 | G97: =F97/1.25*0.55 -> 1017.72 | H97: =(F97+G97)*D97 -> 0
B98: Гидроизоляция кровли | C98: Спанизол D | D98: =Просчет!B249+Просчет!B250*0.5 -> 0 | E98: шт | F98: 875 | G98: =F98/1.25*0.55 -> 385 | H98: =(F98+G98)*D98 -> 0
B99: Гидроизоляция | C99: Ondutiss Smart A | D99: =Просчет!B251 -> 3 | E99: шт | F99: 2194 | G99: =F99/1.25*0.55 -> 965.36 | H99: =(F99+G99)*D99 -> 9478.08
B100: Пароизоляция | C100: Ondutiss Smart B | D100: =Просчет!B252 -> 0.5 | E100: шт | F100: 1735 | G100: =F100/1.25*0.55 -> 763.4 | H100: =(F100+G100)*D100 -> 1249.2
B101: Гидроизоляция кровли | C101: Ondutiss Smart SA | D101: =Просчет!B253 -> 3 | E101: шт | F101: 3905 | G101: =F101/1.25*0.55 -> 1718.2 | H101: =(F101+G101)*D101 -> 16869.6
A102: =A93+1 -> 5 | B102: Утепление
B103: =_xlfn.TEXTJOIN(", ",,IF(Просчет!I88='Смета в налоговую'!C103,Просчет!H88,""),IF(Просчет!I89='Смета в налоговую'!C103,Просчет!H89,""),IF(Просчет!I90='Смета в налоговую'!C103,Просчет!H90,""),IF(Просчет!I91='Смета в налоговую'!C103,Просчет!H91,""),IF(Просчет!I92='Смета в налоговую'!C103,Просчет!H92,""),IF(Просчет!I93='Смета в налоговую'!C103,Просчет!H93,""),IF(Просчет!I95='Смета в налоговую'!C103,Просчет!H95,""),IF(Просчет!I97='Смета в налоговую'!C103,Просчет!H97,""),IF(Просчет!I99='Смета в налоговую'!C103,Просчет!H99,""),IF(Просчет!I100='Смета в налоговую'!C103,Просчет!H100,"")) | C103: Рулонная минеральная вата (ISOVER, 0,036Вт/м*К) | D103: =Просчет!B238 -> 29.7 | E103: =Просчет!C238 -> м3 | F103: 1382 | G103: =F103/1.25*0.55 -> 608.08 | H103: =(F103+G103)*D103 -> 59105.376
B104: =_xlfn.TEXTJOIN(", ",,IF(Просчет!I89='Смета в налоговую'!C104,Просчет!H89,""),IF(Просчет!I90='Смета в налоговую'!C104,Просчет!H90,""),IF(Просчет!I91='Смета в налоговую'!C104,Просчет!H91,""),IF(Просчет!I92='Смета в налоговую'!C104,Просчет!H92,""),IF(Просчет!I93='Смета в налоговую'!C104,Просчет!H93,""),IF(Просчет!I95='Смета в налоговую'!C104,Просчет!H95,""),IF(Просчет!I97='Смета в налоговую'!C104,Просчет!H97,""),IF(Просчет!I99='Смета в налоговую'!C104,Просчет!H99,""),IF(Просчет!I100='Смета в налоговую'!C104,Просчет!H100,""),IF(Просчет!I88='Смета в налоговую'!C104,Просчет!H88,"")) | C104: Плитная минеральная вата (ISOVER, низкой плотности, 0,035Вт/м*К) | D104: =Просчет!B240 -> 0 | E104: =Просчет!C240 -> м3 | F104: 1680 | G104: =F104/1.25*0.55 -> 739.2 | H104: =(F104+G104)*D104 -> 0
B105: =_xlfn.TEXTJOIN(", ",,IF(Просчет!I90='Смета в налоговую'!C105,Просчет!H90,""),IF(Просчет!I91='Смета в налоговую'!C105,Просчет!H91,""),IF(Просчет!I92='Смета в налоговую'!C105,Просчет!H92,""),IF(Просчет!I93='Смета в налоговую'!C105,Просчет!H93,""),IF(Просчет!I95='Смета в налоговую'!C105,Просчет!H95,""),IF(Просчет!I97='Смета в налоговую'!C105,Просчет!H97,""),IF(Просчет!I99='Смета в налоговую'!C105,Просчет!H99,""),IF(Просчет!I100='Смета в налоговую'!C105,Просчет!H100,""),IF(Просчет!I88='Смета в налоговую'!C105,Просчет!H88,""),IF(Просчет!I89='Смета в налоговую'!C105,Просчет!H89,"")) | C105: Плитная минеральная вата (ISOVER, средней плотности, 0,034Вт/м*К) | D105: =Просчет!B241 -> 0 | E105: =Просчет!C241 -> м3 | F105: 1680 | G105: =F105/1.25*0.55 -> 739.2 | H105: =(F105+G105)*D105 -> 0
B106: =_xlfn.TEXTJOIN(", ",,IF(Просчет!I91='Смета в налоговую'!C106,Просчет!H91,""),IF(Просчет!I92='Смета в налоговую'!C106,Просчет!H92,""),IF(Просчет!I93='Смета в налоговую'!C106,Просчет!H93,""),IF(Просчет!I95='Смета в налоговую'!C106,Просчет!H95,""),IF(Просчет!I97='Смета в налоговую'!C106,Просчет!H97,""),IF(Просчет!I99='Смета в налоговую'!C106,Просчет!H99,""),IF(Просчет!I100='Смета в налоговую'!C106,Просчет!H100,""),IF(Просчет!I88='Смета в налоговую'!C106,Просчет!H88,""),IF(Просчет!I89='Смета в налоговую'!C106,Просчет!H89,""),IF(Просчет!I90='Смета в налоговую'!C106,Просчет!H90,"")) | C106: =Просчет!A242 -> Пенополистерол 1180х580х50мм | D106: =1.2*0.6*0.05*Просчет!B242 -> 0 | E106: м3 | F106: 4862 | G106: =F106/1.25*0.55 -> 2139.28 | H106: =(F106+G106)*D106 -> 0
A107: =A102+1 -> 6 | B107: Наружная отделка
...

Sheet Смета для клиента
A1: Приложение №3 к договору строительного подряда №00/00 от 00.00.2020 г.
A3: № | B3: Работа | C3: Материал | D3: Кол-во | E3: Ед. изм. | F3: Стоимость ед. материал | G3: Стоимость ед. работа | H3: Итого
A4: 1 | B4: Устройство фундамента
B5: ='Смета в налоговую'!B18 -> Устройство фундамента | C5: ='Смета в налоговую'!C18 -> 0 | D5: ='Смета в налоговую'!D18 -> 0 | E5: ='Смета в налоговую'!E18 -> компл. | F5: ='Смета в налоговую'!F18 -> 0 | G5: ='Смета в налоговую'!G18 -> 0 | H5: ='Смета в налоговую'!H18 -> 0
B6: ='Смета в налоговую'!B19 -> Устройство сетки от грызунов | C6: ='Смета в налоговую'!C19 -> Сетка от грызунов 1*10м | D6: ='Смета в налоговую'!D19 -> 0 | E6: ='Смета в налоговую'!E19 -> компл. | F6: ='Смета в налоговую'!F19 -> 219 | G6: ='Смета в налоговую'!G19 -> 96.36 | H6: ='Смета в налоговую'!H19 -> 0
B7: ='Смета в налоговую'!B20 -> Геология | C7: ='Смета в налоговую'!C20 -> 0 | D7: ='Смета в налоговую'!D20 -> 0 | E7: ='Смета в налоговую'!E20 -> компл. | F7: ='Смета в налоговую'!F20 -> 0 | G7: ='Смета в налоговую'!G20 -> 0 | H7: ='Смета в налоговую'!H20 -> 0
B8: ='Смета в налоговую'!B21 -> Устройство цоколя | C8: ='Смета в налоговую'!C21 -> Материал предоставляет Заказчик | D8: ='Смета в налоговую'!D21 -> 0 | E8: ='Смета в налоговую'!E21 -> компл. | F8: ='Смета в налоговую'!F21 -> 0 | G8: ='Смета в налоговую'!G21 -> 0 | H8: ='Смета в налоговую'!H21 -> 0
B9: ='Смета в налоговую'!B22 -> Устройство цоколя | C9: ='Смета в налоговую'!C22 -> HAUBERK ТЕХНОНИКОЛЬ Терракотовый кирпич | D9: ='Смета в налоговую'!D22 -> 0 | E9: ='Смета в налоговую'!E22 -> м2 | F9: ='Смета в налоговую'!F22 -> 0 | G9: ='Смета в налоговую'!G22 -> 0 | H9: ='Смета в налоговую'!H22 -> 0
A10: =A4+1 -> 2 | B10: Устройство каркаса и стропильной системы дома
B11: ='Смета в налоговую'!B24 | C11: ='Смета в налоговую'!C24 -> Брус 25х50 мм | D11: ='Смета в налоговую'!D24 -> 0 | E11: ='Смета в налоговую'!E24 -> м3 | F11: ='Смета в налоговую'!F24 -> 11500 | G11: ='Смета в налоговую'!G24 -> 5060 | H11: ='Смета в налоговую'!H24 -> 0
B12: ='Смета в налоговую'!B25 | C12: ='Смета в налоговую'!C25 -> Брус 25х100 мм | D12: ='Смета в налоговую'!D25 -> 0 | E12: ='Смета в налоговую'!E25 -> м3 | F12: ='Смета в налоговую'!F25 -> 11500 | G12: ='Смета в налоговую'!G25 -> 5060 | H12: ='Смета в налоговую'!H25 -> 0
B13: ='Смета в налоговую'!B26 | C13: ='Смета в налоговую'!C26 -> Брус 2-го сорта 25х100 мм | D13: ='Смета в налоговую'!D26 -> 0 | E13: ='Смета в налоговую'!E26 -> м3 | F13: ='Смета в налоговую'!F26 -> 7125 | G13: ='Смета в налоговую'!G26 -> 3135 | H13: ='Смета в налоговую'!H26 -> 0
B14: ='Смета в налоговую'!B27 | C14: ='Смета в налоговую'!C27 -> Брус 25х150 мм | D14: ='Смета в налоговую'!D27 -> 0 | E14: ='Смета в налоговую'!E27 -> м3 | F14: ='Смета в налоговую'!F27 -> 11500 | G14: ='Смета в налоговую'!G27 -> 5060 | H14: ='Смета в налоговую'!H27 -> 0
B15: ='Смета в налоговую'!B28 | C15: ='Смета в налоговую'!C28 -> Брус 25х200 мм | D15: ='Смета в налоговую'!D28 -> 0 | E15: ='Смета в налоговую'!E28 -> м3 | F15: ='Смета в налоговую'!F28 -> 11500 | G15: ='Смета в налоговую'!G28 -> 5060 | H15: ='Смета в налоговую'!H28 -> 0
B16: ='Смета в налоговую'!B29 | C16: ='Смета в налоговую'!C29 -> Брус 40х50 мм | D16: ='Смета в налоговую'!D29 -> 0 | E16: ='Смета в налоговую'!E29 -> м3 | F16: ='Смета в налоговую'!F29 -> 11500 | G16: ='Смета в налоговую'!G29 -> 5060 | H16: ='Смета в налоговую'!H29 -> 0
B17: ='Смета в налоговую'!B30 | C17: ='Смета в налоговую'!C30 -> Брус 50х50 мм | D17: ='Смета в налоговую'!D30 -> 0 | E17: ='Смета в налоговую'!E30 -> м3 | F17: ='Смета в налоговую'!F30 -> 11500 | G17: ='Смета в налоговую'!G30 -> 5060 | H17: ='Смета в налоговую'!H30 -> 0
B18: ='Смета в налоговую'!B31 | C18: ='Смета в налоговую'!C31 -> Брус 50х100 мм | D18: ='Смета в налоговую'!D31 -> 0 | E18: ='Смета в налоговую'!E31 -> м3 | F18: ='Смета в налоговую'!F31 -> 11500 | G18: ='Смета в налоговую'!G31 -> 5060 | H18: ='Смета в налоговую'!H31 -> 0
B19: ='Смета в налоговую'!B32 | C19: ='Смета в налоговую'!C32 -> Брус 50х150 мм | D19: ='Смета в налоговую'!D32 -> 0 | E19: ='Смета в налоговую'!E32 -> м3 | F19: ='Смета в налоговую'!F32 -> 11500 | G19: ='Смета в налоговую'!G32 -> 5060 | H19: ='Смета в налоговую'!H32 -> 0
B20: ='Смета в налоговую'!B33 | C20: ='Смета в налоговую'!C33 -> Брус 50х200 мм | D20: ='Смета в налоговую'!D33 -> 0 | E20: ='Смета в налоговую'!E33 -> м3 | F20: ='Смета в налоговую'!F33 -> 11500 | G20: ='Смета в налоговую'!G33 -> 5060 | H20: ='Смета в налоговую'!H33 -> 0
B21: ='Смета в налоговую'!B34 | C21: ='Смета в налоговую'!C34 -> Брус 100х100 мм | D21: ='Смета в налоговую'!D34 -> 0 | E21: ='Смета в налоговую'!E34 -> м3 | F21: ='Смета в налоговую'!F34 -> 11500 | G21: ='Смета в налоговую'!G34 -> 5060 | H21: ='Смета в налоговую'!H34 -> 0
B22: ='Смета в налоговую'!B35 | C22: ='Смета в налоговую'!C35 -> Брус 100х150 мм | D22: ='Смета в налоговую'!D35 -> 0 | E22: ='Смета в налоговую'!E35 -> м3 | F22: ='Смета в налоговую'!F35 -> 11500 | G22: ='Смета в налоговую'!G35 -> 5060 | H22: ='Смета в налоговую'!H35 -> 0
... B55: ='Смета в налоговую'!B68 -> Сборка в лапу профилированного бруса | C55: ='Смета в налоговую'!C68 -> Профрофилированный брус (сборка в лапу), сухой 95х145 мм | D55: ='Смета в налоговую'!D68 -> 0 | E55: ='Смета в налоговую'!E68 -> м3 | F55: ='Смета в налоговую'!F68 -> 17875 | G55: ='Смета в налоговую'!G68 -> 7865 | H55: ='Смета в налоговую'!H68 -> 0
B56: ='Смета в налоговую'!B69 -> Сборка в чашу профилированного бруса | C56: ='Смета в налоговую'!C69 -> Профрофилированный брус (сборка в чашу), сухой 195х145 мм | D56: ='Смета в налоговую'!D69 -> 0 | E56: ='Смета в налоговую'!E69 -> м3 | F56: ='Смета в налоговую'!F69 -> 17750 | G56: ='Смета в налоговую'!G69 -> 7810 | H56: ='Смета в налоговую'!H69 -> 0 | J56: сборка в чашу из сырого = 14375р/м3
B57: ='Смета в налоговую'!B70 -> Сборка в чашу профилированного бруса | C57: ='Смета в налоговую'!C70 -> Профрофилированный брус (сборка в чашу), сухой 145х145 мм | D57: ='Смета в налоговую'!D70 -> 0 | E57: ='Смета в налоговую'!E70 -> м3 | F57: ='Смета в налоговую'!F70 -> 17750 | G57: ='Смета в налоговую'!G70 -> 7810 | H57: ='Смета в налоговую'!H70 -> 0
B58: ='Смета в налоговую'!B71 -> Сборка в чашу профилированного бруса | C58: ='Смета в налоговую'!C71 -> Профрофилированный брус (сборка в чашу), сухой 95х145 мм | D58: ='Смета в налоговую'!D71 -> 0 | E58: ='Смета в налоговую'!E71 -> м3 | F58: ='Смета в налоговую'!F71 -> 17750 | G58: ='Смета в налоговую'!G71 -> 7810 | H58: ='Смета в налоговую'!H71 -> 0
B59: ='Смета в налоговую'!B72 -> Сборка оцилиндрованного бревна | C59: ='Смета в налоговую'!C72 -> Оцилиндрованное бревно ф18 | D59: ='Смета в налоговую'!D72 -> 0 | E59: ='Смета в налоговую'!E72 -> м3 | F59: ='Смета в налоговую'!F72 -> 11000 | G59: ='Смета в налоговую'!G72 -> 4840 | H59: ='Смета в налоговую'!H72 -> 0
B60: ='Смета в налоговую'!B73 -> Сборка оцилиндрованного бревна | C60: ='Смета в налоговую'!C73 -> Оцилиндрованное бревно ф20 | D60: ='Смета в налоговую'!D73 -> 0 | E60: ='Смета в налоговую'!E73 -> м3 | F60: ='Смета в налоговую'!F73 -> 11000 | G60: ='Смета в налоговую'!G73 -> 4840 | H60: ='Смета в налоговую'!H73 -> 0
B61: ='Смета в налоговую'!B74 -> Сборка оцилиндрованного бревна | C61: ='Смета в налоговую'!C74 -> Оцилиндрованное бревно ф22 | D61: ='Смета в налоговую'!D74 -> 0 | E61: ='Смета в налоговую'!E74 -> м3 | F61: ='Смета в налоговую'!F74 -> 11000 | G61: ='Смета в налоговую'!G74 -> 4840 | H61: ='Смета в налоговую'!H74 -> 0
B62: ='Смета в налоговую'!B75 -> Сборка оцилиндрованного бревна | C62: ='Смета в налоговую'!C75 -> Оцилиндрованное бревно ф24 | D62: ='Смета в налоговую'!D75 -> 0 | E62: ='Смета в налоговую'!E75 -> м3 | F62: ='Смета в налоговую'!F75 -> 11000 | G62: ='Смета в налоговую'!G75 -> 4840 | H62: ='Смета в налоговую'!H75 -> 0
B63: ='Смета в налоговую'!B76 -> Сборка оцилиндрованного бревна | C63: ='Смета в налоговую'!C76 -> Оцилиндрованное бревно ф24 (финский профиль) | D63: ='Смета в налоговую'!D76 -> 0 | E63: ='Смета в налоговую'!E76 -> м3 | F63: ='Смета в налоговую'!F76 -> 0 | G63: ='Смета в налоговую'!G76 -> 0 | H63: ='Смета в налоговую'!H76 -> 0
B64: ='Смета в налоговую'!B77 -> Сборка оцилиндрованного бревна | C64: ='Смета в налоговую'!C77 -> Оцилиндрованное бревно ф26 | D64: ='Смета в налоговую'!D77 -> 0 | E64: ='Смета в налоговую'!E77 -> м3 | F64: ='Смета в налоговую'!F77 -> 0 | G64: ='Смета в налоговую'!G77 -> 0 | H64: ='Смета в налоговую'!H77 -> 0
B65: ='Смета в налоговую'!B78 -> Антисептирование пиломатериала | C65: ='Смета в налоговую'!C78 -> Антисептик 3TREE BIO 10кг | D65: ='Смета в налоговую'!D78 -> 1 | E65: ='Смета в налоговую'!E78 -> компл. | F65: ='Смета в налоговую'!F78 -> 920 | G65: ='Смета в налоговую'!G78 -> 404.8 | H65: ='Смета в налоговую'!H78 -> 1324.8
A66: =A10+1 -> 3 | B66: Устройство кровли
B67: ='Смета в налоговую'!B80 -> Устройство покрытия кровли | C67: ='Смета в налоговую'!C80 -> Оцинкованный профнастил | D67: ='Смета в налоговую'!D80 -> 0 | E67: ='Смета в налоговую'!E80 -> м2 | F67: ='Смета в налоговую'!F80 -> 488 | G67: ='Смета в налоговую'!G80 -> 214.72 | H67: ='Смета в налоговую'!H80 -> 0
B68: ='Смета в налоговую'!B81 -> Устройство покрытия кровли | C68: ='Смета в налоговую'!C81 -> Крашенный профнастил | D68: ='Смета в налоговую'!D81 -> 164 | E68: ='Смета в налоговую'!E81 -> м2 | F68: ='Смета в налоговую'!F81 -> 713 | G68: ='Смета в налоговую'!G81 -> 313.72 | H68: ='Смета в налоговую'!H81 -> 168382.08
B69: ='Смета в налоговую'!B82 -> Устройство покрытия кровли | C69: ='Смета в налоговую'!C82 -> Металлочерепица | D69: ='Смета в налоговую'!D82 -> 0 | E69: ='Смета в налоговую'!E82 -> м2 | F69: ='Смета в налоговую'!F82 -> 750 | G69: ='Смета в налоговую'!G82 -> 330 | H69: ='Смета в налоговую'!H82 -> 0
B70: ='Смета в налоговую'!B83 -> Устройство покрытия кровли | C70: ='Смета в налоговую'!C83 -> Гибкая черепица | D70: ='Смета в налоговую'!D83 -> 0 | E70: ='Смета в налоговую'!E83 -> м2 | F70: ='Смета в налоговую'!F83 -> 0 | G70: ='Смета в налоговую'!G83 -> 0 | H70: ='Смета в налоговую'!H83 -> 0
B71: ='Смета в налоговую'!B84 -> Устройство водосточной системы | C71: ='Смета в налоговую'!C84 -> Водосточная система ПВХ на металлических кронштейнах | D71: ='Смета в налоговую'!D84 -> 1 | E71: ='Смета в налоговую'!E84 -> компл. | F71: ='Смета в налоговую'!F84 -> 0 | G71: ='Смета в налоговую'!G84 -> 0 | H71: ='Смета в налоговую'!H84 -> 0
B72: ='Смета в налоговую'!B85 -> Устройство водосточной системы | C72: ='Смета в налоговую'!C85 -> Водосточная система ПВХ на металлических кронштейнах | D72: ='Смета в налоговую'!D85 -> 0 | E72: ='Смета в налоговую'!E85 -> компл. | F72: ='Смета в налоговую'!F85 -> 0 | G72: ='Смета в налоговую'!G85 -> 0 | H72: ='Смета в налоговую'!H85 -> 0
B73: ='Смета в налоговую'!B86 -> Устройство снегозадержателя | C73: ='Смета в налоговую'!C86 -> Снегозадержатель | D73: ='Смета в налоговую'!D86 -> 0 | E73: ='Смета в налоговую'!E86 -> компл. | F73: ='Смета в налоговую'!F86 -> 0 | G73: ='Смета в налоговую'!G86 -> 0 | H73: ='Смета в налоговую'!H86 -> 0
B74: ='Смета в налоговую'!B87 | C74: ='Смета в налоговую'!C87 -> Сайдинг | D74: ='Смета в налоговую'!D87 -> 0 | E74: ='Смета в налоговую'!E87 -> м2 | F74: ='Смета в налоговую'!F87 -> 0 | G74: ='Смета в налоговую'!G87 -> 0 | H74: ='Смета в налоговую'!H87 -> 0
B75: ='Смета в налоговую'!B88 | C75: ='Смета в налоговую'!C88 -> Вагонка 90х12,5 - 6м, Сорт АВ | D75: ='Смета в налоговую'!D88 -> 0 | E75: ='Смета в налоговую'!E88 -> м2 | F75: ='Смета в налоговую'!F88 -> 275 | G75: ='Смета в налоговую'!G88 -> 121 | H75: ='Смета в налоговую'!H88 -> 0
B76: ='Смета в налоговую'!B89 | C76: ='Смета в налоговую'!C89 -> Вагонка 90х12,5 - 6м, Сорт Эконом | D76: ='Смета в налоговую'!D89 -> 0 | E76: ='Смета в налоговую'!E89 -> м2 | F76: ='Смета в налоговую'!F89 -> 194 | G76: ='Смета в налоговую'!G89 -> 85.36 | H76: ='Смета в налоговую'!H89 -> 0
B77: ='Смета в налоговую'!B90 | C77: ='Смета в налоговую'!C90 -> Рау-хаус 135х16- 6м, Сорт АВ | D77: ='Смета в налоговую'!D90 -> 99 | E77: ='Смета в налоговую'!E90 -> м2 | F77: ='Смета в налоговую'!F90 -> 450 | G77: ='Смета в налоговую'!G90 -> 198 | H77: ='Смета в налоговую'!H90 -> 64152
B78: ='Смета в налоговую'!B91 | C78: ='Смета в налоговую'!C91 -> Софит перфорированный 50/50 | D78: ='Смета в налоговую'!D91 -> 0 | E78: ='Смета в налоговую'!E91 -> м2 | F78: ='Смета в налоговую'!F91 -> 0 | G78: ='Смета в налоговую'!G91 -> 0 | H78: ='Смета в налоговую'!H91 -> 0
B79: ='Смета в налоговую'!B92 -> Устройство вентиляционных решеток | C79: ='Смета в налоговую'!C92 -> Вентиляционная решетка | D79: ='Смета в налоговую'!D92 -> 0 | E79: ='Смета в налоговую'!E92 -> шт | F79: ='Смета в налоговую'!F92 -> 500 | G79: ='Смета в налоговую'!G92 -> 220 | H79: ='Смета в налоговую'!H92 -> 0
A80: =A66+1 -> 4 | B80: Паро/гидроизоляция
B81: ='Смета в налоговую'!B94 -> Гидроизоляция | C81: ='Смета в налоговую'!C94 -> Спанизол А | D81: ='Смета в налоговую'!D94 -> 0 | E81: ='Смета в налоговую'!E94 -> шт | F81: ='Смета в налоговую'!F94 -> 938 | G81: ='Смета в налоговую'!G94 -> 412.72 | H81: ='Смета в налоговую'!H94 -> 0
B82: ='Смета в налоговую'!B95 -> Пароизоляция | C82: ='Смета в налоговую'!C95 -> Фольгированная пароизоляция | D82: ='Смета в налоговую'!D95 -> 0 | E82: ='Смета в налоговую'!E95 -> шт | F82: ='Смета в налоговую'!F95 -> 900 | G82: ='Смета в налоговую'!G95 -> 396 | H82: ='Смета в налоговую'!H95 -> 0
B83: ='Смета в налоговую'!B96 -> Пароизоляция | C83: ='Смета в налоговую'!C96 -> Спанизол В | D83: ='Смета в налоговую'!D96 -> 0 | E83: ='Смета в налоговую'!E96 -> шт | F83: ='Смета в налоговую'!F96 -> 788 | G83: ='Смета в налоговую'!G96 -> 346.72 | H83: ='Смета в налоговую'!H96 -> 0
B84: ='Смета в налоговую'!B97 -> Гидроизоляция кровли | C84: ='Смета в налоговую'!C97 -> Спанизол АМ | D84: ='Смета в налоговую'!D97 -> 0 | E84: ='Смета в налоговую'!E97 -> шт | F84: ='Смета в налоговую'!F97 -> 2313 | G84: ='Смета в налоговую'!G97 -> 1017.72 | H84: ='Смета в налоговую'!H97 -> 0
B85: ='Смета в налоговую'!B98 -> Гидроизоляция кровли | C85: ='Смета в налоговую'!C98 -> Спанизол D | D85: ='Смета в налоговую'!D98 -> 0 | E85: ='Смета в налоговую'!E98 -> шт | F85: ='Смета в налоговую'!F98 -> 875 | G85: ='Смета в налоговую'!G98 -> 385 | H85: ='Смета в налоговую'!H98 -> 0
B86: ='Смета в налоговую'!B99 -> Гидроизоляция | C86: ='Смета в налоговую'!C99 -> Ondutiss Smart A | D86: ='Смета в налоговую'!D99 -> 3 | E86: ='Смета в налоговую'!E99 -> шт | F86: ='Смета в налоговую'!F99 -> 2194 | G86: ='Смета в налоговую'!G99 -> 965.36 | H86: ='Смета в налоговую'!H99 -> 9478.08
B87: ='Смета в налоговую'!B100 -> Пароизоляция | C87: ='Смета в налоговую'!C100 -> Ondutiss Smart B | D87: ='Смета в налоговую'!D100 -> 0.5 | E87: ='Смета в налоговую'!E100 -> шт | F87: ='Смета в налоговую'!F100 -> 1735 | G87: ='Смета в налоговую'!G100 -> 763.4 | H87: ='Смета в налоговую'!H100 -> 1249.2
B88: ='Смета в налоговую'!B101 -> Гидроизоляция кровли | C88: ='Смета в налоговую'!C101 -> Ondutiss Smart SA | D88: ='Смета в налоговую'!D101 -> 3 | E88: ='Смета в налоговую'!E101 -> шт | F88: ='Смета в налоговую'!F101 -> 3905 | G88: ='Смета в налоговую'!G101 -> 1718.2 | H88: ='Смета в налоговую'!H101 -> 16869.6
A89: =A80+1 -> 5 | B89: Утепление
B90: ='Смета в налоговую'!B103 | C90: ='Смета в налоговую'!C103 -> Рулонная минеральная вата (ISOVER, 0,036Вт/м*К) | D90: ='Смета в налоговую'!D103 -> 29.7 | E90: ='Смета в налоговую'!E103 -> м3 | F90: ='Смета в налоговую'!F103 -> 1382 | G90: ='Смета в налоговую'!G103 -> 608.08 | H90: ='Смета в налоговую'!H103 -> 59105.376
B91: ='Смета в налоговую'!B104 | C91: ='Смета в налоговую'!C104 -> Плитная минеральная вата (ISOVER, низкой плотности, 0,035Вт/м*К) | D91: ='Смета в налоговую'!D104 -> 0 | E91: ='Смета в налоговую'!E104 -> м3 | F91: ='Смета в налоговую'!F104 -> 1680 | G91: ='Смета в налоговую'!G104 -> 739.2 | H91: ='Смета в налоговую'!H104 -> 0
B92: ='Смета в налоговую'!B105 | C92: ='Смета в налоговую'!C105 -> Плитная минеральная вата (ISOVER, средней плотности, 0,034Вт/м*К) | D92: ='Смета в налоговую'!D105 -> 0 | E92: ='Смета в налоговую'!E105 -> м3 | F92: ='Смета в налоговую'!F105 -> 1680 | G92: ='Смета в налоговую'!G105 -> 739.2 | H92: ='Смета в налоговую'!H105 -> 0
B93: ='Смета в налоговую'!B106 | C93: ='Смета в налоговую'!C106 -> Пенополистерол 1180х580х50мм | D93: ='Смета в налоговую'!D106 -> 0 | E93: ='Смета в налоговую'!E106 -> м3 | F93: ='Смета в налоговую'!F106 -> 4862 | G93: ='Смета в налоговую'!G106 -> 2139.28 | H93: ='Смета в налоговую'!H106 -> 0
A94: =A89+1 -> 6 | B94: Наружная отделка
B95: ='Смета в налоговую'!B108 | C95: ='Смета в налоговую'!C108 -> Рау-хаус 135х16- 6м, Сорт АВ | D95: ='Смета в налоговую'!D108 -> 141 | E95: ='Смета в налоговую'!E108 -> м2 | F95: ='Смета в налоговую'!F108 -> 450 | G95: ='Смета в налоговую'!G108 -> 198 | H95: ='Смета в налоговую'!H108 -> 91368 | J95: нар
B96: ='Смета в налоговую'!B109 | C96: ='Смета в налоговую'!C109 -> Рау-хаус 110х16- 6м, Сорт АВ | D96: ='Смета в налоговую'!D109 -> 0 | E96: ='Смета в налоговую'!E109 -> м2 | F96: ='Смета в налоговую'!F109 -> 450 | G96: ='Смета в налоговую'!G109 -> 198 | H96: ='Смета в налоговую'!H109 -> 0 | J96: нар
B97: ='Смета в налоговую'!B110 | C97: ='Смета в налоговую'!C110 -> Террасная доска 112х24 - 6м, Сорт АВ | D97: ='Смета в налоговую'!D110 -> 0 | E97: ='Смета в налоговую'!E110 -> м2 | F97: ='Смета в налоговую'!F110 -> 525 | G97: ='Смета в налоговую'!G110 -> 231 | H97: ='Смета в налоговую'!H110 -> 0
B98: ='Смета в налоговую'!B111 | C98: ='Смета в налоговую'!C111 -> Калибровка 140х35- 6м | D98: ='Смета в налоговую'!D111 -> 0 | E98: ='Смета в налоговую'!E111 -> шт | F98: ='Смета в налоговую'!F111 -> 625 | G98: ='Смета в налоговую'!G111 -> 275 | H98: ='Смета в налоговую'!H111 -> 0
B99: ='Смета в налоговую'!B112 | C99: ='Смета в налоговую'!C112 -> Шпунтовка 90х26 - 6м, Сорт АВ | D99: ='Смета в налоговую'!D112 -> 0 | E99: ='Смета в налоговую'!E112 -> м2 | F99: ='Смета в налоговую'!F112 -> 525 | G99: ='Смета в налоговую'!G112 -> 231 | H99: ='Смета в налоговую'!H112 -> 0
B100: ='Смета в налоговую'!B113 | C100: ='Смета в налоговую'!C113 -> Шпунтовка 135х35 - 6м, Сорт АВ | D100: ='Смета в налоговую'!D113 -> 0 | E100: ='Смета в налоговую'!E113 -> м2 | F100: ='Смета в налоговую'!F113 -> 700 | G100: ='Смета в налоговую'!G113 -> 308 | H100: ='Смета в налоговую'!H113 -> 0
B101: ='Смета в налоговую'!B114 | C101: ='Смета в налоговую'!C114 -> ОСБ-3 9мм | D101: ='Смета в налоговую'!D114 -> 0 | E101: ='Смета в налоговую'!E114 -> шт | F101: ='Смета в налоговую'!F114 -> 813 | G101: ='Смета в налоговую'!G114 -> 357.72 | H101: ='Смета в налоговую'!H114 -> 0
B102: ='Смета в налоговую'!B115 | C102: ='Смета в налоговую'!C115 -> ОСБ-3 12мм | D102: ='Смета в налоговую'!D115 -> 0 | E102: ='Смета в налоговую'!E115 -> шт | F102: ='Смета в налоговую'!F115 -> 1063 | G102: ='Смета в налоговую'!G115 -> 467.72 | H102: ='Смета в налоговую'!H115 -> 0
B103: ='Смета в налоговую'!B116 | C103: ='Смета в налоговую'!C116 -> Фанера 12 | D103: ='Смета в налоговую'!D116 -> 0 | E103: ='Смета в налоговую'!E116 -> шт | F103: ='Смета в налоговую'!F116 -> 1088 | G103: ='Смета в налоговую'!G116 -> 478.72 | H103: ='Смета в налоговую'!H116 -> 0
B104: ='Смета в налоговую'!B117 | C104: ='Смета в налоговую'!C117 -> ЦСП 10 | D104: ='Смета в налоговую'!D117 -> 0 | E104: ='Смета в налоговую'!E117 -> шт | F104: ='Смета в налоговую'!F117 -> 1150 | G104: ='Смета в налоговую'!G117 -> 506 | H104: ='Смета в налоговую'!H117 -> 0
B105: ='Смета в налоговую'!B118 | C105: ='Смета в налоговую'!C118 -> ЦСП 12 | D105: ='Смета в налоговую'!D118 -> 0 | E105: ='Смета в налоговую'!E118 -> шт | F105: ='Смета в налоговую'!F118 -> 1438 | G105: ='Смета в налоговую'!G118 -> 632.72 | H105: ='Смета в налоговую'!H118 -> 0
B106: ='Смета в налоговую'!B119 | C106: ='Смета в налоговую'!C119 -> Гипрок Стронг 15мм | D106: ='Смета в налоговую'!D119 -> 0 | E106: ='Смета в налоговую'!E119 -> шт | F106: ='Смета в налоговую'!F119 -> 450 | G106: ='Смета в налоговую'!G119 -> 198 | H106: ='Смета в налоговую'!H119 -> 0
B107: ='Смета в налоговую'!B120 | C107: ='Смета в налоговую'!C120 -> Гипрок Стронг Аква 15мм | D107: ='Смета в налоговую'!D120 -> 0 | E107: ='Смета в налоговую'!E120 -> шт | F107: ='Смета в налоговую'!F120 -> 488 | G107: ='Смета в налоговую'!G120 -> 214.72 | H107: ='Смета в налоговую'!H120 -> 0
B108: ='Смета в налоговую'!B121 | C108: ='Смета в налоговую'!C121 -> GTS, 9,5мм | D108: ='Смета в налоговую'!D121 -> 0 | E108: ='Смета в налоговую'!E121 -> шт | F108: ='Смета в налоговую'!F121 -> 338 | G108: ='Смета в налоговую'!G121 -> 148.72 | H108: ='Смета в налоговую'!H121 -> 0
... B116: ='Смета в налоговую'!B129 | C116: ='Смета в налоговую'!C129 -> Блок-хаус, С (0,135) | D116: ='Смета в налоговую'!D129 -> 0 | E116: ='Смета в налоговую'!E129 -> м2 | F116: ='Смета в налоговую'!F129 -> 688 | G116: ='Смета в налоговую'!G129 -> 302.72 | H116: ='Смета в налоговую'!H129 -> 0
C117: ='Смета в налоговую'!C130 -> Укладка плитки Заказчика | D117: ='Смета в налоговую'!D130 -> 0 | E117: ='Смета в налоговую'!E130 -> компл. | F117: ='Смета в налоговую'!F130 -> 0 | G117: ='Смета в налоговую'!G130 -> 0 | H117: ='Смета в налоговую'!H130 -> 0
C118: ='Смета в налоговую'!C131 -> Укладка ламината Заказчика | D118: ='Смета в налоговую'!D131 -> 0 | E118: ='Смета в налоговую'!E131 -> компл. | F118: ='Смета в налоговую'!F131 -> 0 | G118: ='Смета в налоговую'!G131 -> 0 | H118: ='Смета в налоговую'!H131 -> 0
C119: ='Смета в налоговую'!C132 -> Монтаж обоев Заказчика | D119: ='Смета в налоговую'!D132 -> 0 | E119: ='Смета в налоговую'!E132 -> компл. | F119: ='Смета в налоговую'!F132 -> 0 | G119: ='Смета в налоговую'!G132 -> 0 | H119: ='Смета в налоговую'!H132 -> 0
B120: ='Смета в налоговую'!B133 | C120: ='Смета в налоговую'!C133 -> Натяжной потолок (белый, матовый) | D120: ='Смета в налоговую'!D133 -> 0 | E120: ='Смета в налоговую'!E133 -> м2 | F120: ='Смета в налоговую'!F133 -> 0 | G120: ='Смета в налоговую'!G133 -> 0 | H120: ='Смета в налоговую'!H133 -> 0
B121: ='Смета в налоговую'!B134 | C121: ='Смета в налоговую'!C134 -> Вагонка осина 90х12,5 - 2м | D121: ='Смета в налоговую'!D134 -> 0 | E121: ='Смета в налоговую'!E134 -> м2 | F121: ='Смета в налоговую'!F134 -> 438 | G121: ='Смета в налоговую'!G134 -> 192.72 | H121: ='Смета в налоговую'!H134 -> 0
B122: ='Смета в налоговую'!B135 | C122: ='Смета в налоговую'!C135 -> Вагонка липа 90х12,5 - 2м | D122: ='Смета в налоговую'!D135 -> 0 | E122: ='Смета в налоговую'!E135 -> м2 | F122: ='Смета в налоговую'!F135 -> 625 | G122: ='Смета в налоговую'!G135 -> 275 | H122: ='Смета в налоговую'!H135 -> 0
B123: ='Смета в налоговую'!B136 | C123: ='Смета в налоговую'!C136 -> Петли для двери на чердак | D123: ='Смета в налоговую'!D136 -> 0 | E123: ='Смета в налоговую'!E136 -> шт | F123: ='Смета в налоговую'!F136 -> 250 | G123: ='Смета в налоговую'!G136 -> 110 | H123: ='Смета в налоговую'!H136 -> 0
B124: ='Смета в налоговую'!B137 | C124: ='Смета в налоговую'!C137 -> Петли для люка | D124: ='Смета в налоговую'!D137 -> 0 | E124: ='Смета в налоговую'!E137 -> шт | F124: ='Смета в налоговую'!F137 -> 250 | G124: ='Смета в налоговую'!G137 -> 110 | H124: ='Смета в налоговую'!H137 -> 0
A125: =A94+1 -> 7 | B125: Внутренняя отделка
B126: ='Смета в налоговую'!B139 | C126: ='Смета в налоговую'!C139 -> Вагонка 90х12,5 - 6м, Сорт АВ | D126: ='Смета в налоговую'!D139 -> 0 | E126: ='Смета в налоговую'!E139 -> м2 | F126: ='Смета в налоговую'!F139 -> 275 | G126: ='Смета в налоговую'!G139 -> 121 | H126: ='Смета в налоговую'!H139 -> 0 | J126: внутр
B127: ='Смета в налоговую'!B140 | C127: ='Смета в налоговую'!C140 -> Рау-хаус 135х16- 6м, Сорт АВ | D127: ='Смета в налоговую'!D140 -> 0 | E127: ='Смета в налоговую'!E140 -> м2 | F127: ='Смета в налоговую'!F140 -> 450 | G127: ='Смета в налоговую'!G140 -> 198 | H127: ='Смета в налоговую'!H140 -> 0 | J127: внутр
B128: ='Смета в налоговую'!B141 | C128: ='Смета в налоговую'!C141 -> Рау-хаус 110х16- 6м, Сорт АВ | D128: ='Смета в налоговую'!D141 -> 0 | E128: ='Смета в налоговую'!E141 -> м2 | F128: ='Смета в налоговую'!F141 -> 450 | G128: ='Смета в налоговую'!G141 -> 198 | H128: ='Смета в налоговую'!H141 -> 0 | J128: внутр
B129: ='Смета в налоговую'!B142 | C129: ='Смета в налоговую'!C142 -> Террасная доска 112х24 - 6м, Сорт АВ | D129: ='Смета в налоговую'!D142 -> 0 | E129: ='Смета в налоговую'!E142 -> м2 | F129: ='Смета в налоговую'!F142 -> 525 | G129: ='Смета в налоговую'!G142 -> 231 | H129: ='Смета в налоговую'!H142 -> 0
B130: ='Смета в налоговую'!B143 | C130: ='Смета в налоговую'!C143 -> Калибровка 140х35- 6м | D130: ='Смета в налоговую'!D143 -> 0 | E130: ='Смета в налоговую'!E143 -> шт | F130: ='Смета в налоговую'!F143 -> 625 | G130: ='Смета в налоговую'!G143 -> 275 | H130: ='Смета в налоговую'!H143 -> 0
B131: ='Смета в налоговую'!B144 | C131: ='Смета в налоговую'!C144 -> Шпунтовка 90х26 - 6м, Сорт АВ | D131: ='Смета в налоговую'!D144 -> 0 | E131: ='Смета в налоговую'!E144 -> м2 | F131: ='Смета в налоговую'!F144 -> 525 | G131: ='Смета в налоговую'!G144 -> 231 | H131: ='Смета в налоговую'!H144 -> 0
B132: ='Смета в налоговую'!B145 | C132: ='Смета в налоговую'!C145 -> Шпунтовка 135х35 - 6м, Сорт АВ | D132: ='Смета в налоговую'!D145 -> 0 | E132: ='Смета в налоговую'!E145 -> м2 | F132: ='Смета в налоговую'!F145 -> 700 | G132: ='Смета в налоговую'!G145 -> 308 | H132: ='Смета в налоговую'!H145 -> 0
B133: ='Смета в налоговую'!B146 | C133: ='Смета в налоговую'!C146 -> ОСБ-3 9мм | D133: ='Смета в налоговую'!D146 -> 0 | E133: ='Смета в налоговую'!E146 -> шт | F133: ='Смета в налоговую'!F146 -> 813 | G133: ='Смета в налоговую'!G146 -> 357.72 | H133: ='Смета в налоговую'!H146 -> 0
B134: ='Смета в налоговую'!B147 | C134: ='Смета в налоговую'!C147 -> ОСБ-3 12мм | D134: ='Смета в налоговую'!D147 -> 0 | E134: ='Смета в налоговую'!E147 -> шт | F134: ='Смета в налоговую'!F147 -> 1063 | G134: ='Смета в налоговую'!G147 -> 467.72 | H134: ='Смета в налоговую'!H147 -> 0
B135: ='Смета в налоговую'!B148 | C135: ='Смета в налоговую'!C148 -> Фанера 12 | D135: ='Смета в налоговую'!D148 -> 0 | E135: ='Смета в налоговую'!E148 -> шт | F135: ='Смета в налоговую'!F148 -> 1088 | G135: ='Смета в налоговую'!G148 -> 478.72 | H135: ='Смета в налоговую'!H148 -> 0
B136: ='Смета в налоговую'!B149 | C136: ='Смета в налоговую'!C149 -> ЦСП 10 | D136: ='Смета в налоговую'!D149 -> 0 | E136: ='Смета в налоговую'!E149 -> шт | F136: ='Смета в налоговую'!F149 -> 1150 | G136: ='Смета в налоговую'!G149 -> 506 | H136: ='Смета в налоговую'!H149 -> 0
B137: ='Смета в налоговую'!B150 | C137: ='Смета в налоговую'!C150 -> ЦСП 12 | D137: ='Смета в налоговую'!D150 -> 0 | E137: ='Смета в налоговую'!E150 -> шт | F137: ='Смета в налоговую'!F150 -> 1438 | G137: ='Смета в налоговую'!G150 -> 632.72 | H137: ='Смета в налоговую'!H150 -> 0
B138: ='Смета в налоговую'!B151 | C138: ='Смета в налоговую'!C151 -> Гипрок Стронг 15мм | D138: ='Смета в налоговую'!D151 -> 25 | E138: ='Смета в налоговую'!E151 -> шт | F138: ='Смета в налоговую'!F151 -> 450 | G138: ='Смета в налоговую'!G151 -> 198 | H138: ='Смета в налоговую'!H151 -> 16200
B139: ='Смета в налоговую'!B152 | C139: ='Смета в налоговую'!C152 -> Гипрок Стронг Аква 15мм | D139: ='Смета в налоговую'!D152 -> 0 | E139: ='Смета в налоговую'!E152 -> шт | F139: ='Смета в налоговую'!F152 -> 488 | G139: ='Смета в налоговую'!G152 -> 214.72 | H139: ='Смета в налоговую'!H152 -> 0
B140: ='Смета в налоговую'!B153 | C140: ='Смета в налоговую'!C153 -> GTS, 9,5мм | D140: ='Смета в налоговую'!D153 -> 0 | E140: ='Смета в налоговую'!E153 -> шт | F140: ='Смета в налоговую'!F153 -> 338 | G140: ='Смета в налоговую'!G153 -> 148.72 | H140: ='Смета в налоговую'!H153 -> 0
...
